{
  "iteration": 4,
  "tasks_solved": 23,
  "tasks_total": 44,
  "total_programs_enumerated": 3150000,
  "programs_per_second": 11373.358742263237,
  "wake_time_seconds": 276.9630389213562,
  "newly_solved_this_iter": [],
  "recognition_epochs": [
    {
      "epoch": 1,
      "total_loss": 1.3504085938135784,
      "pred_loss": 0.9452860156695048,
      "struct_loss": 0.12153677344322204,
      "count_loss": 0.0,
      "n_tasks": 23
    },
    {
      "epoch": 2,
      "total_loss": 1.4195000330607097,
      "pred_loss": 0.9936500231424967,
      "struct_loss": 0.12775500297546388,
      "count_loss": 0.0,
      "n_tasks": 23
    },
    {
      "epoch": 3,
      "total_loss": 1.352173646291097,
      "pred_loss": 0.9465215524037678,
      "struct_loss": 0.12169562816619872,
      "count_loss": 0.0,
      "n_tasks": 23
    },
    {
      "epoch": 4,
      "total_loss": 1.3625563780466716,
      "pred_loss": 0.9537894646326701,
      "struct_loss": 0.12263007402420043,
      "count_loss": 0.0,
      "n_tasks": 23
    },
    {
      "epoch": 5,
      "total_loss": 1.2590079704920452,
      "pred_loss": 0.8813055793444315,
      "struct_loss": 0.11331071734428406,
      "count_loss": 0.0,
      "n_tasks": 23
    }
  ],
  "final_recognition_loss": 1.2590079704920452,
  "recognition_time_seconds": 0.2562901973724365,
  "task_predictions": [
    {
      "task_name": "poker_has_pair",
      "top_5_primitives": [
        [
          "#((\u03bb (\u03bb (\u03bb (\u03bb (\u03bb $1 ($2 $3) $4))))))",
          0.9999977350234985
        ],
        [
          "#((\u03bb (\u03bb (\u03bb lt $1 $2))))",
          0.9950762391090393
        ],
        [
          "#((\u03bb (\u03bb (\u03bb (\u03bb (\u03bb (\u03bb $1 ($2 $3 $4) $5)))))))",
          0.9891597628593445
        ],
        [
          "filter",
          0.9846749305725098
        ],
        [
          "drop",
          0.9723331928253174
        ]
      ],
      "prediction_entropy": 13.633833885192871,
      "predicted_count": 3.3074004650115967
    },
    {
      "task_name": "poker_three_of_kind",
      "top_5_primitives": [
        [
          "any",
          0.9975695013999939
        ],
        [
          "second_half",
          0.9900233149528503
        ],
        [
          "#((\u03bb (\u03bb (\u03bb (\u03bb (\u03bb (\u03bb $1 ($2 $3 $4) $5)))))))",
          0.9895159006118774
        ],
        [
          "zip_with",
          0.9878121018409729
        ],
        [
          "n_unique_suits",
          0.983278214931488
        ]
      ],
      "prediction_entropy": 14.363340377807617,
      "predicted_count": 0.2297717183828354
    },
    {
      "task_name": "poker_flush",
      "top_5_primitives": [
        [
          "HEARTS",
          0.9856471419334412
        ],
        [
          "2",
          0.9837279319763184
        ],
        [
          "#((\u03bb (\u03bb (\u03bb (\u03bb (\u03bb $1 ($2 $3) $4))))))",
          0.979473888874054
        ],
        [
          "second_half",
          0.974431037902832
        ],
        [
          "-",
          0.9736721515655518
        ]
      ],
      "prediction_entropy": 13.315176010131836,
      "predicted_count": 0.15295134484767914
    },
    {
      "task_name": "poker_same_color",
      "top_5_primitives": [
        [
          "#((\u03bb (\u03bb (\u03bb lt $1 $2))))",
          0.9935477375984192
        ],
        [
          "max_rank",
          0.9348915219306946
        ],
        [
          "#((\u03bb (\u03bb (\u03bb (\u03bb lt ($1 $2) $3)))))",
          0.9110366702079773
        ],
        [
          "-",
          0.9021064043045044
        ],
        [
          "head",
          0.8964722156524658
        ]
      ],
      "prediction_entropy": 17.31447982788086,
      "predicted_count": 0.44433045387268066
    },
    {
      "task_name": "poker_two_suits",
      "top_5_primitives": [
        [
          "any",
          0.9696689248085022
        ],
        [
          "length",
          0.9625062942504883
        ],
        [
          "#((\u03bb (\u03bb (\u03bb lt $1 $2))))",
          0.9520657062530518
        ],
        [
          "le",
          0.9160647392272949
        ],
        [
          "HEARTS",
          0.8972856998443604
        ]
      ],
      "prediction_entropy": 16.21708106994629,
      "predicted_count": 1.3400298357009888
    },
    {
      "task_name": "poker_straight",
      "top_5_primitives": [
        [
          "any",
          0.998607337474823
        ],
        [
          "#((\u03bb (\u03bb (\u03bb (\u03bb (\u03bb $1 ($2 $3) $4))))))",
          0.9984844326972961
        ],
        [
          "#((\u03bb (\u03bb (\u03bb (\u03bb lt ($1 $2) $3)))))",
          0.9968397617340088
        ],
        [
          "second_half",
          0.995244562625885
        ],
        [
          "count_suit",
          0.9783072471618652
        ]
      ],
      "prediction_entropy": 14.946646690368652,
      "predicted_count": 1.4247921705245972
    },
    {
      "task_name": "bj_sum_even",
      "top_5_primitives": [
        [
          "#((\u03bb (\u03bb (\u03bb lt $1 $2))))",
          0.9951889514923096
        ],
        [
          "#((\u03bb (\u03bb (\u03bb (\u03bb $1 ($2 $0) $3)))))",
          0.991600513458252
        ],
        [
          "#((\u03bb (\u03bb (\u03bb (\u03bb (\u03bb $1 ($2 $3) $4))))))",
          0.9845440983772278
        ],
        [
          "any",
          0.9817299842834473
        ],
        [
          "second_half",
          0.9745060801506042
        ]
      ],
      "prediction_entropy": 13.662479400634766,
      "predicted_count": 4.922989368438721
    },
    {
      "task_name": "bj_sum_odd",
      "top_5_primitives": [
        [
          "#((\u03bb (\u03bb (\u03bb lt $1 $2))))",
          0.9998377561569214
        ],
        [
          "#((\u03bb (\u03bb (\u03bb (\u03bb lt ($1 $2) $3)))))",
          0.9988648891448975
        ],
        [
          "RED",
          0.9507767558097839
        ],
        [
          "max_rank",
          0.8783310651779175
        ],
        [
          "map",
          0.871703565120697
        ]
      ],
      "prediction_entropy": 16.6370849609375,
      "predicted_count": 4.075242042541504
    },
    {
      "task_name": "rummy_run_3",
      "top_5_primitives": [
        [
          "#((\u03bb (\u03bb (\u03bb lt $1 $2))))",
          0.999467670917511
        ],
        [
          "last",
          0.9667518138885498
        ],
        [
          "length",
          0.9616520404815674
        ],
        [
          "not",
          0.930310070514679
        ],
        [
          "any",
          0.9205644726753235
        ]
      ],
      "prediction_entropy": 18.423049926757812,
      "predicted_count": 1.7791668176651
    },
    {
      "task_name": "rummy_set_3",
      "top_5_primitives": [
        [
          "#((\u03bb (\u03bb (\u03bb (\u03bb (\u03bb $1 ($2 $3) $4))))))",
          1.0
        ],
        [
          "second_half",
          0.9999411106109619
        ],
        [
          "sum_ranks",
          0.9997377991676331
        ],
        [
          "count_suit",
          0.9955376386642456
        ],
        [
          "any",
          0.9924923777580261
        ]
      ],
      "prediction_entropy": 9.351873397827148,
      "predicted_count": -2.6936094760894775
    },
    {
      "task_name": "rummy_all_different",
      "top_5_primitives": [
        [
          "#((\u03bb (\u03bb (\u03bb (\u03bb (\u03bb $1 ($2 $3) $4))))))",
          0.9888793230056763
        ],
        [
          "any",
          0.9688798189163208
        ],
        [
          "#((\u03bb (\u03bb (\u03bb gt $1 $2))))",
          0.9505326151847839
        ],
        [
          "#((\u03bb (\u03bb (\u03bb (\u03bb lt ($1 $2) $3)))))",
          0.9342048168182373
        ],
        [
          "max_rank",
          0.9251857399940491
        ]
      ],
      "prediction_entropy": 18.393342971801758,
      "predicted_count": 2.376809597015381
    },
    {
      "task_name": "rummy_three_ranks",
      "top_5_primitives": [
        [
          "#((\u03bb (\u03bb (\u03bb lt $1 $2))))",
          0.9984408020973206
        ],
        [
          "#((\u03bb (\u03bb (\u03bb (\u03bb (\u03bb (\u03bb $1 ($2 $3 $4) $5)))))))",
          0.9975882768630981
        ],
        [
          "map",
          0.9655560255050659
        ],
        [
          "HEARTS",
          0.9636222124099731
        ],
        [
          "max_rank",
          0.9485378861427307
        ]
      ],
      "prediction_entropy": 16.883447647094727,
      "predicted_count": 4.8993706703186035
    },
    {
      "task_name": "sol_alternating",
      "top_5_primitives": [
        [
          "#((\u03bb (\u03bb (\u03bb (\u03bb (\u03bb (\u03bb $1 ($2 $3 $4) $5)))))))",
          0.9999926090240479
        ],
        [
          "#((\u03bb (\u03bb (\u03bb lt $1 $2))))",
          0.999947190284729
        ],
        [
          "#((\u03bb (\u03bb (\u03bb (\u03bb (\u03bb $1 ($2 ($3 $0)) $4))))))",
          0.9938994646072388
        ],
        [
          "max_rank",
          0.9861193895339966
        ],
        [
          "RED",
          0.9776589274406433
        ]
      ],
      "prediction_entropy": 14.714587211608887,
      "predicted_count": 2.55660080909729
    },
    {
      "task_name": "sol_v_shape",
      "top_5_primitives": [
        [
          "#((\u03bb (\u03bb (\u03bb (\u03bb (\u03bb $1 ($2 $3) $4))))))",
          0.9997602105140686
        ],
        [
          "any",
          0.9994795918464661
        ],
        [
          "#((\u03bb (\u03bb (\u03bb (\u03bb lt ($1 $2) $3)))))",
          0.9983062744140625
        ],
        [
          "#((\u03bb (\u03bb (\u03bb (\u03bb (\u03bb (\u03bb $1 ($2 $3 $4) $5)))))))",
          0.9969093203544617
        ],
        [
          "#((\u03bb (\u03bb (\u03bb gt $1 $2))))",
          0.9940037131309509
        ]
      ],
      "prediction_entropy": 14.562491416931152,
      "predicted_count": 4.2773518562316895
    },
    {
      "task_name": "sol_ascending",
      "top_5_primitives": [
        [
          "#((\u03bb (\u03bb (\u03bb (\u03bb (\u03bb (\u03bb $1 ($2 $3 $4) $5)))))))",
          0.9999425411224365
        ],
        [
          "max_rank",
          0.9993658661842346
        ],
        [
          "#((\u03bb (\u03bb (\u03bb (\u03bb (\u03bb $1 ($2 ($3 $0)) $4))))))",
          0.9990390539169312
        ],
        [
          "if",
          0.9987515211105347
        ],
        [
          "second_half",
          0.9985055923461914
        ]
      ],
      "prediction_entropy": 11.000556945800781,
      "predicted_count": 5.87904691696167
    },
    {
      "task_name": "sol_sorted",
      "top_5_primitives": [
        [
          "#((\u03bb (\u03bb (\u03bb (\u03bb (\u03bb (\u03bb $1 ($2 $3 $4) $5)))))))",
          0.9995781779289246
        ],
        [
          "get_suit",
          0.9993879795074463
        ],
        [
          "HEARTS",
          0.9958912134170532
        ],
        [
          "second_half",
          0.9920313358306885
        ],
        [
          "and",
          0.9901110529899597
        ]
      ],
      "prediction_entropy": 13.421710014343262,
      "predicted_count": 3.6221563816070557
    },
    {
      "task_name": "sol_same_suit_seq",
      "top_5_primitives": [
        [
          "#((\u03bb (\u03bb (\u03bb lt $1 $2))))",
          0.9967999458312988
        ],
        [
          "any",
          0.9935075044631958
        ],
        [
          "length",
          0.9753417372703552
        ],
        [
          "sum_ranks",
          0.9170289039611816
        ],
        [
          "#((\u03bb (\u03bb (\u03bb gt $1 $2))))",
          0.9163671135902405
        ]
      ],
      "prediction_entropy": 15.7618989944458,
      "predicted_count": 1.105117678642273
    },
    {
      "task_name": "simple_first_red",
      "top_5_primitives": [
        [
          "#((\u03bb (\u03bb (\u03bb (\u03bb (\u03bb $1 ($2 $3) $4))))))",
          0.9962021708488464
        ],
        [
          "HEARTS",
          0.9948882460594177
        ],
        [
          "#((\u03bb (\u03bb (\u03bb lt $1 $2))))",
          0.9923415184020996
        ],
        [
          "#((\u03bb (\u03bb (\u03bb (\u03bb (\u03bb (\u03bb $1 ($2 $3 $4) $5)))))))",
          0.9797973036766052
        ],
        [
          "length",
          0.9707360863685608
        ]
      ],
      "prediction_entropy": 12.855928421020508,
      "predicted_count": 2.2496836185455322
    },
    {
      "task_name": "simple_last_black",
      "top_5_primitives": [
        [
          "#((\u03bb (\u03bb (\u03bb (\u03bb (\u03bb $1 ($2 $3) $4))))))",
          0.9970917701721191
        ],
        [
          "sum_ranks",
          0.9788359999656677
        ],
        [
          "head",
          0.9757058024406433
        ],
        [
          "get_color",
          0.9748470783233643
        ],
        [
          "2",
          0.9549703001976013
        ]
      ],
      "prediction_entropy": 16.038318634033203,
      "predicted_count": 4.641831874847412
    },
    {
      "task_name": "simple_ends_suit",
      "top_5_primitives": [
        [
          "#((\u03bb (\u03bb (\u03bb (\u03bb (\u03bb (\u03bb $1 ($2 $3 $4) $5)))))))",
          0.9962460398674011
        ],
        [
          "#((\u03bb (\u03bb (\u03bb lt $1 $2))))",
          0.9960839748382568
        ],
        [
          "rank_val",
          0.9763760566711426
        ],
        [
          "max_rank",
          0.9725454449653625
        ],
        [
          "RED",
          0.9491521716117859
        ]
      ],
      "prediction_entropy": 15.236095428466797,
      "predicted_count": 3.470212459564209
    },
    {
      "task_name": "simple_ends_color",
      "top_5_primitives": [
        [
          "#((\u03bb (\u03bb (\u03bb (\u03bb $1 ($2 ($3 $0)))))))",
          0.9954277276992798
        ],
        [
          "any",
          0.993794322013855
        ],
        [
          "all_same_color",
          0.9791845083236694
        ],
        [
          "sum_ranks",
          0.967979371547699
        ],
        [
          "second_half",
          0.9493930339813232
        ]
      ],
      "prediction_entropy": 17.596364974975586,
      "predicted_count": 3.7789547443389893
    },
    {
      "task_name": "simple_ends_rank",
      "top_5_primitives": [
        [
          "#((\u03bb (\u03bb (\u03bb (\u03bb (\u03bb $1 ($2 $3) $4))))))",
          0.9987908005714417
        ],
        [
          "HEARTS",
          0.9889273643493652
        ],
        [
          "#((\u03bb (\u03bb (\u03bb (\u03bb (\u03bb (\u03bb $1 ($2 $3 $4) $5)))))))",
          0.9792329668998718
        ],
        [
          "2",
          0.9711110591888428
        ],
        [
          "#((\u03bb (\u03bb (\u03bb (\u03bb lt ($1 $2) $3)))))",
          0.9085631370544434
        ]
      ],
      "prediction_entropy": 15.879851341247559,
      "predicted_count": 3.7020649909973145
    },
    {
      "task_name": "simple_has_spade",
      "top_5_primitives": [
        [
          "any",
          0.9513493776321411
        ],
        [
          "sum_ranks",
          0.9450289607048035
        ],
        [
          "#((\u03bb (\u03bb (\u03bb (\u03bb $1 ($2 ($3 $0)))))))",
          0.9129499793052673
        ],
        [
          "n_unique_suits",
          0.9028704166412354
        ],
        [
          "#((\u03bb (\u03bb (\u03bb gt $1 $2))))",
          0.898785412311554
        ]
      ],
      "prediction_entropy": 17.815698623657227,
      "predicted_count": 1.8411308526992798
    },
    {
      "task_name": "simple_has_heart",
      "top_5_primitives": [
        [
          "#((\u03bb (\u03bb (\u03bb lt $1 $2))))",
          0.9768658876419067
        ],
        [
          "last",
          0.9427095651626587
        ],
        [
          "#((\u03bb (\u03bb (\u03bb (\u03bb (\u03bb $1 ($2 $3) $4))))))",
          0.8801993727684021
        ],
        [
          "n_unique_suits",
          0.8222895860671997
        ],
        [
          "BLACK",
          0.8138896822929382
        ]
      ],
      "prediction_entropy": 20.77277946472168,
      "predicted_count": 2.006837844848633
    },
    {
      "task_name": "simple_all_even",
      "top_5_primitives": [
        [
          "#((\u03bb (\u03bb (\u03bb (\u03bb (\u03bb $1 ($2 $3) $4))))))",
          1.0
        ],
        [
          "-",
          0.9999598264694214
        ],
        [
          "#((\u03bb (\u03bb (\u03bb (\u03bb lt ($1 $2) $3)))))",
          0.9999520778656006
        ],
        [
          "any",
          0.9951673746109009
        ],
        [
          "head",
          0.9897353649139404
        ]
      ],
      "prediction_entropy": 9.750341415405273,
      "predicted_count": 2.7200562953948975
    },
    {
      "task_name": "simple_all_odd",
      "top_5_primitives": [
        [
          "#((\u03bb (\u03bb (\u03bb $1 $2))))",
          0.9999207258224487
        ],
        [
          "sum_ranks",
          0.9991661310195923
        ],
        [
          "any",
          0.9972379207611084
        ],
        [
          "#((\u03bb (\u03bb (\u03bb lt $1 $2))))",
          0.9971319437026978
        ],
        [
          "true",
          0.993640124797821
        ]
      ],
      "prediction_entropy": 13.601122856140137,
      "predicted_count": 2.760432004928589
    },
    {
      "task_name": "simple_diverse_ranks",
      "top_5_primitives": [
        [
          "max_rank",
          0.9644548892974854
        ],
        [
          "#((\u03bb (\u03bb (\u03bb (\u03bb lt ($1 $2) $3)))))",
          0.9341365694999695
        ],
        [
          "mod",
          0.9327371716499329
        ],
        [
          "sum_ranks",
          0.896824061870575
        ],
        [
          "HEARTS",
          0.8952432870864868
        ]
      ],
      "prediction_entropy": 16.668821334838867,
      "predicted_count": 2.823817729949951
    },
    {
      "task_name": "simple_two_suits",
      "top_5_primitives": [
        [
          "#((\u03bb (\u03bb (\u03bb lt $1 $2))))",
          0.9426909685134888
        ],
        [
          "#((\u03bb (\u03bb (\u03bb (\u03bb lt ($1 $2) $3)))))",
          0.933568000793457
        ],
        [
          "HEARTS",
          0.921678900718689
        ],
        [
          "RED",
          0.9024423956871033
        ],
        [
          "last",
          0.8955419063568115
        ]
      ],
      "prediction_entropy": 18.875560760498047,
      "predicted_count": 3.0784645080566406
    },
    {
      "task_name": "sym_suits_palindrome",
      "top_5_primitives": [
        [
          "#((\u03bb (\u03bb (\u03bb (\u03bb (\u03bb $1 ($2 $3) $4))))))",
          0.9999884366989136
        ],
        [
          "second_half",
          0.9988824725151062
        ],
        [
          "HEARTS",
          0.9967920184135437
        ],
        [
          "rank_val",
          0.9951866269111633
        ],
        [
          "#((\u03bb (\u03bb (\u03bb lt $1 $2))))",
          0.9876964688301086
        ]
      ],
      "prediction_entropy": 13.08560848236084,
      "predicted_count": 1.1809090375900269
    },
    {
      "task_name": "sym_periodic_colors",
      "top_5_primitives": [
        [
          "sum_ranks",
          0.9999562501907349
        ],
        [
          "second_half",
          0.9991557598114014
        ],
        [
          "#((\u03bb (\u03bb (\u03bb (\u03bb (\u03bb $1 ($2 $3) $4))))))",
          0.9983512163162231
        ],
        [
          "5",
          0.996058464050293
        ],
        [
          "get_rank",
          0.995902955532074
        ]
      ],
      "prediction_entropy": 11.515135765075684,
      "predicted_count": 1.0665396451950073
    },
    {
      "task_name": "sym_ranks_palindrome",
      "top_5_primitives": [
        [
          "#((\u03bb (\u03bb (\u03bb lt $1 $2))))",
          0.9999995231628418
        ],
        [
          "rank_val",
          0.9932438731193542
        ],
        [
          "second_half",
          0.9740906953811646
        ],
        [
          "HEARTS",
          0.962531566619873
        ],
        [
          "sum_ranks",
          0.9612486362457275
        ]
      ],
      "prediction_entropy": 13.694957733154297,
      "predicted_count": 1.1251827478408813
    },
    {
      "task_name": "sym_halves_suits",
      "top_5_primitives": [
        [
          "#((\u03bb (\u03bb (\u03bb (\u03bb (\u03bb (\u03bb $1 ($2 $3 $4) $5)))))))",
          0.9999998807907104
        ],
        [
          "#((\u03bb (\u03bb (\u03bb lt $1 $2))))",
          0.9973059892654419
        ],
        [
          "max_rank",
          0.9886960983276367
        ],
        [
          "#((\u03bb (\u03bb (\u03bb (\u03bb (\u03bb $1 ($2 ($3 $0)) $4))))))",
          0.984519362449646
        ],
        [
          "map",
          0.9835360050201416
        ]
      ],
      "prediction_entropy": 11.688872337341309,
      "predicted_count": 5.075263023376465
    },
    {
      "task_name": "count_two_red",
      "top_5_primitives": [
        [
          "#((\u03bb (\u03bb (\u03bb lt $1 $2))))",
          0.999784529209137
        ],
        [
          "get_color",
          0.9956943988800049
        ],
        [
          "#((\u03bb (\u03bb (\u03bb (\u03bb (\u03bb (\u03bb $1 ($2 $3 $4) $5)))))))",
          0.9942077398300171
        ],
        [
          "filter",
          0.9926000833511353
        ],
        [
          "max_rank",
          0.9889378547668457
        ]
      ],
      "prediction_entropy": 11.817510604858398,
      "predicted_count": 3.854624032974243
    },
    {
      "task_name": "count_more_red",
      "top_5_primitives": [
        [
          "#((\u03bb (\u03bb (\u03bb (\u03bb $1 ($2 $0) $3)))))",
          0.9925406575202942
        ],
        [
          "#((\u03bb (\u03bb (\u03bb (\u03bb lt ($1 $2) $3)))))",
          0.9782727956771851
        ],
        [
          "any",
          0.9702803492546082
        ],
        [
          "#((\u03bb (\u03bb (\u03bb lt $1 $2))))",
          0.963760256767273
        ],
        [
          "length",
          0.9282419681549072
        ]
      ],
      "prediction_entropy": 15.755132675170898,
      "predicted_count": 3.1653928756713867
    },
    {
      "task_name": "count_three_suit",
      "top_5_primitives": [
        [
          "any",
          0.9964573979377747
        ],
        [
          "n_unique_suits",
          0.9956395626068115
        ],
        [
          "max_rank",
          0.994878888130188
        ],
        [
          "second_half",
          0.9936959147453308
        ],
        [
          "#((\u03bb (\u03bb (\u03bb (\u03bb lt ($1 $2) $3)))))",
          0.9910707473754883
        ]
      ],
      "prediction_entropy": 12.437348365783691,
      "predicted_count": 1.6736823320388794
    },
    {
      "task_name": "count_majority_color",
      "top_5_primitives": [
        [
          "#((\u03bb (\u03bb (\u03bb (\u03bb (\u03bb $1 ($2 $3) $4))))))",
          0.9998304843902588
        ],
        [
          "HEARTS",
          0.9976409673690796
        ],
        [
          "second_half",
          0.9935802221298218
        ],
        [
          "any",
          0.9906104207038879
        ],
        [
          "get_color",
          0.9897210001945496
        ]
      ],
      "prediction_entropy": 15.113994598388672,
      "predicted_count": 6.202844619750977
    },
    {
      "task_name": "comp_left_half_uniform_color",
      "top_5_primitives": [
        [
          "second_half",
          0.999901294708252
        ],
        [
          "sum_ranks",
          0.9998948574066162
        ],
        [
          "any",
          0.9948006868362427
        ],
        [
          "CLUBS",
          0.9938070178031921
        ],
        [
          "get_color",
          0.9932976365089417
        ]
      ],
      "prediction_entropy": 11.447827339172363,
      "predicted_count": 1.2396208047866821
    },
    {
      "task_name": "comp_right_half_has_pair",
      "top_5_primitives": [
        [
          "#((\u03bb (\u03bb (\u03bb lt $1 $2))))",
          0.9968902468681335
        ],
        [
          "#((\u03bb (\u03bb (\u03bb (\u03bb (\u03bb $1 ($2 $3) $4))))))",
          0.9824575781822205
        ],
        [
          "#((\u03bb (\u03bb (\u03bb (\u03bb (\u03bb (\u03bb $1 ($2 $3 $4) $5)))))))",
          0.9691269993782043
        ],
        [
          "last",
          0.9567363858222961
        ],
        [
          "1",
          0.9525741338729858
        ]
      ],
      "prediction_entropy": 16.173851013183594,
      "predicted_count": 4.744033336639404
    },
    {
      "task_name": "comp_skip1_same_color",
      "top_5_primitives": [
        [
          "second_half",
          0.9991782307624817
        ],
        [
          "rank_val",
          0.9985010623931885
        ],
        [
          "-",
          0.9982335567474365
        ],
        [
          "sum_ranks",
          0.9978598952293396
        ],
        [
          "#((\u03bb (\u03bb (\u03bb (\u03bb (\u03bb $1 ($2 $3) $4))))))",
          0.9907174706459045
        ]
      ],
      "prediction_entropy": 10.495211601257324,
      "predicted_count": 0.2869004011154175
    },
    {
      "task_name": "comp_shift2_color",
      "top_5_primitives": [
        [
          "second_half",
          0.9920390844345093
        ],
        [
          "last",
          0.9515807628631592
        ],
        [
          "max_rank",
          0.9475830793380737
        ],
        [
          "any",
          0.9347084164619446
        ],
        [
          "map",
          0.8777503967285156
        ]
      ],
      "prediction_entropy": 17.480165481567383,
      "predicted_count": 1.579651117324829
    },
    {
      "task_name": "comp_first_two_same_suit",
      "top_5_primitives": [
        [
          "#((\u03bb (\u03bb (\u03bb lt $1 $2))))",
          0.9999518394470215
        ],
        [
          "last",
          0.960077166557312
        ],
        [
          "length",
          0.9367812275886536
        ],
        [
          "HEARTS",
          0.9128655195236206
        ],
        [
          "eq",
          0.8444395065307617
        ]
      ],
      "prediction_entropy": 17.941295623779297,
      "predicted_count": 2.5594472885131836
    },
    {
      "task_name": "comp_last_two_same_color",
      "top_5_primitives": [
        [
          "any",
          0.9990817308425903
        ],
        [
          "second_half",
          0.9875259399414062
        ],
        [
          "sum_ranks",
          0.9518772959709167
        ],
        [
          "last",
          0.943688690662384
        ],
        [
          "all_same_color",
          0.9246674180030823
        ]
      ],
      "prediction_entropy": 15.720540046691895,
      "predicted_count": 1.456876277923584
    },
    {
      "task_name": "comp_binary_suit_alt",
      "top_5_primitives": [
        [
          "#((\u03bb (\u03bb (\u03bb (\u03bb lt ($1 $2) $3)))))",
          0.9999983310699463
        ],
        [
          "#((\u03bb (\u03bb (\u03bb (\u03bb (\u03bb $1 ($2 $3) $4))))))",
          0.9999953508377075
        ],
        [
          "at",
          0.999481737613678
        ],
        [
          "n_unique_colors",
          0.9987956285476685
        ],
        [
          "zip_with",
          0.9974762797355652
        ]
      ],
      "prediction_entropy": 10.922274589538574,
      "predicted_count": 2.467836618423462
    },
    {
      "task_name": "comp_color_pairs",
      "top_5_primitives": [
        [
          "get_rank",
          0.9906666874885559
        ],
        [
          "map",
          0.9889881014823914
        ],
        [
          "second_half",
          0.987798810005188
        ],
        [
          "head",
          0.9767159819602966
        ],
        [
          "count_suit",
          0.962924599647522
        ]
      ],
      "prediction_entropy": 15.488236427307129,
      "predicted_count": 3.4762256145477295
    }
  ],
  "mean_prediction_entropy": 14.737997055053711,
  "prediction_entropy_std": 2.634871006011963,
  "new_abstractions": [
    {
      "iteration": 4,
      "abstraction_name": "#((\u03bb (\u03bb (\u03bb lt $1 $2))))",
      "abstraction_body": "(\u03bb (\u03bb (\u03bb lt $1 $2)))",
      "size": 8,
      "estimated_savings": 0.0
    },
    {
      "iteration": 4,
      "abstraction_name": "#((\u03bb (\u03bb (\u03bb (\u03bb lt ($1 $2) $3)))))",
      "abstraction_body": "(\u03bb (\u03bb (\u03bb (\u03bb lt ($1 $2) $3))))",
      "size": 11,
      "estimated_savings": 0.0
    },
    {
      "iteration": 4,
      "abstraction_name": "#((\u03bb (\u03bb (\u03bb gt $1 $2))))",
      "abstraction_body": "(\u03bb (\u03bb (\u03bb gt $1 $2)))",
      "size": 8,
      "estimated_savings": 0.0
    }
  ],
  "compression_time_seconds": 0.017153024673461914,
  "grammar_size": 71,
  "dream_log": {
    "iteration": 4,
    "n_standard_dreams": 2,
    "n_contrastive_dreams": 0,
    "avg_examples_per_dream": 10.0,
    "sample_dream_programs": [
      "(\u03bb true)",
      "(\u03bb false)"
    ]
  },
  "dream_time_seconds": 0.39314794540405273,
  "model_checkpoint_path": "results_overnight_wakesleep/study_20260101_200112/baseline_full_library/checkpoints/model_iter_04.pt"
}