{
  "summary": {
    "rule_id": "four_of_a_kind_adjacent",
    "total_visits": 400004,
    "n_distinct_programs": 318,
    "n_mapped": 154,
    "n_unmapped": 164,
    "n_parse_fail": 0,
    "mass_mapped_frac": 0.6915480845191548,
    "mass_unmapped_frac": 0.3084519154808452,
    "mass_parse_fail_frac": 0.0,
    "attribution_depth_first_mass_frac": {
      "C": 0.2982520174798252,
      "C_residual": 0.008794912050879492,
      "B": 0.0014049859501404987
    },
    "attribution_pruner_first_mass_frac": {
      "C": 0.2969470305296947,
      "C_residual": 0.008794912050879492,
      "B": 0.0014049859501404987,
      "D": 0.0013049869501304988
    },
    "cooccurrence_mass_frac": {
      "depth>6": 0.2969470305296947,
      "d6_eligible_but_unmapped": 0.008794912050879492,
      "type_fail": 0.0014049859501404987,
      "depth>6+pruner_rejected": 0.0013049869501304988
    },
    "max_list_chain": 2,
    "d7_pool_provided": true
  },
  "unmapped_predicates": [
    {
      "prog_str": "(\u03bb has_color (drop (sum_ranks $0) (second_half $0)) BLACK)",
      "visit_count": 6,
      "visit_mass": 1.4999850001499985e-05,
      "parse_ok": true,
      "type_ok": true,
      "pruner_ok": true,
      "depth": 7,
      "size": 14,
      "in_d6_pool_hypothetical": false,
      "in_d7_pool_hypothetical": true,
      "in_d7_pool_actual": false,
      "fingerprint": "0841ea62d9232a98182d4125fc05cc900721f0b303549d552a96bd99a451c447",
      "canonical_type": "list(card) -> bool",
      "mapped": false,
      "unmapped_reason": "fp_not_in_pool"
    },
    {
      "prog_str": "(\u03bb has_color (drop (n_repeated_ranks (last (adjacent_pairs (sort_by_rank $0)))) (second_half $0)) BLACK)",
      "visit_count": 2,
      "visit_mass": 4.999950000499995e-06,
      "parse_ok": true,
      "type_ok": true,
      "pruner_ok": true,
      "depth": 10,
      "size": 20,
      "in_d6_pool_hypothetical": false,
      "in_d7_pool_hypothetical": false,
      "in_d7_pool_actual": false,
      "fingerprint": "1a56e62ae445b879586903c3a121ac151828c4e78e0b816cb433ae28fdb41de0",
      "canonical_type": "list(card) -> bool",
      "mapped": false,
      "unmapped_reason": "fp_not_in_pool"
    },
    {
      "prog_str": "(\u03bb gt 5 (n_repeated_ranks $0))",
      "visit_count": 116,
      "visit_mass": 0.0002899971000289997,
      "parse_ok": true,
      "type_ok": true,
      "pruner_ok": true,
      "depth": 4,
      "size": 8,
      "in_d6_pool_hypothetical": true,
      "in_d7_pool_hypothetical": true,
      "in_d7_pool_actual": false,
      "fingerprint": "4ec297ba99da804fe1068f1a398d0de8c7ed84461f2efbfd59557f1f5c94ab96",
      "canonical_type": "list(card) -> bool",
      "mapped": false,
      "unmapped_reason": "fp_not_in_pool"
    },
    {
      "prog_str": "(\u03bb gt 5 (n_repeated_suits $0))",
      "visit_count": 288,
      "visit_mass": 0.0007199928000719992,
      "parse_ok": true,
      "type_ok": true,
      "pruner_ok": true,
      "depth": 4,
      "size": 8,
      "in_d6_pool_hypothetical": true,
      "in_d7_pool_hypothetical": true,
      "in_d7_pool_actual": false,
      "fingerprint": "4ec297ba99da804fe1068f1a398d0de8c7ed84461f2efbfd59557f1f5c94ab96",
      "canonical_type": "list(card) -> bool",
      "mapped": false,
      "unmapped_reason": "fp_not_in_pool"
    },
    {
      "prog_str": "(\u03bb gt 4 (n_repeated_suits $0))",
      "visit_count": 184,
      "visit_mass": 0.0004599954000459995,
      "parse_ok": true,
      "type_ok": true,
      "pruner_ok": true,
      "depth": 4,
      "size": 8,
      "in_d6_pool_hypothetical": true,
      "in_d7_pool_hypothetical": true,
      "in_d7_pool_actual": false,
      "fingerprint": "4ec297ba99da804fe1068f1a398d0de8c7ed84461f2efbfd59557f1f5c94ab96",
      "canonical_type": "list(card) -> bool",
      "mapped": false,
      "unmapped_reason": "fp_not_in_pool"
    },
    {
      "prog_str": "(\u03bb gt 3 (n_unique_colors $0))",
      "visit_count": 160,
      "visit_mass": 0.0003999960000399996,
      "parse_ok": true,
      "type_ok": true,
      "pruner_ok": true,
      "depth": 4,
      "size": 8,
      "in_d6_pool_hypothetical": true,
      "in_d7_pool_hypothetical": true,
      "in_d7_pool_actual": false,
      "fingerprint": "4ec297ba99da804fe1068f1a398d0de8c7ed84461f2efbfd59557f1f5c94ab96",
      "canonical_type": "list(card) -> bool",
      "mapped": false,
      "unmapped_reason": "fp_not_in_pool"
    },
    {
      "prog_str": "(\u03bb gt 3 (n_unique_colors (sort_by_rank $0)))",
      "visit_count": 4,
      "visit_mass": 9.99990000099999e-06,
      "parse_ok": true,
      "type_ok": true,
      "pruner_ok": true,
      "depth": 5,
      "size": 10,
      "in_d6_pool_hypothetical": true,
      "in_d7_pool_hypothetical": true,
      "in_d7_pool_actual": false,
      "fingerprint": "4ec297ba99da804fe1068f1a398d0de8c7ed84461f2efbfd59557f1f5c94ab96",
      "canonical_type": "list(card) -> bool",
      "mapped": false,
      "unmapped_reason": "fp_not_in_pool"
    },
    {
      "prog_str": "(\u03bb gt 4 (n_unique_colors (sort_by_rank $0)))",
      "visit_count": 28,
      "visit_mass": 6.999930000699993e-05,
      "parse_ok": true,
      "type_ok": true,
      "pruner_ok": true,
      "depth": 5,
      "size": 10,
      "in_d6_pool_hypothetical": true,
      "in_d7_pool_hypothetical": true,
      "in_d7_pool_actual": false,
      "fingerprint": "4ec297ba99da804fe1068f1a398d0de8c7ed84461f2efbfd59557f1f5c94ab96",
      "canonical_type": "list(card) -> bool",
      "mapped": false,
      "unmapped_reason": "fp_not_in_pool"
    },
    {
      "prog_str": "(\u03bb gt 5 (n_unique_colors (sort_by_rank $0)))",
      "visit_count": 38,
      "visit_mass": 9.499905000949991e-05,
      "parse_ok": true,
      "type_ok": true,
      "pruner_ok": true,
      "depth": 5,
      "size": 10,
      "in_d6_pool_hypothetical": true,
      "in_d7_pool_hypothetical": true,
      "in_d7_pool_actual": false,
      "fingerprint": "4ec297ba99da804fe1068f1a398d0de8c7ed84461f2efbfd59557f1f5c94ab96",
      "canonical_type": "list(card) -> bool",
      "mapped": false,
      "unmapped_reason": "fp_not_in_pool"
    },
    {
      "prog_str": "(\u03bb eq $0 $0)",
      "visit_count": 8,
      "visit_mass": 1.999980000199998e-05,
      "parse_ok": true,
      "type_ok": false,
      "pruner_ok": true,
      "depth": 4,
      "size": 6,
      "in_d6_pool_hypothetical": false,
      "in_d7_pool_hypothetical": false,
      "in_d7_pool_actual": null,
      "fingerprint": null,
      "canonical_type": "'a -> bool",
      "mapped": false,
      "unmapped_reason": "fp_not_in_pool"
    },
    {
      "prog_str": "(\u03bb ge (sum_ranks $0) 3)",
      "visit_count": 23,
      "visit_mass": 5.749942500574994e-05,
      "parse_ok": true,
      "type_ok": true,
      "pruner_ok": true,
      "depth": 5,
      "size": 8,
      "in_d6_pool_hypothetical": true,
      "in_d7_pool_hypothetical": true,
      "in_d7_pool_actual": false,
      "fingerprint": "4ec297ba99da804fe1068f1a398d0de8c7ed84461f2efbfd59557f1f5c94ab96",
      "canonical_type": "list(card) -> bool",
      "mapped": false,
      "unmapped_reason": "fp_not_in_pool"
    },
    {
      "prog_str": "(\u03bb ge (sum_ranks $0) 5)",
      "visit_count": 16,
      "visit_mass": 3.999960000399996e-05,
      "parse_ok": true,
      "type_ok": true,
      "pruner_ok": true,
      "depth": 5,
      "size": 8,
      "in_d6_pool_hypothetical": true,
      "in_d7_pool_hypothetical": true,
      "in_d7_pool_actual": false,
      "fingerprint": "4ec297ba99da804fe1068f1a398d0de8c7ed84461f2efbfd59557f1f5c94ab96",
      "canonical_type": "list(card) -> bool",
      "mapped": false,
      "unmapped_reason": "fp_not_in_pool"
    },
    {
      "prog_str": "(\u03bb ge (sum_ranks (sort_by_rank $0)) 5)",
      "visit_count": 11,
      "visit_mass": 2.7499725002749972e-05,
      "parse_ok": true,
      "type_ok": true,
      "pruner_ok": true,
      "depth": 6,
      "size": 10,
      "in_d6_pool_hypothetical": true,
      "in_d7_pool_hypothetical": true,
      "in_d7_pool_actual": false,
      "fingerprint": "4ec297ba99da804fe1068f1a398d0de8c7ed84461f2efbfd59557f1f5c94ab96",
      "canonical_type": "list(card) -> bool",
      "mapped": false,
      "unmapped_reason": "fp_not_in_pool"
    },
    {
      "prog_str": "(\u03bb ge (sum_ranks (sort_by_rank $0)) 0)",
      "visit_count": 3,
      "visit_mass": 7.499925000749993e-06,
      "parse_ok": true,
      "type_ok": true,
      "pruner_ok": true,
      "depth": 6,
      "size": 10,
      "in_d6_pool_hypothetical": true,
      "in_d7_pool_hypothetical": true,
      "in_d7_pool_actual": false,
      "fingerprint": "4ec297ba99da804fe1068f1a398d0de8c7ed84461f2efbfd59557f1f5c94ab96",
      "canonical_type": "list(card) -> bool",
      "mapped": false,
      "unmapped_reason": "fp_not_in_pool"
    },
    {
      "prog_str": "(\u03bb ge (sum_ranks (sort_by_rank $0)) 2)",
      "visit_count": 14,
      "visit_mass": 3.499965000349997e-05,
      "parse_ok": true,
      "type_ok": true,
      "pruner_ok": true,
      "depth": 6,
      "size": 10,
      "in_d6_pool_hypothetical": true,
      "in_d7_pool_hypothetical": true,
      "in_d7_pool_actual": false,
      "fingerprint": "4ec297ba99da804fe1068f1a398d0de8c7ed84461f2efbfd59557f1f5c94ab96",
      "canonical_type": "list(card) -> bool",
      "mapped": false,
      "unmapped_reason": "fp_not_in_pool"
    },
    {
      "prog_str": "(\u03bb ge (sum_ranks (sort_by_rank $0)) 4)",
      "visit_count": 5,
      "visit_mass": 1.2499875001249987e-05,
      "parse_ok": true,
      "type_ok": true,
      "pruner_ok": true,
      "depth": 6,
      "size": 10,
      "in_d6_pool_hypothetical": true,
      "in_d7_pool_hypothetical": true,
      "in_d7_pool_actual": false,
      "fingerprint": "4ec297ba99da804fe1068f1a398d0de8c7ed84461f2efbfd59557f1f5c94ab96",
      "canonical_type": "list(card) -> bool",
      "mapped": false,
      "unmapped_reason": "fp_not_in_pool"
    },
    {
      "prog_str": "(\u03bb ge (sum_ranks (sort_by_rank $0)) 3)",
      "visit_count": 19,
      "visit_mass": 4.7499525004749954e-05,
      "parse_ok": true,
      "type_ok": true,
      "pruner_ok": true,
      "depth": 6,
      "size": 10,
      "in_d6_pool_hypothetical": true,
      "in_d7_pool_hypothetical": true,
      "in_d7_pool_actual": false,
      "fingerprint": "4ec297ba99da804fe1068f1a398d0de8c7ed84461f2efbfd59557f1f5c94ab96",
      "canonical_type": "list(card) -> bool",
      "mapped": false,
      "unmapped_reason": "fp_not_in_pool"
    },
    {
      "prog_str": "(\u03bb ge (sum_ranks $0) 2)",
      "visit_count": 8,
      "visit_mass": 1.999980000199998e-05,
      "parse_ok": true,
      "type_ok": true,
      "pruner_ok": true,
      "depth": 5,
      "size": 8,
      "in_d6_pool_hypothetical": true,
      "in_d7_pool_hypothetical": true,
      "in_d7_pool_actual": false,
      "fingerprint": "4ec297ba99da804fe1068f1a398d0de8c7ed84461f2efbfd59557f1f5c94ab96",
      "canonical_type": "list(card) -> bool",
      "mapped": false,
      "unmapped_reason": "fp_not_in_pool"
    },
    {
      "prog_str": "(\u03bb ge (half_len $0) 2)",
      "visit_count": 65,
      "visit_mass": 0.00016249837501624984,
      "parse_ok": true,
      "type_ok": false,
      "pruner_ok": true,
      "depth": 5,
      "size": 8,
      "in_d6_pool_hypothetical": false,
      "in_d7_pool_hypothetical": false,
      "in_d7_pool_actual": null,
      "fingerprint": null,
      "canonical_type": "list('b) -> bool",
      "mapped": false,
      "unmapped_reason": "fp_not_in_pool"
    },
    {
      "prog_str": "(\u03bb ge (half_len $0) 1)",
      "visit_count": 12,
      "visit_mass": 2.999970000299997e-05,
      "parse_ok": true,
      "type_ok": false,
      "pruner_ok": true,
      "depth": 5,
      "size": 8,
      "in_d6_pool_hypothetical": false,
      "in_d7_pool_hypothetical": false,
      "in_d7_pool_actual": null,
      "fingerprint": null,
      "canonical_type": "list('b) -> bool",
      "mapped": false,
      "unmapped_reason": "fp_not_in_pool"
    },
    {
      "prog_str": "(\u03bb ge (n_unique_suits $0) 1)",
      "visit_count": 19,
      "visit_mass": 4.7499525004749954e-05,
      "parse_ok": true,
      "type_ok": true,
      "pruner_ok": true,
      "depth": 5,
      "size": 8,
      "in_d6_pool_hypothetical": true,
      "in_d7_pool_hypothetical": true,
      "in_d7_pool_actual": false,
      "fingerprint": "4ec297ba99da804fe1068f1a398d0de8c7ed84461f2efbfd59557f1f5c94ab96",
      "canonical_type": "list(card) -> bool",
      "mapped": false,
      "unmapped_reason": "fp_not_in_pool"
    },
    {
      "prog_str": "(\u03bb ge (sum_ranks $0) 1)",
      "visit_count": 54,
      "visit_mass": 0.00013499865001349986,
      "parse_ok": true,
      "type_ok": true,
      "pruner_ok": true,
      "depth": 5,
      "size": 8,
      "in_d6_pool_hypothetical": true,
      "in_d7_pool_hypothetical": true,
      "in_d7_pool_actual": false,
      "fingerprint": "4ec297ba99da804fe1068f1a398d0de8c7ed84461f2efbfd59557f1f5c94ab96",
      "canonical_type": "list(card) -> bool",
      "mapped": false,
      "unmapped_reason": "fp_not_in_pool"
    },
    {
      "prog_str": "(\u03bb ge (sum_ranks $0) 4)",
      "visit_count": 18,
      "visit_mass": 4.499955000449995e-05,
      "parse_ok": true,
      "type_ok": true,
      "pruner_ok": true,
      "depth": 5,
      "size": 8,
      "in_d6_pool_hypothetical": true,
      "in_d7_pool_hypothetical": true,
      "in_d7_pool_actual": false,
      "fingerprint": "4ec297ba99da804fe1068f1a398d0de8c7ed84461f2efbfd59557f1f5c94ab96",
      "canonical_type": "list(card) -> bool",
      "mapped": false,
      "unmapped_reason": "fp_not_in_pool"
    },
    {
      "prog_str": "(\u03bb ge (sum_ranks $0) 0)",
      "visit_count": 4,
      "visit_mass": 9.99990000099999e-06,
      "parse_ok": true,
      "type_ok": true,
      "pruner_ok": true,
      "depth": 5,
      "size": 8,
      "in_d6_pool_hypothetical": true,
      "in_d7_pool_hypothetical": true,
      "in_d7_pool_actual": false,
      "fingerprint": "4ec297ba99da804fe1068f1a398d0de8c7ed84461f2efbfd59557f1f5c94ab96",
      "canonical_type": "list(card) -> bool",
      "mapped": false,
      "unmapped_reason": "fp_not_in_pool"
    },
    {
      "prog_str": "(\u03bb ge (n_repeated_ranks (sort_by_rank (sort_by_rank (drop (n_unique_ranks $0) $0)))) 1)",
      "visit_count": 62,
      "visit_mass": 0.00015499845001549985,
      "parse_ok": true,
      "type_ok": true,
      "pruner_ok": false,
      "depth": 10,
      "size": 18,
      "in_d6_pool_hypothetical": false,
      "in_d7_pool_hypothetical": false,
      "in_d7_pool_actual": false,
      "fingerprint": "fe56b2d2404bce8243abd29cd35a0d108fcc1ee658110cdf7c1e4433bf21fb43",
      "canonical_type": "list(card) -> bool",
      "mapped": false,
      "unmapped_reason": "fp_not_in_pool"
    },
    {
      "prog_str": "(\u03bb ge (n_repeated_ranks $0) 0)",
      "visit_count": 75,
      "visit_mass": 0.0001874981250187498,
      "parse_ok": true,
      "type_ok": true,
      "pruner_ok": true,
      "depth": 5,
      "size": 8,
      "in_d6_pool_hypothetical": true,
      "in_d7_pool_hypothetical": true,
      "in_d7_pool_actual": false,
      "fingerprint": "4ec297ba99da804fe1068f1a398d0de8c7ed84461f2efbfd59557f1f5c94ab96",
      "canonical_type": "list(card) -> bool",
      "mapped": false,
      "unmapped_reason": "fp_not_in_pool"
    },
    {
      "prog_str": "(\u03bb has_suit (head (at (adjacent_pairs (adjacent_pairs $0)) (n_unique_ranks $0))) HEARTS)",
      "visit_count": 13,
      "visit_mass": 3.2499675003249965e-05,
      "parse_ok": true,
      "type_ok": true,
      "pruner_ok": true,
      "depth": 9,
      "size": 18,
      "in_d6_pool_hypothetical": false,
      "in_d7_pool_hypothetical": false,
      "in_d7_pool_actual": false,
      "fingerprint": "786fe41b056fe62cf7dc639551931c74903ac00e992395f371f7ca230626546f",
      "canonical_type": "list(card) -> bool",
      "mapped": false,
      "unmapped_reason": "fp_not_in_pool"
    },
    {
      "prog_str": "(\u03bb gt 4 (n_repeated_ranks $0))",
      "visit_count": 10,
      "visit_mass": 2.4999750002499974e-05,
      "parse_ok": true,
      "type_ok": true,
      "pruner_ok": true,
      "depth": 4,
      "size": 8,
      "in_d6_pool_hypothetical": true,
      "in_d7_pool_hypothetical": true,
      "in_d7_pool_actual": false,
      "fingerprint": "4ec297ba99da804fe1068f1a398d0de8c7ed84461f2efbfd59557f1f5c94ab96",
      "canonical_type": "list(card) -> bool",
      "mapped": false,
      "unmapped_reason": "fp_not_in_pool"
    },
    {
      "prog_str": "(\u03bb gt 5 (half_len $0))",
      "visit_count": 270,
      "visit_mass": 0.0006749932500674993,
      "parse_ok": true,
      "type_ok": false,
      "pruner_ok": true,
      "depth": 4,
      "size": 8,
      "in_d6_pool_hypothetical": false,
      "in_d7_pool_hypothetical": false,
      "in_d7_pool_actual": null,
      "fingerprint": null,
      "canonical_type": "list('c) -> bool",
      "mapped": false,
      "unmapped_reason": "fp_not_in_pool"
    },
    {
      "prog_str": "(\u03bb gt 4 (half_len $0))",
      "visit_count": 38,
      "visit_mass": 9.499905000949991e-05,
      "parse_ok": true,
      "type_ok": false,
      "pruner_ok": true,
      "depth": 4,
      "size": 8,
      "in_d6_pool_hypothetical": false,
      "in_d7_pool_hypothetical": false,
      "in_d7_pool_actual": null,
      "fingerprint": null,
      "canonical_type": "list('c) -> bool",
      "mapped": false,
      "unmapped_reason": "fp_not_in_pool"
    },
    {
      "prog_str": "(\u03bb gt (n_unique_suits (drop (n_unique_colors (second_half $0)) $0)) (n_unique_ranks $0))",
      "visit_count": 81,
      "visit_mass": 0.0002024979750202498,
      "parse_ok": true,
      "type_ok": true,
      "pruner_ok": true,
      "depth": 9,
      "size": 18,
      "in_d6_pool_hypothetical": false,
      "in_d7_pool_hypothetical": false,
      "in_d7_pool_actual": false,
      "fingerprint": "0841ea62d9232a98182d4125fc05cc900721f0b303549d552a96bd99a451c447",
      "canonical_type": "list(card) -> bool",
      "mapped": false,
      "unmapped_reason": "fp_not_in_pool"
    },
    {
      "prog_str": "(\u03bb gt (n_unique_suits (take 4 (reverse $0))) (n_unique_ranks $0))",
      "visit_count": 7222,
      "visit_mass": 0.01805481945180548,
      "parse_ok": true,
      "type_ok": true,
      "pruner_ok": true,
      "depth": 7,
      "size": 16,
      "in_d6_pool_hypothetical": false,
      "in_d7_pool_hypothetical": true,
      "in_d7_pool_actual": false,
      "fingerprint": "0841ea62d9232a98182d4125fc05cc900721f0b303549d552a96bd99a451c447",
      "canonical_type": "list(card) -> bool",
      "mapped": false,
      "unmapped_reason": "fp_not_in_pool"
    },
    {
      "prog_str": "(\u03bb gt (n_unique_suits (take 4 (reverse $0))) (n_unique_ranks (sort_by_rank $0)))",
      "visit_count": 45,
      "visit_mass": 0.00011249887501124989,
      "parse_ok": true,
      "type_ok": true,
      "pruner_ok": true,
      "depth": 7,
      "size": 18,
      "in_d6_pool_hypothetical": false,
      "in_d7_pool_hypothetical": true,
      "in_d7_pool_actual": false,
      "fingerprint": "0841ea62d9232a98182d4125fc05cc900721f0b303549d552a96bd99a451c447",
      "canonical_type": "list(card) -> bool",
      "mapped": false,
      "unmapped_reason": "fp_not_in_pool"
    },
    {
      "prog_str": "(\u03bb gt (n_unique_suits (take (suit_to_int DIAMONDS) (reverse $0))) (n_unique_ranks $0))",
      "visit_count": 113,
      "visit_mass": 0.0002824971750282497,
      "parse_ok": true,
      "type_ok": true,
      "pruner_ok": true,
      "depth": 8,
      "size": 18,
      "in_d6_pool_hypothetical": false,
      "in_d7_pool_hypothetical": false,
      "in_d7_pool_actual": false,
      "fingerprint": "0841ea62d9232a98182d4125fc05cc900721f0b303549d552a96bd99a451c447",
      "canonical_type": "list(card) -> bool",
      "mapped": false,
      "unmapped_reason": "fp_not_in_pool"
    },
    {
      "prog_str": "(\u03bb gt (n_unique_suits (reverse (drop 2 $0))) (n_unique_ranks $0))",
      "visit_count": 25366,
      "visit_mass": 0.06341436585634144,
      "parse_ok": true,
      "type_ok": true,
      "pruner_ok": true,
      "depth": 8,
      "size": 16,
      "in_d6_pool_hypothetical": false,
      "in_d7_pool_hypothetical": false,
      "in_d7_pool_actual": false,
      "fingerprint": "0841ea62d9232a98182d4125fc05cc900721f0b303549d552a96bd99a451c447",
      "canonical_type": "list(card) -> bool",
      "mapped": false,
      "unmapped_reason": "fp_not_in_pool"
    },
    {
      "prog_str": "(\u03bb gt (n_unique_suits (reverse (drop 2 $0))) (n_unique_ranks (reverse $0)))",
      "visit_count": 372,
      "visit_mass": 0.0009299907000929991,
      "parse_ok": true,
      "type_ok": true,
      "pruner_ok": true,
      "depth": 8,
      "size": 18,
      "in_d6_pool_hypothetical": false,
      "in_d7_pool_hypothetical": false,
      "in_d7_pool_actual": false,
      "fingerprint": "0841ea62d9232a98182d4125fc05cc900721f0b303549d552a96bd99a451c447",
      "canonical_type": "list(card) -> bool",
      "mapped": false,
      "unmapped_reason": "fp_not_in_pool"
    },
    {
      "prog_str": "(\u03bb gt (n_unique_suits (reverse (drop (+ 0 2) $0))) (n_unique_ranks (reverse $0)))",
      "visit_count": 33,
      "visit_mass": 8.249917500824991e-05,
      "parse_ok": true,
      "type_ok": true,
      "pruner_ok": true,
      "depth": 10,
      "size": 22,
      "in_d6_pool_hypothetical": false,
      "in_d7_pool_hypothetical": false,
      "in_d7_pool_actual": false,
      "fingerprint": "0841ea62d9232a98182d4125fc05cc900721f0b303549d552a96bd99a451c447",
      "canonical_type": "list(card) -> bool",
      "mapped": false,
      "unmapped_reason": "fp_not_in_pool"
    },
    {
      "prog_str": "(\u03bb gt (n_unique_suits (reverse (drop (+ 0 2) $0))) (n_unique_ranks (sort_by_rank $0)))",
      "visit_count": 45,
      "visit_mass": 0.00011249887501124989,
      "parse_ok": true,
      "type_ok": true,
      "pruner_ok": true,
      "depth": 10,
      "size": 22,
      "in_d6_pool_hypothetical": false,
      "in_d7_pool_hypothetical": false,
      "in_d7_pool_actual": false,
      "fingerprint": "0841ea62d9232a98182d4125fc05cc900721f0b303549d552a96bd99a451c447",
      "canonical_type": "list(card) -> bool",
      "mapped": false,
      "unmapped_reason": "fp_not_in_pool"
    },
    {
      "prog_str": "(\u03bb gt (n_unique_suits (reverse (drop (+ 0 2) $0))) (n_unique_ranks $0))",
      "visit_count": 477,
      "visit_mass": 0.0011924880751192487,
      "parse_ok": true,
      "type_ok": true,
      "pruner_ok": true,
      "depth": 10,
      "size": 20,
      "in_d6_pool_hypothetical": false,
      "in_d7_pool_hypothetical": false,
      "in_d7_pool_actual": false,
      "fingerprint": "0841ea62d9232a98182d4125fc05cc900721f0b303549d552a96bd99a451c447",
      "canonical_type": "list(card) -> bool",
      "mapped": false,
      "unmapped_reason": "fp_not_in_pool"
    },
    {
      "prog_str": "(\u03bb gt (n_unique_suits (reverse (drop 2 $0))) (n_unique_ranks (sort_by_rank $0)))",
      "visit_count": 1130,
      "visit_mass": 0.002824971750282497,
      "parse_ok": true,
      "type_ok": true,
      "pruner_ok": true,
      "depth": 8,
      "size": 18,
      "in_d6_pool_hypothetical": false,
      "in_d7_pool_hypothetical": false,
      "in_d7_pool_actual": false,
      "fingerprint": "0841ea62d9232a98182d4125fc05cc900721f0b303549d552a96bd99a451c447",
      "canonical_type": "list(card) -> bool",
      "mapped": false,
      "unmapped_reason": "fp_not_in_pool"
    },
    {
      "prog_str": "(\u03bb gt (n_unique_suits (reverse (drop 2 $0))) (n_unique_ranks (drop 0 $0)))",
      "visit_count": 18,
      "visit_mass": 4.499955000449995e-05,
      "parse_ok": true,
      "type_ok": true,
      "pruner_ok": true,
      "depth": 8,
      "size": 20,
      "in_d6_pool_hypothetical": false,
      "in_d7_pool_hypothetical": false,
      "in_d7_pool_actual": false,
      "fingerprint": "0841ea62d9232a98182d4125fc05cc900721f0b303549d552a96bd99a451c447",
      "canonical_type": "list(card) -> bool",
      "mapped": false,
      "unmapped_reason": "fp_not_in_pool"
    },
    {
      "prog_str": "(\u03bb gt (n_unique_suits (reverse (drop 2 $0))) (n_unique_ranks (unique $0)))",
      "visit_count": 589,
      "visit_mass": 0.0014724852751472485,
      "parse_ok": true,
      "type_ok": true,
      "pruner_ok": true,
      "depth": 8,
      "size": 18,
      "in_d6_pool_hypothetical": false,
      "in_d7_pool_hypothetical": false,
      "in_d7_pool_actual": false,
      "fingerprint": "0841ea62d9232a98182d4125fc05cc900721f0b303549d552a96bd99a451c447",
      "canonical_type": "list(card) -> bool",
      "mapped": false,
      "unmapped_reason": "fp_not_in_pool"
    },
    {
      "prog_str": "(\u03bb gt (n_unique_suits (reverse (drop (suit_to_int CLUBS) $0))) (n_unique_ranks $0))",
      "visit_count": 739,
      "visit_mass": 0.0018474815251847481,
      "parse_ok": true,
      "type_ok": true,
      "pruner_ok": true,
      "depth": 9,
      "size": 18,
      "in_d6_pool_hypothetical": false,
      "in_d7_pool_hypothetical": false,
      "in_d7_pool_actual": false,
      "fingerprint": "0841ea62d9232a98182d4125fc05cc900721f0b303549d552a96bd99a451c447",
      "canonical_type": "list(card) -> bool",
      "mapped": false,
      "unmapped_reason": "fp_not_in_pool"
    },
    {
      "prog_str": "(\u03bb gt (n_unique_suits (reverse (drop (suit_to_int CLUBS) $0))) (n_unique_ranks (sort_by_rank $0)))",
      "visit_count": 15,
      "visit_mass": 3.749962500374996e-05,
      "parse_ok": true,
      "type_ok": true,
      "pruner_ok": true,
      "depth": 9,
      "size": 20,
      "in_d6_pool_hypothetical": false,
      "in_d7_pool_hypothetical": false,
      "in_d7_pool_actual": false,
      "fingerprint": "0841ea62d9232a98182d4125fc05cc900721f0b303549d552a96bd99a451c447",
      "canonical_type": "list(card) -> bool",
      "mapped": false,
      "unmapped_reason": "fp_not_in_pool"
    },
    {
      "prog_str": "(\u03bb gt (n_unique_suits (reverse (drop (n_repeated_ranks $0) $0))) (n_unique_ranks $0))",
      "visit_count": 1042,
      "visit_mass": 0.0026049739502604975,
      "parse_ok": true,
      "type_ok": true,
      "pruner_ok": true,
      "depth": 9,
      "size": 18,
      "in_d6_pool_hypothetical": false,
      "in_d7_pool_hypothetical": false,
      "in_d7_pool_actual": false,
      "fingerprint": "0841ea62d9232a98182d4125fc05cc900721f0b303549d552a96bd99a451c447",
      "canonical_type": "list(card) -> bool",
      "mapped": false,
      "unmapped_reason": "fp_not_in_pool"
    },
    {
      "prog_str": "(\u03bb gt (n_unique_suits (reverse (drop (max_suit_count $0) $0))) (n_unique_ranks $0))",
      "visit_count": 680,
      "visit_mass": 0.0016999830001699983,
      "parse_ok": true,
      "type_ok": true,
      "pruner_ok": true,
      "depth": 9,
      "size": 18,
      "in_d6_pool_hypothetical": false,
      "in_d7_pool_hypothetical": false,
      "in_d7_pool_actual": false,
      "fingerprint": "0841ea62d9232a98182d4125fc05cc900721f0b303549d552a96bd99a451c447",
      "canonical_type": "list(card) -> bool",
      "mapped": false,
      "unmapped_reason": "fp_not_in_pool"
    },
    {
      "prog_str": "(\u03bb gt (n_unique_suits (drop 2 $0)) (n_unique_ranks (reverse $0)))",
      "visit_count": 1356,
      "visit_mass": 0.0033899661003389966,
      "parse_ok": true,
      "type_ok": true,
      "pruner_ok": true,
      "depth": 7,
      "size": 16,
      "in_d6_pool_hypothetical": false,
      "in_d7_pool_hypothetical": true,
      "in_d7_pool_actual": false,
      "fingerprint": "0841ea62d9232a98182d4125fc05cc900721f0b303549d552a96bd99a451c447",
      "canonical_type": "list(card) -> bool",
      "mapped": false,
      "unmapped_reason": "fp_not_in_pool"
    },
    {
      "prog_str": "(\u03bb gt (n_unique_suits (drop 2 $0)) (n_unique_ranks $0))",
      "visit_count": 51992,
      "visit_mass": 0.12997870021299787,
      "parse_ok": true,
      "type_ok": true,
      "pruner_ok": true,
      "depth": 7,
      "size": 14,
      "in_d6_pool_hypothetical": false,
      "in_d7_pool_hypothetical": true,
      "in_d7_pool_actual": false,
      "fingerprint": "0841ea62d9232a98182d4125fc05cc900721f0b303549d552a96bd99a451c447",
      "canonical_type": "list(card) -> bool",
      "mapped": false,
      "unmapped_reason": "fp_not_in_pool"
    },
    {
      "prog_str": "(\u03bb gt (n_unique_suits (drop 2 $0)) (n_unique_ranks (reverse (sort_by_rank $0))))",
      "visit_count": 12,
      "visit_mass": 2.999970000299997e-05,
      "parse_ok": true,
      "type_ok": true,
      "pruner_ok": true,
      "depth": 7,
      "size": 18,
      "in_d6_pool_hypothetical": false,
      "in_d7_pool_hypothetical": true,
      "in_d7_pool_actual": false,
      "fingerprint": "0841ea62d9232a98182d4125fc05cc900721f0b303549d552a96bd99a451c447",
      "canonical_type": "list(card) -> bool",
      "mapped": false,
      "unmapped_reason": "fp_not_in_pool"
    },
    {
      "prog_str": "(\u03bb gt (n_unique_suits (drop 2 $0)) (n_unique_ranks (unique $0)))",
      "visit_count": 1324,
      "visit_mass": 0.0033099669003309965,
      "parse_ok": true,
      "type_ok": true,
      "pruner_ok": true,
      "depth": 7,
      "size": 16,
      "in_d6_pool_hypothetical": false,
      "in_d7_pool_hypothetical": true,
      "in_d7_pool_actual": false,
      "fingerprint": "0841ea62d9232a98182d4125fc05cc900721f0b303549d552a96bd99a451c447",
      "canonical_type": "list(card) -> bool",
      "mapped": false,
      "unmapped_reason": "fp_not_in_pool"
    },
    {
      "prog_str": "(\u03bb gt (n_unique_suits (drop 2 (unique $0))) (n_unique_ranks $0))",
      "visit_count": 476,
      "visit_mass": 0.0011899881001189987,
      "parse_ok": true,
      "type_ok": true,
      "pruner_ok": true,
      "depth": 7,
      "size": 16,
      "in_d6_pool_hypothetical": false,
      "in_d7_pool_hypothetical": true,
      "in_d7_pool_actual": false,
      "fingerprint": "0841ea62d9232a98182d4125fc05cc900721f0b303549d552a96bd99a451c447",
      "canonical_type": "list(card) -> bool",
      "mapped": false,
      "unmapped_reason": "fp_not_in_pool"
    },
    {
      "prog_str": "(\u03bb gt (n_unique_suits (drop (+ 1 (n_repeated_ranks $0)) $0)) (n_unique_ranks $0))",
      "visit_count": 134,
      "visit_mass": 0.0003349966500334997,
      "parse_ok": true,
      "type_ok": true,
      "pruner_ok": true,
      "depth": 9,
      "size": 20,
      "in_d6_pool_hypothetical": false,
      "in_d7_pool_hypothetical": false,
      "in_d7_pool_actual": false,
      "fingerprint": "0841ea62d9232a98182d4125fc05cc900721f0b303549d552a96bd99a451c447",
      "canonical_type": "list(card) -> bool",
      "mapped": false,
      "unmapped_reason": "fp_not_in_pool"
    },
    {
      "prog_str": "(\u03bb gt (n_unique_suits (drop 2 $0)) (n_unique_ranks (unique (reverse $0))))",
      "visit_count": 47,
      "visit_mass": 0.00011749882501174988,
      "parse_ok": true,
      "type_ok": true,
      "pruner_ok": true,
      "depth": 7,
      "size": 18,
      "in_d6_pool_hypothetical": false,
      "in_d7_pool_hypothetical": true,
      "in_d7_pool_actual": false,
      "fingerprint": "0841ea62d9232a98182d4125fc05cc900721f0b303549d552a96bd99a451c447",
      "canonical_type": "list(card) -> bool",
      "mapped": false,
      "unmapped_reason": "fp_not_in_pool"
    },
    {
      "prog_str": "(\u03bb gt (n_unique_suits (drop (suit_to_int CLUBS) $0)) (n_unique_ranks $0))",
      "visit_count": 4313,
      "visit_mass": 0.010782392176078239,
      "parse_ok": true,
      "type_ok": true,
      "pruner_ok": true,
      "depth": 8,
      "size": 16,
      "in_d6_pool_hypothetical": false,
      "in_d7_pool_hypothetical": false,
      "in_d7_pool_actual": false,
      "fingerprint": "0841ea62d9232a98182d4125fc05cc900721f0b303549d552a96bd99a451c447",
      "canonical_type": "list(card) -> bool",
      "mapped": false,
      "unmapped_reason": "fp_not_in_pool"
    },
    {
      "prog_str": "(\u03bb gt (n_unique_suits (reverse (drop 2 $0))) (n_unique_ranks (sort_by_rank (sort_by_rank $0))))",
      "visit_count": 50,
      "visit_mass": 0.00012499875001249989,
      "parse_ok": true,
      "type_ok": true,
      "pruner_ok": true,
      "depth": 8,
      "size": 20,
      "in_d6_pool_hypothetical": false,
      "in_d7_pool_hypothetical": false,
      "in_d7_pool_actual": false,
      "fingerprint": "0841ea62d9232a98182d4125fc05cc900721f0b303549d552a96bd99a451c447",
      "canonical_type": "list(card) -> bool",
      "mapped": false,
      "unmapped_reason": "fp_not_in_pool"
    },
    {
      "prog_str": "(\u03bb gt (n_unique_suits (sort_by_rank (drop 2 $0))) (n_unique_ranks $0))",
      "visit_count": 7559,
      "visit_mass": 0.01889731102688973,
      "parse_ok": true,
      "type_ok": true,
      "pruner_ok": true,
      "depth": 8,
      "size": 16,
      "in_d6_pool_hypothetical": false,
      "in_d7_pool_hypothetical": false,
      "in_d7_pool_actual": false,
      "fingerprint": "0841ea62d9232a98182d4125fc05cc900721f0b303549d552a96bd99a451c447",
      "canonical_type": "list(card) -> bool",
      "mapped": false,
      "unmapped_reason": "fp_not_in_pool"
    },
    {
      "prog_str": "(\u03bb gt (n_unique_suits (sort_by_rank (drop 2 $0))) (n_unique_ranks (sort_by_rank (unique $0))))",
      "visit_count": 10,
      "visit_mass": 2.4999750002499974e-05,
      "parse_ok": true,
      "type_ok": true,
      "pruner_ok": true,
      "depth": 8,
      "size": 20,
      "in_d6_pool_hypothetical": false,
      "in_d7_pool_hypothetical": false,
      "in_d7_pool_actual": false,
      "fingerprint": "0841ea62d9232a98182d4125fc05cc900721f0b303549d552a96bd99a451c447",
      "canonical_type": "list(card) -> bool",
      "mapped": false,
      "unmapped_reason": "fp_not_in_pool"
    },
    {
      "prog_str": "(\u03bb gt (n_unique_suits (sort_by_rank (drop 2 $0))) (n_unique_ranks (reverse $0)))",
      "visit_count": 102,
      "visit_mass": 0.00025499745002549975,
      "parse_ok": true,
      "type_ok": true,
      "pruner_ok": true,
      "depth": 8,
      "size": 18,
      "in_d6_pool_hypothetical": false,
      "in_d7_pool_hypothetical": false,
      "in_d7_pool_actual": false,
      "fingerprint": "0841ea62d9232a98182d4125fc05cc900721f0b303549d552a96bd99a451c447",
      "canonical_type": "list(card) -> bool",
      "mapped": false,
      "unmapped_reason": "fp_not_in_pool"
    },
    {
      "prog_str": "(\u03bb gt (n_unique_suits (sort_by_rank (drop 2 $0))) (n_unique_ranks (unique $0)))",
      "visit_count": 21,
      "visit_mass": 5.249947500524995e-05,
      "parse_ok": true,
      "type_ok": true,
      "pruner_ok": true,
      "depth": 8,
      "size": 18,
      "in_d6_pool_hypothetical": false,
      "in_d7_pool_hypothetical": false,
      "in_d7_pool_actual": false,
      "fingerprint": "0841ea62d9232a98182d4125fc05cc900721f0b303549d552a96bd99a451c447",
      "canonical_type": "list(card) -> bool",
      "mapped": false,
      "unmapped_reason": "fp_not_in_pool"
    },
    {
      "prog_str": "(\u03bb gt (n_unique_suits (sort_by_rank (drop (max_suit_count $0) $0))) (n_unique_ranks $0))",
      "visit_count": 192,
      "visit_mass": 0.00047999520004799953,
      "parse_ok": true,
      "type_ok": true,
      "pruner_ok": true,
      "depth": 9,
      "size": 18,
      "in_d6_pool_hypothetical": false,
      "in_d7_pool_hypothetical": false,
      "in_d7_pool_actual": false,
      "fingerprint": "0841ea62d9232a98182d4125fc05cc900721f0b303549d552a96bd99a451c447",
      "canonical_type": "list(card) -> bool",
      "mapped": false,
      "unmapped_reason": "fp_not_in_pool"
    },
    {
      "prog_str": "(\u03bb gt (n_unique_suits (sort_by_rank (drop (n_repeated_suits $0) $0))) (n_unique_ranks $0))",
      "visit_count": 133,
      "visit_mass": 0.00033249667503324967,
      "parse_ok": true,
      "type_ok": true,
      "pruner_ok": true,
      "depth": 9,
      "size": 18,
      "in_d6_pool_hypothetical": false,
      "in_d7_pool_hypothetical": false,
      "in_d7_pool_actual": false,
      "fingerprint": "4aadd875990216e977306ce46ab3401a8bdae6b17c04f2058f61fc5f3e19db73",
      "canonical_type": "list(card) -> bool",
      "mapped": false,
      "unmapped_reason": "fp_not_in_pool"
    },
    {
      "prog_str": "(\u03bb gt (n_unique_suits (drop (n_unique_colors $0) (drop 0 $0))) (n_unique_ranks $0))",
      "visit_count": 12,
      "visit_mass": 2.999970000299997e-05,
      "parse_ok": true,
      "type_ok": true,
      "pruner_ok": true,
      "depth": 8,
      "size": 20,
      "in_d6_pool_hypothetical": false,
      "in_d7_pool_hypothetical": false,
      "in_d7_pool_actual": false,
      "fingerprint": "0841ea62d9232a98182d4125fc05cc900721f0b303549d552a96bd99a451c447",
      "canonical_type": "list(card) -> bool",
      "mapped": false,
      "unmapped_reason": "fp_not_in_pool"
    },
    {
      "prog_str": "(\u03bb gt (n_unique_suits (drop 1 (unique $0))) (n_unique_ranks $0))",
      "visit_count": 81,
      "visit_mass": 0.0002024979750202498,
      "parse_ok": true,
      "type_ok": true,
      "pruner_ok": true,
      "depth": 7,
      "size": 16,
      "in_d6_pool_hypothetical": false,
      "in_d7_pool_hypothetical": true,
      "in_d7_pool_actual": false,
      "fingerprint": "b1e46d60ce76a3697653ecf830a63d7571d197993693a8c7bb7e52230a54ae22",
      "canonical_type": "list(card) -> bool",
      "mapped": false,
      "unmapped_reason": "fp_not_in_pool"
    },
    {
      "prog_str": "(\u03bb gt (n_unique_suits (drop (n_repeated_ranks $0) $0)) (n_unique_ranks $0))",
      "visit_count": 146,
      "visit_mass": 0.00036499635003649965,
      "parse_ok": true,
      "type_ok": true,
      "pruner_ok": true,
      "depth": 8,
      "size": 16,
      "in_d6_pool_hypothetical": false,
      "in_d7_pool_hypothetical": false,
      "in_d7_pool_actual": false,
      "fingerprint": "0841ea62d9232a98182d4125fc05cc900721f0b303549d552a96bd99a451c447",
      "canonical_type": "list(card) -> bool",
      "mapped": false,
      "unmapped_reason": "fp_not_in_pool"
    },
    {
      "prog_str": "(\u03bb gt (n_unique_suits (drop 2 $0)) (n_unique_ranks (sort_by_rank $0)))",
      "visit_count": 649,
      "visit_mass": 0.0016224837751622483,
      "parse_ok": true,
      "type_ok": true,
      "pruner_ok": true,
      "depth": 7,
      "size": 16,
      "in_d6_pool_hypothetical": false,
      "in_d7_pool_hypothetical": true,
      "in_d7_pool_actual": false,
      "fingerprint": "0841ea62d9232a98182d4125fc05cc900721f0b303549d552a96bd99a451c447",
      "canonical_type": "list(card) -> bool",
      "mapped": false,
      "unmapped_reason": "fp_not_in_pool"
    },
    {
      "prog_str": "(\u03bb not (gt (length $0) 3))",
      "visit_count": 8,
      "visit_mass": 1.999980000199998e-05,
      "parse_ok": true,
      "type_ok": false,
      "pruner_ok": true,
      "depth": 6,
      "size": 10,
      "in_d6_pool_hypothetical": false,
      "in_d7_pool_hypothetical": false,
      "in_d7_pool_actual": null,
      "fingerprint": null,
      "canonical_type": "list('b) -> bool",
      "mapped": false,
      "unmapped_reason": "fp_not_in_pool"
    },
    {
      "prog_str": "(\u03bb not (gt (length $0) 2))",
      "visit_count": 6,
      "visit_mass": 1.4999850001499985e-05,
      "parse_ok": true,
      "type_ok": false,
      "pruner_ok": true,
      "depth": 6,
      "size": 10,
      "in_d6_pool_hypothetical": false,
      "in_d7_pool_hypothetical": false,
      "in_d7_pool_actual": null,
      "fingerprint": null,
      "canonical_type": "list('b) -> bool",
      "mapped": false,
      "unmapped_reason": "fp_not_in_pool"
    },
    {
      "prog_str": "(\u03bb not (gt (length $0) (sum_ranks $0)))",
      "visit_count": 126,
      "visit_mass": 0.0003149968500314997,
      "parse_ok": true,
      "type_ok": true,
      "pruner_ok": true,
      "depth": 6,
      "size": 12,
      "in_d6_pool_hypothetical": true,
      "in_d7_pool_hypothetical": true,
      "in_d7_pool_actual": false,
      "fingerprint": "4ec297ba99da804fe1068f1a398d0de8c7ed84461f2efbfd59557f1f5c94ab96",
      "canonical_type": "list(card) -> bool",
      "mapped": false,
      "unmapped_reason": "fp_not_in_pool"
    },
    {
      "prog_str": "(\u03bb not (gt 4 (sum_ranks $0)))",
      "visit_count": 7,
      "visit_mass": 1.7499825001749983e-05,
      "parse_ok": true,
      "type_ok": true,
      "pruner_ok": true,
      "depth": 5,
      "size": 10,
      "in_d6_pool_hypothetical": true,
      "in_d7_pool_hypothetical": true,
      "in_d7_pool_actual": false,
      "fingerprint": "4ec297ba99da804fe1068f1a398d0de8c7ed84461f2efbfd59557f1f5c94ab96",
      "canonical_type": "list(card) -> bool",
      "mapped": false,
      "unmapped_reason": "fp_not_in_pool"
    },
    {
      "prog_str": "(\u03bb not (gt 5 (sum_ranks $0)))",
      "visit_count": 79,
      "visit_mass": 0.0001974980250197498,
      "parse_ok": true,
      "type_ok": true,
      "pruner_ok": true,
      "depth": 5,
      "size": 10,
      "in_d6_pool_hypothetical": true,
      "in_d7_pool_hypothetical": true,
      "in_d7_pool_actual": false,
      "fingerprint": "4ec297ba99da804fe1068f1a398d0de8c7ed84461f2efbfd59557f1f5c94ab96",
      "canonical_type": "list(card) -> bool",
      "mapped": false,
      "unmapped_reason": "fp_not_in_pool"
    },
    {
      "prog_str": "(\u03bb not (gt 2 (sum_ranks $0)))",
      "visit_count": 50,
      "visit_mass": 0.00012499875001249989,
      "parse_ok": true,
      "type_ok": true,
      "pruner_ok": true,
      "depth": 5,
      "size": 10,
      "in_d6_pool_hypothetical": true,
      "in_d7_pool_hypothetical": true,
      "in_d7_pool_actual": false,
      "fingerprint": "4ec297ba99da804fe1068f1a398d0de8c7ed84461f2efbfd59557f1f5c94ab96",
      "canonical_type": "list(card) -> bool",
      "mapped": false,
      "unmapped_reason": "fp_not_in_pool"
    },
    {
      "prog_str": "(\u03bb not (gt 2 (min_rank $0)))",
      "visit_count": 17,
      "visit_mass": 4.249957500424996e-05,
      "parse_ok": true,
      "type_ok": true,
      "pruner_ok": true,
      "depth": 5,
      "size": 10,
      "in_d6_pool_hypothetical": true,
      "in_d7_pool_hypothetical": true,
      "in_d7_pool_actual": false,
      "fingerprint": "4ec297ba99da804fe1068f1a398d0de8c7ed84461f2efbfd59557f1f5c94ab96",
      "canonical_type": "list(card) -> bool",
      "mapped": false,
      "unmapped_reason": "fp_not_in_pool"
    },
    {
      "prog_str": "(\u03bb not (gt (suit_to_int SPADES) (sum_ranks $0)))",
      "visit_count": 9,
      "visit_mass": 2.2499775002249976e-05,
      "parse_ok": true,
      "type_ok": true,
      "pruner_ok": true,
      "depth": 6,
      "size": 12,
      "in_d6_pool_hypothetical": true,
      "in_d7_pool_hypothetical": true,
      "in_d7_pool_actual": false,
      "fingerprint": "4ec297ba99da804fe1068f1a398d0de8c7ed84461f2efbfd59557f1f5c94ab96",
      "canonical_type": "list(card) -> bool",
      "mapped": false,
      "unmapped_reason": "fp_not_in_pool"
    },
    {
      "prog_str": "(\u03bb not (gt (suit_to_int HEARTS) (sum_ranks $0)))",
      "visit_count": 12,
      "visit_mass": 2.999970000299997e-05,
      "parse_ok": true,
      "type_ok": true,
      "pruner_ok": true,
      "depth": 6,
      "size": 12,
      "in_d6_pool_hypothetical": true,
      "in_d7_pool_hypothetical": true,
      "in_d7_pool_actual": false,
      "fingerprint": "4ec297ba99da804fe1068f1a398d0de8c7ed84461f2efbfd59557f1f5c94ab96",
      "canonical_type": "list(card) -> bool",
      "mapped": false,
      "unmapped_reason": "fp_not_in_pool"
    },
    {
      "prog_str": "(\u03bb not (gt 0 (sum_ranks $0)))",
      "visit_count": 6,
      "visit_mass": 1.4999850001499985e-05,
      "parse_ok": true,
      "type_ok": true,
      "pruner_ok": true,
      "depth": 5,
      "size": 10,
      "in_d6_pool_hypothetical": true,
      "in_d7_pool_hypothetical": true,
      "in_d7_pool_actual": false,
      "fingerprint": "4ec297ba99da804fe1068f1a398d0de8c7ed84461f2efbfd59557f1f5c94ab96",
      "canonical_type": "list(card) -> bool",
      "mapped": false,
      "unmapped_reason": "fp_not_in_pool"
    },
    {
      "prog_str": "(\u03bb not (gt 0 (sum_ranks (head (adjacent_pairs $0)))))",
      "visit_count": 26,
      "visit_mass": 6.499935000649993e-05,
      "parse_ok": true,
      "type_ok": true,
      "pruner_ok": true,
      "depth": 7,
      "size": 14,
      "in_d6_pool_hypothetical": false,
      "in_d7_pool_hypothetical": true,
      "in_d7_pool_actual": false,
      "fingerprint": "4ec297ba99da804fe1068f1a398d0de8c7ed84461f2efbfd59557f1f5c94ab96",
      "canonical_type": "list(card) -> bool",
      "mapped": false,
      "unmapped_reason": "fp_not_in_pool"
    },
    {
      "prog_str": "(\u03bb not (gt 0 (half_len $0)))",
      "visit_count": 58,
      "visit_mass": 0.00014499855001449984,
      "parse_ok": true,
      "type_ok": false,
      "pruner_ok": true,
      "depth": 5,
      "size": 10,
      "in_d6_pool_hypothetical": false,
      "in_d7_pool_hypothetical": false,
      "in_d7_pool_actual": null,
      "fingerprint": null,
      "canonical_type": "list('c) -> bool",
      "mapped": false,
      "unmapped_reason": "fp_not_in_pool"
    },
    {
      "prog_str": "(\u03bb not (gt 3 (half_len $0)))",
      "visit_count": 82,
      "visit_mass": 0.0002049979500204998,
      "parse_ok": true,
      "type_ok": false,
      "pruner_ok": true,
      "depth": 5,
      "size": 10,
      "in_d6_pool_hypothetical": false,
      "in_d7_pool_hypothetical": false,
      "in_d7_pool_actual": null,
      "fingerprint": null,
      "canonical_type": "list('c) -> bool",
      "mapped": false,
      "unmapped_reason": "fp_not_in_pool"
    },
    {
      "prog_str": "(\u03bb not (gt 2 (half_len $0)))",
      "visit_count": 15,
      "visit_mass": 3.749962500374996e-05,
      "parse_ok": true,
      "type_ok": false,
      "pruner_ok": true,
      "depth": 5,
      "size": 10,
      "in_d6_pool_hypothetical": false,
      "in_d7_pool_hypothetical": false,
      "in_d7_pool_actual": null,
      "fingerprint": null,
      "canonical_type": "list('c) -> bool",
      "mapped": false,
      "unmapped_reason": "fp_not_in_pool"
    },
    {
      "prog_str": "(\u03bb ge (count_suit $0 HEARTS) 0)",
      "visit_count": 9,
      "visit_mass": 2.2499775002249976e-05,
      "parse_ok": true,
      "type_ok": true,
      "pruner_ok": true,
      "depth": 6,
      "size": 10,
      "in_d6_pool_hypothetical": true,
      "in_d7_pool_hypothetical": true,
      "in_d7_pool_actual": false,
      "fingerprint": "4ec297ba99da804fe1068f1a398d0de8c7ed84461f2efbfd59557f1f5c94ab96",
      "canonical_type": "list(card) -> bool",
      "mapped": false,
      "unmapped_reason": "fp_not_in_pool"
    },
    {
      "prog_str": "(\u03bb ge (count_suit $0 CLUBS) 0)",
      "visit_count": 19,
      "visit_mass": 4.7499525004749954e-05,
      "parse_ok": true,
      "type_ok": true,
      "pruner_ok": true,
      "depth": 6,
      "size": 10,
      "in_d6_pool_hypothetical": true,
      "in_d7_pool_hypothetical": true,
      "in_d7_pool_actual": false,
      "fingerprint": "4ec297ba99da804fe1068f1a398d0de8c7ed84461f2efbfd59557f1f5c94ab96",
      "canonical_type": "list(card) -> bool",
      "mapped": false,
      "unmapped_reason": "fp_not_in_pool"
    },
    {
      "prog_str": "(\u03bb ge (count_suit $0 DIAMONDS) 0)",
      "visit_count": 17,
      "visit_mass": 4.249957500424996e-05,
      "parse_ok": true,
      "type_ok": true,
      "pruner_ok": true,
      "depth": 6,
      "size": 10,
      "in_d6_pool_hypothetical": true,
      "in_d7_pool_hypothetical": true,
      "in_d7_pool_actual": false,
      "fingerprint": "4ec297ba99da804fe1068f1a398d0de8c7ed84461f2efbfd59557f1f5c94ab96",
      "canonical_type": "list(card) -> bool",
      "mapped": false,
      "unmapped_reason": "fp_not_in_pool"
    },
    {
      "prog_str": "(\u03bb ge (max_suit_count $0) 1)",
      "visit_count": 92,
      "visit_mass": 0.00022999770002299976,
      "parse_ok": true,
      "type_ok": true,
      "pruner_ok": true,
      "depth": 5,
      "size": 8,
      "in_d6_pool_hypothetical": true,
      "in_d7_pool_hypothetical": true,
      "in_d7_pool_actual": false,
      "fingerprint": "4ec297ba99da804fe1068f1a398d0de8c7ed84461f2efbfd59557f1f5c94ab96",
      "canonical_type": "list(card) -> bool",
      "mapped": false,
      "unmapped_reason": "fp_not_in_pool"
    },
    {
      "prog_str": "(\u03bb ge (max_suit_count (unique $0)) 1)",
      "visit_count": 1,
      "visit_mass": 2.4999750002499977e-06,
      "parse_ok": true,
      "type_ok": true,
      "pruner_ok": true,
      "depth": 6,
      "size": 10,
      "in_d6_pool_hypothetical": true,
      "in_d7_pool_hypothetical": true,
      "in_d7_pool_actual": false,
      "fingerprint": "4ec297ba99da804fe1068f1a398d0de8c7ed84461f2efbfd59557f1f5c94ab96",
      "canonical_type": "list(card) -> bool",
      "mapped": false,
      "unmapped_reason": "fp_not_in_pool"
    },
    {
      "prog_str": "(\u03bb ge (max_suit_count (unique $0)) 2)",
      "visit_count": 1,
      "visit_mass": 2.4999750002499977e-06,
      "parse_ok": true,
      "type_ok": true,
      "pruner_ok": true,
      "depth": 6,
      "size": 10,
      "in_d6_pool_hypothetical": true,
      "in_d7_pool_hypothetical": true,
      "in_d7_pool_actual": false,
      "fingerprint": "4ec297ba99da804fe1068f1a398d0de8c7ed84461f2efbfd59557f1f5c94ab96",
      "canonical_type": "list(card) -> bool",
      "mapped": false,
      "unmapped_reason": "fp_not_in_pool"
    },
    {
      "prog_str": "(\u03bb ge (max_suit_count (sort_by_rank $0)) 2)",
      "visit_count": 37,
      "visit_mass": 9.24990750092499e-05,
      "parse_ok": true,
      "type_ok": true,
      "pruner_ok": true,
      "depth": 6,
      "size": 10,
      "in_d6_pool_hypothetical": true,
      "in_d7_pool_hypothetical": true,
      "in_d7_pool_actual": false,
      "fingerprint": "4ec297ba99da804fe1068f1a398d0de8c7ed84461f2efbfd59557f1f5c94ab96",
      "canonical_type": "list(card) -> bool",
      "mapped": false,
      "unmapped_reason": "fp_not_in_pool"
    },
    {
      "prog_str": "(\u03bb ge (max_suit_count (sort_by_rank $0)) 1)",
      "visit_count": 14,
      "visit_mass": 3.499965000349997e-05,
      "parse_ok": true,
      "type_ok": true,
      "pruner_ok": true,
      "depth": 6,
      "size": 10,
      "in_d6_pool_hypothetical": true,
      "in_d7_pool_hypothetical": true,
      "in_d7_pool_actual": false,
      "fingerprint": "4ec297ba99da804fe1068f1a398d0de8c7ed84461f2efbfd59557f1f5c94ab96",
      "canonical_type": "list(card) -> bool",
      "mapped": false,
      "unmapped_reason": "fp_not_in_pool"
    },
    {
      "prog_str": "(\u03bb ge (max_suit_count (sort_by_rank $0)) (n_unique_colors $0))",
      "visit_count": 3,
      "visit_mass": 7.499925000749993e-06,
      "parse_ok": true,
      "type_ok": true,
      "pruner_ok": true,
      "depth": 6,
      "size": 12,
      "in_d6_pool_hypothetical": true,
      "in_d7_pool_hypothetical": true,
      "in_d7_pool_actual": false,
      "fingerprint": "4ec297ba99da804fe1068f1a398d0de8c7ed84461f2efbfd59557f1f5c94ab96",
      "canonical_type": "list(card) -> bool",
      "mapped": false,
      "unmapped_reason": "fp_not_in_pool"
    },
    {
      "prog_str": "(\u03bb ge 2 (n_unique_colors $0))",
      "visit_count": 9,
      "visit_mass": 2.2499775002249976e-05,
      "parse_ok": true,
      "type_ok": true,
      "pruner_ok": true,
      "depth": 4,
      "size": 8,
      "in_d6_pool_hypothetical": true,
      "in_d7_pool_hypothetical": true,
      "in_d7_pool_actual": false,
      "fingerprint": "4ec297ba99da804fe1068f1a398d0de8c7ed84461f2efbfd59557f1f5c94ab96",
      "canonical_type": "list(card) -> bool",
      "mapped": false,
      "unmapped_reason": "fp_not_in_pool"
    },
    {
      "prog_str": "(\u03bb ge 3 (n_unique_colors $0))",
      "visit_count": 28,
      "visit_mass": 6.999930000699993e-05,
      "parse_ok": true,
      "type_ok": true,
      "pruner_ok": true,
      "depth": 4,
      "size": 8,
      "in_d6_pool_hypothetical": true,
      "in_d7_pool_hypothetical": true,
      "in_d7_pool_actual": false,
      "fingerprint": "4ec297ba99da804fe1068f1a398d0de8c7ed84461f2efbfd59557f1f5c94ab96",
      "canonical_type": "list(card) -> bool",
      "mapped": false,
      "unmapped_reason": "fp_not_in_pool"
    },
    {
      "prog_str": "(\u03bb lt (suit_to_int HEARTS) (half_len (sort_by_rank $0)))",
      "visit_count": 3,
      "visit_mass": 7.499925000749993e-06,
      "parse_ok": true,
      "type_ok": true,
      "pruner_ok": true,
      "depth": 5,
      "size": 12,
      "in_d6_pool_hypothetical": true,
      "in_d7_pool_hypothetical": true,
      "in_d7_pool_actual": false,
      "fingerprint": "4ec297ba99da804fe1068f1a398d0de8c7ed84461f2efbfd59557f1f5c94ab96",
      "canonical_type": "list(card) -> bool",
      "mapped": false,
      "unmapped_reason": "fp_not_in_pool"
    },
    {
      "prog_str": "(\u03bb lt 0 (half_len (sort_by_rank $0)))",
      "visit_count": 11,
      "visit_mass": 2.7499725002749972e-05,
      "parse_ok": true,
      "type_ok": true,
      "pruner_ok": true,
      "depth": 5,
      "size": 10,
      "in_d6_pool_hypothetical": true,
      "in_d7_pool_hypothetical": true,
      "in_d7_pool_actual": false,
      "fingerprint": "4ec297ba99da804fe1068f1a398d0de8c7ed84461f2efbfd59557f1f5c94ab96",
      "canonical_type": "list(card) -> bool",
      "mapped": false,
      "unmapped_reason": "fp_not_in_pool"
    },
    {
      "prog_str": "(\u03bb lt 0 (n_unique_ranks $0))",
      "visit_count": 89,
      "visit_mass": 0.00022249777502224977,
      "parse_ok": true,
      "type_ok": true,
      "pruner_ok": true,
      "depth": 4,
      "size": 8,
      "in_d6_pool_hypothetical": true,
      "in_d7_pool_hypothetical": true,
      "in_d7_pool_actual": false,
      "fingerprint": "4ec297ba99da804fe1068f1a398d0de8c7ed84461f2efbfd59557f1f5c94ab96",
      "canonical_type": "list(card) -> bool",
      "mapped": false,
      "unmapped_reason": "fp_not_in_pool"
    },
    {
      "prog_str": "(\u03bb lt 0 (min_rank $0))",
      "visit_count": 68,
      "visit_mass": 0.00016999830001699983,
      "parse_ok": true,
      "type_ok": true,
      "pruner_ok": true,
      "depth": 4,
      "size": 8,
      "in_d6_pool_hypothetical": true,
      "in_d7_pool_hypothetical": true,
      "in_d7_pool_actual": false,
      "fingerprint": "4ec297ba99da804fe1068f1a398d0de8c7ed84461f2efbfd59557f1f5c94ab96",
      "canonical_type": "list(card) -> bool",
      "mapped": false,
      "unmapped_reason": "fp_not_in_pool"
    },
    {
      "prog_str": "(\u03bb lt 1 (min_rank $0))",
      "visit_count": 12,
      "visit_mass": 2.999970000299997e-05,
      "parse_ok": true,
      "type_ok": true,
      "pruner_ok": true,
      "depth": 4,
      "size": 8,
      "in_d6_pool_hypothetical": true,
      "in_d7_pool_hypothetical": true,
      "in_d7_pool_actual": false,
      "fingerprint": "4ec297ba99da804fe1068f1a398d0de8c7ed84461f2efbfd59557f1f5c94ab96",
      "canonical_type": "list(card) -> bool",
      "mapped": false,
      "unmapped_reason": "fp_not_in_pool"
    },
    {
      "prog_str": "(\u03bb lt 0 (sum_ranks $0))",
      "visit_count": 11,
      "visit_mass": 2.7499725002749972e-05,
      "parse_ok": true,
      "type_ok": true,
      "pruner_ok": true,
      "depth": 4,
      "size": 8,
      "in_d6_pool_hypothetical": true,
      "in_d7_pool_hypothetical": true,
      "in_d7_pool_actual": false,
      "fingerprint": "4ec297ba99da804fe1068f1a398d0de8c7ed84461f2efbfd59557f1f5c94ab96",
      "canonical_type": "list(card) -> bool",
      "mapped": false,
      "unmapped_reason": "fp_not_in_pool"
    },
    {
      "prog_str": "(\u03bb lt 4 (sum_ranks $0))",
      "visit_count": 15,
      "visit_mass": 3.749962500374996e-05,
      "parse_ok": true,
      "type_ok": true,
      "pruner_ok": true,
      "depth": 4,
      "size": 8,
      "in_d6_pool_hypothetical": true,
      "in_d7_pool_hypothetical": true,
      "in_d7_pool_actual": false,
      "fingerprint": "4ec297ba99da804fe1068f1a398d0de8c7ed84461f2efbfd59557f1f5c94ab96",
      "canonical_type": "list(card) -> bool",
      "mapped": false,
      "unmapped_reason": "fp_not_in_pool"
    },
    {
      "prog_str": "(\u03bb lt 2 (sum_ranks $0))",
      "visit_count": 12,
      "visit_mass": 2.999970000299997e-05,
      "parse_ok": true,
      "type_ok": true,
      "pruner_ok": true,
      "depth": 4,
      "size": 8,
      "in_d6_pool_hypothetical": true,
      "in_d7_pool_hypothetical": true,
      "in_d7_pool_actual": false,
      "fingerprint": "4ec297ba99da804fe1068f1a398d0de8c7ed84461f2efbfd59557f1f5c94ab96",
      "canonical_type": "list(card) -> bool",
      "mapped": false,
      "unmapped_reason": "fp_not_in_pool"
    },
    {
      "prog_str": "(\u03bb lt 1 (sum_ranks $0))",
      "visit_count": 23,
      "visit_mass": 5.749942500574994e-05,
      "parse_ok": true,
      "type_ok": true,
      "pruner_ok": true,
      "depth": 4,
      "size": 8,
      "in_d6_pool_hypothetical": true,
      "in_d7_pool_hypothetical": true,
      "in_d7_pool_actual": false,
      "fingerprint": "4ec297ba99da804fe1068f1a398d0de8c7ed84461f2efbfd59557f1f5c94ab96",
      "canonical_type": "list(card) -> bool",
      "mapped": false,
      "unmapped_reason": "fp_not_in_pool"
    },
    {
      "prog_str": "(\u03bb lt 3 (sum_ranks $0))",
      "visit_count": 20,
      "visit_mass": 4.999950000499995e-05,
      "parse_ok": true,
      "type_ok": true,
      "pruner_ok": true,
      "depth": 4,
      "size": 8,
      "in_d6_pool_hypothetical": true,
      "in_d7_pool_hypothetical": true,
      "in_d7_pool_actual": false,
      "fingerprint": "4ec297ba99da804fe1068f1a398d0de8c7ed84461f2efbfd59557f1f5c94ab96",
      "canonical_type": "list(card) -> bool",
      "mapped": false,
      "unmapped_reason": "fp_not_in_pool"
    },
    {
      "prog_str": "(\u03bb lt 5 (sum_ranks $0))",
      "visit_count": 2,
      "visit_mass": 4.999950000499995e-06,
      "parse_ok": true,
      "type_ok": true,
      "pruner_ok": true,
      "depth": 4,
      "size": 8,
      "in_d6_pool_hypothetical": true,
      "in_d7_pool_hypothetical": true,
      "in_d7_pool_actual": false,
      "fingerprint": "4ec297ba99da804fe1068f1a398d0de8c7ed84461f2efbfd59557f1f5c94ab96",
      "canonical_type": "list(card) -> bool",
      "mapped": false,
      "unmapped_reason": "fp_not_in_pool"
    },
    {
      "prog_str": "(\u03bb lt 1 (max_rank $0))",
      "visit_count": 23,
      "visit_mass": 5.749942500574994e-05,
      "parse_ok": true,
      "type_ok": true,
      "pruner_ok": true,
      "depth": 4,
      "size": 8,
      "in_d6_pool_hypothetical": true,
      "in_d7_pool_hypothetical": true,
      "in_d7_pool_actual": false,
      "fingerprint": "4ec297ba99da804fe1068f1a398d0de8c7ed84461f2efbfd59557f1f5c94ab96",
      "canonical_type": "list(card) -> bool",
      "mapped": false,
      "unmapped_reason": "fp_not_in_pool"
    },
    {
      "prog_str": "(\u03bb ge (rank_val (head $0)) 1)",
      "visit_count": 82,
      "visit_mass": 0.0002049979500204998,
      "parse_ok": true,
      "type_ok": true,
      "pruner_ok": true,
      "depth": 6,
      "size": 10,
      "in_d6_pool_hypothetical": true,
      "in_d7_pool_hypothetical": true,
      "in_d7_pool_actual": false,
      "fingerprint": "4ec297ba99da804fe1068f1a398d0de8c7ed84461f2efbfd59557f1f5c94ab96",
      "canonical_type": "list(card) -> bool",
      "mapped": false,
      "unmapped_reason": "fp_not_in_pool"
    },
    {
      "prog_str": "(\u03bb ge (rank_val (head $0)) 0)",
      "visit_count": 81,
      "visit_mass": 0.0002024979750202498,
      "parse_ok": true,
      "type_ok": true,
      "pruner_ok": true,
      "depth": 6,
      "size": 10,
      "in_d6_pool_hypothetical": true,
      "in_d7_pool_hypothetical": true,
      "in_d7_pool_actual": false,
      "fingerprint": "4ec297ba99da804fe1068f1a398d0de8c7ed84461f2efbfd59557f1f5c94ab96",
      "canonical_type": "list(card) -> bool",
      "mapped": false,
      "unmapped_reason": "fp_not_in_pool"
    },
    {
      "prog_str": "(\u03bb ge (rank_val (head $0)) 2)",
      "visit_count": 92,
      "visit_mass": 0.00022999770002299976,
      "parse_ok": true,
      "type_ok": true,
      "pruner_ok": true,
      "depth": 6,
      "size": 10,
      "in_d6_pool_hypothetical": true,
      "in_d7_pool_hypothetical": true,
      "in_d7_pool_actual": false,
      "fingerprint": "4ec297ba99da804fe1068f1a398d0de8c7ed84461f2efbfd59557f1f5c94ab96",
      "canonical_type": "list(card) -> bool",
      "mapped": false,
      "unmapped_reason": "fp_not_in_pool"
    },
    {
      "prog_str": "(\u03bb ge (rank_val (head $0)) (suit_to_int CLUBS))",
      "visit_count": 4,
      "visit_mass": 9.99990000099999e-06,
      "parse_ok": true,
      "type_ok": true,
      "pruner_ok": true,
      "depth": 6,
      "size": 12,
      "in_d6_pool_hypothetical": true,
      "in_d7_pool_hypothetical": true,
      "in_d7_pool_actual": false,
      "fingerprint": "4ec297ba99da804fe1068f1a398d0de8c7ed84461f2efbfd59557f1f5c94ab96",
      "canonical_type": "list(card) -> bool",
      "mapped": false,
      "unmapped_reason": "fp_not_in_pool"
    },
    {
      "prog_str": "(\u03bb ge (rank_val (head $0)) (suit_to_int HEARTS))",
      "visit_count": 10,
      "visit_mass": 2.4999750002499974e-05,
      "parse_ok": true,
      "type_ok": true,
      "pruner_ok": true,
      "depth": 6,
      "size": 12,
      "in_d6_pool_hypothetical": true,
      "in_d7_pool_hypothetical": true,
      "in_d7_pool_actual": false,
      "fingerprint": "4ec297ba99da804fe1068f1a398d0de8c7ed84461f2efbfd59557f1f5c94ab96",
      "canonical_type": "list(card) -> bool",
      "mapped": false,
      "unmapped_reason": "fp_not_in_pool"
    },
    {
      "prog_str": "(\u03bb ge (count_color $0 BLACK) 0)",
      "visit_count": 30,
      "visit_mass": 7.499925000749992e-05,
      "parse_ok": true,
      "type_ok": true,
      "pruner_ok": true,
      "depth": 6,
      "size": 10,
      "in_d6_pool_hypothetical": true,
      "in_d7_pool_hypothetical": true,
      "in_d7_pool_actual": false,
      "fingerprint": "4ec297ba99da804fe1068f1a398d0de8c7ed84461f2efbfd59557f1f5c94ab96",
      "canonical_type": "list(card) -> bool",
      "mapped": false,
      "unmapped_reason": "fp_not_in_pool"
    },
    {
      "prog_str": "(\u03bb ge (count_color $0 RED) 0)",
      "visit_count": 70,
      "visit_mass": 0.00017499825001749983,
      "parse_ok": true,
      "type_ok": true,
      "pruner_ok": true,
      "depth": 6,
      "size": 10,
      "in_d6_pool_hypothetical": true,
      "in_d7_pool_hypothetical": true,
      "in_d7_pool_actual": false,
      "fingerprint": "4ec297ba99da804fe1068f1a398d0de8c7ed84461f2efbfd59557f1f5c94ab96",
      "canonical_type": "list(card) -> bool",
      "mapped": false,
      "unmapped_reason": "fp_not_in_pool"
    },
    {
      "prog_str": "(\u03bb ge (n_unique_ranks $0) 2)",
      "visit_count": 18,
      "visit_mass": 4.499955000449995e-05,
      "parse_ok": true,
      "type_ok": true,
      "pruner_ok": true,
      "depth": 5,
      "size": 8,
      "in_d6_pool_hypothetical": true,
      "in_d7_pool_hypothetical": true,
      "in_d7_pool_actual": false,
      "fingerprint": "4ec297ba99da804fe1068f1a398d0de8c7ed84461f2efbfd59557f1f5c94ab96",
      "canonical_type": "list(card) -> bool",
      "mapped": false,
      "unmapped_reason": "fp_not_in_pool"
    },
    {
      "prog_str": "(\u03bb ge (n_unique_ranks $0) 0)",
      "visit_count": 34,
      "visit_mass": 8.499915000849992e-05,
      "parse_ok": true,
      "type_ok": true,
      "pruner_ok": true,
      "depth": 5,
      "size": 8,
      "in_d6_pool_hypothetical": true,
      "in_d7_pool_hypothetical": true,
      "in_d7_pool_actual": false,
      "fingerprint": "4ec297ba99da804fe1068f1a398d0de8c7ed84461f2efbfd59557f1f5c94ab96",
      "canonical_type": "list(card) -> bool",
      "mapped": false,
      "unmapped_reason": "fp_not_in_pool"
    },
    {
      "prog_str": "(\u03bb ge (n_unique_ranks $0) 1)",
      "visit_count": 18,
      "visit_mass": 4.499955000449995e-05,
      "parse_ok": true,
      "type_ok": true,
      "pruner_ok": true,
      "depth": 5,
      "size": 8,
      "in_d6_pool_hypothetical": true,
      "in_d7_pool_hypothetical": true,
      "in_d7_pool_actual": false,
      "fingerprint": "4ec297ba99da804fe1068f1a398d0de8c7ed84461f2efbfd59557f1f5c94ab96",
      "canonical_type": "list(card) -> bool",
      "mapped": false,
      "unmapped_reason": "fp_not_in_pool"
    },
    {
      "prog_str": "(\u03bb ge (n_unique_ranks (unique $0)) 1)",
      "visit_count": 22,
      "visit_mass": 5.4999450005499945e-05,
      "parse_ok": true,
      "type_ok": true,
      "pruner_ok": true,
      "depth": 6,
      "size": 10,
      "in_d6_pool_hypothetical": true,
      "in_d7_pool_hypothetical": true,
      "in_d7_pool_actual": false,
      "fingerprint": "4ec297ba99da804fe1068f1a398d0de8c7ed84461f2efbfd59557f1f5c94ab96",
      "canonical_type": "list(card) -> bool",
      "mapped": false,
      "unmapped_reason": "fp_not_in_pool"
    },
    {
      "prog_str": "(\u03bb ge (n_unique_ranks $0) (- 5 3))",
      "visit_count": 15,
      "visit_mass": 3.749962500374996e-05,
      "parse_ok": true,
      "type_ok": true,
      "pruner_ok": true,
      "depth": 5,
      "size": 12,
      "in_d6_pool_hypothetical": true,
      "in_d7_pool_hypothetical": true,
      "in_d7_pool_actual": false,
      "fingerprint": "4ec297ba99da804fe1068f1a398d0de8c7ed84461f2efbfd59557f1f5c94ab96",
      "canonical_type": "list(card) -> bool",
      "mapped": false,
      "unmapped_reason": "fp_not_in_pool"
    },
    {
      "prog_str": "(\u03bb ge (n_unique_ranks $0) (- 0 3))",
      "visit_count": 5,
      "visit_mass": 1.2499875001249987e-05,
      "parse_ok": true,
      "type_ok": true,
      "pruner_ok": true,
      "depth": 5,
      "size": 12,
      "in_d6_pool_hypothetical": true,
      "in_d7_pool_hypothetical": true,
      "in_d7_pool_actual": false,
      "fingerprint": "4ec297ba99da804fe1068f1a398d0de8c7ed84461f2efbfd59557f1f5c94ab96",
      "canonical_type": "list(card) -> bool",
      "mapped": false,
      "unmapped_reason": "fp_not_in_pool"
    },
    {
      "prog_str": "(\u03bb ge (n_unique_ranks $0) (- 0 5))",
      "visit_count": 2,
      "visit_mass": 4.999950000499995e-06,
      "parse_ok": true,
      "type_ok": true,
      "pruner_ok": true,
      "depth": 5,
      "size": 12,
      "in_d6_pool_hypothetical": true,
      "in_d7_pool_hypothetical": true,
      "in_d7_pool_actual": false,
      "fingerprint": "4ec297ba99da804fe1068f1a398d0de8c7ed84461f2efbfd59557f1f5c94ab96",
      "canonical_type": "list(card) -> bool",
      "mapped": false,
      "unmapped_reason": "fp_not_in_pool"
    },
    {
      "prog_str": "(\u03bb lt (count_color (second_half $0) RED) 4)",
      "visit_count": 53,
      "visit_mass": 0.00013249867501324988,
      "parse_ok": true,
      "type_ok": true,
      "pruner_ok": true,
      "depth": 7,
      "size": 12,
      "in_d6_pool_hypothetical": false,
      "in_d7_pool_hypothetical": true,
      "in_d7_pool_actual": false,
      "fingerprint": "4ec297ba99da804fe1068f1a398d0de8c7ed84461f2efbfd59557f1f5c94ab96",
      "canonical_type": "list(card) -> bool",
      "mapped": false,
      "unmapped_reason": "fp_not_in_pool"
    },
    {
      "prog_str": "(\u03bb lt (count_color (second_half $0) BLACK) 4)",
      "visit_count": 65,
      "visit_mass": 0.00016249837501624984,
      "parse_ok": true,
      "type_ok": true,
      "pruner_ok": true,
      "depth": 7,
      "size": 12,
      "in_d6_pool_hypothetical": false,
      "in_d7_pool_hypothetical": true,
      "in_d7_pool_actual": false,
      "fingerprint": "4ec297ba99da804fe1068f1a398d0de8c7ed84461f2efbfd59557f1f5c94ab96",
      "canonical_type": "list(card) -> bool",
      "mapped": false,
      "unmapped_reason": "fp_not_in_pool"
    },
    {
      "prog_str": "(\u03bb lt (count_color (second_half $0) BLACK) 5)",
      "visit_count": 3,
      "visit_mass": 7.499925000749993e-06,
      "parse_ok": true,
      "type_ok": true,
      "pruner_ok": true,
      "depth": 7,
      "size": 12,
      "in_d6_pool_hypothetical": false,
      "in_d7_pool_hypothetical": true,
      "in_d7_pool_actual": false,
      "fingerprint": "4ec297ba99da804fe1068f1a398d0de8c7ed84461f2efbfd59557f1f5c94ab96",
      "canonical_type": "list(card) -> bool",
      "mapped": false,
      "unmapped_reason": "fp_not_in_pool"
    },
    {
      "prog_str": "(\u03bb lt (count_color (second_half $0) RED) 5)",
      "visit_count": 2,
      "visit_mass": 4.999950000499995e-06,
      "parse_ok": true,
      "type_ok": true,
      "pruner_ok": true,
      "depth": 7,
      "size": 12,
      "in_d6_pool_hypothetical": false,
      "in_d7_pool_hypothetical": true,
      "in_d7_pool_actual": false,
      "fingerprint": "4ec297ba99da804fe1068f1a398d0de8c7ed84461f2efbfd59557f1f5c94ab96",
      "canonical_type": "list(card) -> bool",
      "mapped": false,
      "unmapped_reason": "fp_not_in_pool"
    },
    {
      "prog_str": "(\u03bb gt (n_unique_suits $0) 0)",
      "visit_count": 20,
      "visit_mass": 4.999950000499995e-05,
      "parse_ok": true,
      "type_ok": true,
      "pruner_ok": true,
      "depth": 5,
      "size": 8,
      "in_d6_pool_hypothetical": true,
      "in_d7_pool_hypothetical": true,
      "in_d7_pool_actual": false,
      "fingerprint": "4ec297ba99da804fe1068f1a398d0de8c7ed84461f2efbfd59557f1f5c94ab96",
      "canonical_type": "list(card) -> bool",
      "mapped": false,
      "unmapped_reason": "fp_not_in_pool"
    },
    {
      "prog_str": "(\u03bb gt (n_unique_suits (unique (drop 2 $0))) (n_unique_ranks $0))",
      "visit_count": 10528,
      "visit_mass": 0.026319736802631975,
      "parse_ok": true,
      "type_ok": true,
      "pruner_ok": true,
      "depth": 8,
      "size": 16,
      "in_d6_pool_hypothetical": false,
      "in_d7_pool_hypothetical": false,
      "in_d7_pool_actual": false,
      "fingerprint": "0841ea62d9232a98182d4125fc05cc900721f0b303549d552a96bd99a451c447",
      "canonical_type": "list(card) -> bool",
      "mapped": false,
      "unmapped_reason": "fp_not_in_pool"
    },
    {
      "prog_str": "(\u03bb gt (n_unique_suits (unique (drop 2 (unique $0)))) (n_unique_ranks $0))",
      "visit_count": 284,
      "visit_mass": 0.0007099929000709993,
      "parse_ok": true,
      "type_ok": true,
      "pruner_ok": false,
      "depth": 8,
      "size": 18,
      "in_d6_pool_hypothetical": false,
      "in_d7_pool_hypothetical": false,
      "in_d7_pool_actual": false,
      "fingerprint": "0841ea62d9232a98182d4125fc05cc900721f0b303549d552a96bd99a451c447",
      "canonical_type": "list(card) -> bool",
      "mapped": false,
      "unmapped_reason": "fp_not_in_pool"
    },
    {
      "prog_str": "(\u03bb gt (n_unique_suits (unique (drop 2 $0))) (n_unique_ranks (sort_by_rank $0)))",
      "visit_count": 279,
      "visit_mass": 0.0006974930250697493,
      "parse_ok": true,
      "type_ok": true,
      "pruner_ok": true,
      "depth": 8,
      "size": 18,
      "in_d6_pool_hypothetical": false,
      "in_d7_pool_hypothetical": false,
      "in_d7_pool_actual": false,
      "fingerprint": "0841ea62d9232a98182d4125fc05cc900721f0b303549d552a96bd99a451c447",
      "canonical_type": "list(card) -> bool",
      "mapped": false,
      "unmapped_reason": "fp_not_in_pool"
    },
    {
      "prog_str": "(\u03bb gt (n_unique_suits (unique (drop (suit_to_int CLUBS) $0))) (n_unique_ranks $0))",
      "visit_count": 103,
      "visit_mass": 0.00025749742502574976,
      "parse_ok": true,
      "type_ok": true,
      "pruner_ok": true,
      "depth": 9,
      "size": 18,
      "in_d6_pool_hypothetical": false,
      "in_d7_pool_hypothetical": false,
      "in_d7_pool_actual": false,
      "fingerprint": "0841ea62d9232a98182d4125fc05cc900721f0b303549d552a96bd99a451c447",
      "canonical_type": "list(card) -> bool",
      "mapped": false,
      "unmapped_reason": "fp_not_in_pool"
    },
    {
      "prog_str": "(\u03bb gt (n_unique_suits (unique (drop 2 $0))) (n_unique_ranks (unique $0)))",
      "visit_count": 45,
      "visit_mass": 0.00011249887501124989,
      "parse_ok": true,
      "type_ok": true,
      "pruner_ok": true,
      "depth": 8,
      "size": 18,
      "in_d6_pool_hypothetical": false,
      "in_d7_pool_hypothetical": false,
      "in_d7_pool_actual": false,
      "fingerprint": "0841ea62d9232a98182d4125fc05cc900721f0b303549d552a96bd99a451c447",
      "canonical_type": "list(card) -> bool",
      "mapped": false,
      "unmapped_reason": "fp_not_in_pool"
    },
    {
      "prog_str": "(\u03bb gt (n_unique_suits (unique (drop (n_unique_colors (take 4 $0)) $0))) (n_unique_ranks $0))",
      "visit_count": 36,
      "visit_mass": 8.99991000089999e-05,
      "parse_ok": true,
      "type_ok": true,
      "pruner_ok": true,
      "depth": 11,
      "size": 22,
      "in_d6_pool_hypothetical": false,
      "in_d7_pool_hypothetical": false,
      "in_d7_pool_actual": false,
      "fingerprint": "0841ea62d9232a98182d4125fc05cc900721f0b303549d552a96bd99a451c447",
      "canonical_type": "list(card) -> bool",
      "mapped": false,
      "unmapped_reason": "fp_not_in_pool"
    },
    {
      "prog_str": "(\u03bb gt (n_unique_suits (unique (drop (n_unique_colors (sort_by_rank $0)) $0))) (n_unique_ranks $0))",
      "visit_count": 40,
      "visit_mass": 9.99990000099999e-05,
      "parse_ok": true,
      "type_ok": true,
      "pruner_ok": true,
      "depth": 10,
      "size": 20,
      "in_d6_pool_hypothetical": false,
      "in_d7_pool_hypothetical": false,
      "in_d7_pool_actual": false,
      "fingerprint": "0841ea62d9232a98182d4125fc05cc900721f0b303549d552a96bd99a451c447",
      "canonical_type": "list(card) -> bool",
      "mapped": false,
      "unmapped_reason": "fp_not_in_pool"
    },
    {
      "prog_str": "(\u03bb gt (n_unique_suits (unique (drop (n_unique_colors (reverse $0)) $0))) (n_unique_ranks $0))",
      "visit_count": 8,
      "visit_mass": 1.999980000199998e-05,
      "parse_ok": true,
      "type_ok": true,
      "pruner_ok": true,
      "depth": 10,
      "size": 20,
      "in_d6_pool_hypothetical": false,
      "in_d7_pool_hypothetical": false,
      "in_d7_pool_actual": false,
      "fingerprint": "0841ea62d9232a98182d4125fc05cc900721f0b303549d552a96bd99a451c447",
      "canonical_type": "list(card) -> bool",
      "mapped": false,
      "unmapped_reason": "fp_not_in_pool"
    },
    {
      "prog_str": "(\u03bb gt (n_unique_suits (unique (drop (n_unique_colors $0) $0))) (n_unique_ranks $0))",
      "visit_count": 164,
      "visit_mass": 0.0004099959000409996,
      "parse_ok": true,
      "type_ok": true,
      "pruner_ok": true,
      "depth": 9,
      "size": 18,
      "in_d6_pool_hypothetical": false,
      "in_d7_pool_hypothetical": false,
      "in_d7_pool_actual": false,
      "fingerprint": "0841ea62d9232a98182d4125fc05cc900721f0b303549d552a96bd99a451c447",
      "canonical_type": "list(card) -> bool",
      "mapped": false,
      "unmapped_reason": "fp_not_in_pool"
    },
    {
      "prog_str": "(\u03bb gt (n_unique_suits (drop (max_suit_count (take 4 $0)) $0)) (n_unique_ranks $0))",
      "visit_count": 11,
      "visit_mass": 2.7499725002749972e-05,
      "parse_ok": true,
      "type_ok": true,
      "pruner_ok": true,
      "depth": 10,
      "size": 20,
      "in_d6_pool_hypothetical": false,
      "in_d7_pool_hypothetical": false,
      "in_d7_pool_actual": false,
      "fingerprint": "0841ea62d9232a98182d4125fc05cc900721f0b303549d552a96bd99a451c447",
      "canonical_type": "list(card) -> bool",
      "mapped": false,
      "unmapped_reason": "fp_not_in_pool"
    },
    {
      "prog_str": "(\u03bb gt (n_unique_suits (drop (max_suit_count $0) $0)) (n_unique_ranks $0))",
      "visit_count": 167,
      "visit_mass": 0.0004174958250417496,
      "parse_ok": true,
      "type_ok": true,
      "pruner_ok": true,
      "depth": 8,
      "size": 16,
      "in_d6_pool_hypothetical": false,
      "in_d7_pool_hypothetical": false,
      "in_d7_pool_actual": false,
      "fingerprint": "0841ea62d9232a98182d4125fc05cc900721f0b303549d552a96bd99a451c447",
      "canonical_type": "list(card) -> bool",
      "mapped": false,
      "unmapped_reason": "fp_not_in_pool"
    },
    {
      "prog_str": "(\u03bb gt (n_unique_suits (drop (n_unique_colors $0) $0)) (n_unique_ranks $0))",
      "visit_count": 84,
      "visit_mass": 0.0002099979000209998,
      "parse_ok": true,
      "type_ok": true,
      "pruner_ok": true,
      "depth": 8,
      "size": 16,
      "in_d6_pool_hypothetical": false,
      "in_d7_pool_hypothetical": false,
      "in_d7_pool_actual": false,
      "fingerprint": "0841ea62d9232a98182d4125fc05cc900721f0b303549d552a96bd99a451c447",
      "canonical_type": "list(card) -> bool",
      "mapped": false,
      "unmapped_reason": "fp_not_in_pool"
    },
    {
      "prog_str": "(\u03bb gt (count_color $0 BLACK) (- 0 3))",
      "visit_count": 9,
      "visit_mass": 2.2499775002249976e-05,
      "parse_ok": true,
      "type_ok": true,
      "pruner_ok": true,
      "depth": 6,
      "size": 14,
      "in_d6_pool_hypothetical": true,
      "in_d7_pool_hypothetical": true,
      "in_d7_pool_actual": false,
      "fingerprint": "4ec297ba99da804fe1068f1a398d0de8c7ed84461f2efbfd59557f1f5c94ab96",
      "canonical_type": "list(card) -> bool",
      "mapped": false,
      "unmapped_reason": "fp_not_in_pool"
    },
    {
      "prog_str": "(\u03bb gt (sum_ranks (second_half $0)) 1)",
      "visit_count": 1,
      "visit_mass": 2.4999750002499977e-06,
      "parse_ok": true,
      "type_ok": true,
      "pruner_ok": true,
      "depth": 6,
      "size": 10,
      "in_d6_pool_hypothetical": true,
      "in_d7_pool_hypothetical": true,
      "in_d7_pool_actual": false,
      "fingerprint": "4ec297ba99da804fe1068f1a398d0de8c7ed84461f2efbfd59557f1f5c94ab96",
      "canonical_type": "list(card) -> bool",
      "mapped": false,
      "unmapped_reason": "fp_not_in_pool"
    },
    {
      "prog_str": "(\u03bb gt (sum_ranks (second_half $0)) 0)",
      "visit_count": 24,
      "visit_mass": 5.999940000599994e-05,
      "parse_ok": true,
      "type_ok": true,
      "pruner_ok": true,
      "depth": 6,
      "size": 10,
      "in_d6_pool_hypothetical": true,
      "in_d7_pool_hypothetical": true,
      "in_d7_pool_actual": false,
      "fingerprint": "4ec297ba99da804fe1068f1a398d0de8c7ed84461f2efbfd59557f1f5c94ab96",
      "canonical_type": "list(card) -> bool",
      "mapped": false,
      "unmapped_reason": "fp_not_in_pool"
    },
    {
      "prog_str": "(\u03bb gt (sum_ranks $0) 0)",
      "visit_count": 5,
      "visit_mass": 1.2499875001249987e-05,
      "parse_ok": true,
      "type_ok": true,
      "pruner_ok": true,
      "depth": 5,
      "size": 8,
      "in_d6_pool_hypothetical": true,
      "in_d7_pool_hypothetical": true,
      "in_d7_pool_actual": false,
      "fingerprint": "4ec297ba99da804fe1068f1a398d0de8c7ed84461f2efbfd59557f1f5c94ab96",
      "canonical_type": "list(card) -> bool",
      "mapped": false,
      "unmapped_reason": "fp_not_in_pool"
    },
    {
      "prog_str": "(\u03bb gt (sum_ranks $0) 3)",
      "visit_count": 21,
      "visit_mass": 5.249947500524995e-05,
      "parse_ok": true,
      "type_ok": true,
      "pruner_ok": true,
      "depth": 5,
      "size": 8,
      "in_d6_pool_hypothetical": true,
      "in_d7_pool_hypothetical": true,
      "in_d7_pool_actual": false,
      "fingerprint": "4ec297ba99da804fe1068f1a398d0de8c7ed84461f2efbfd59557f1f5c94ab96",
      "canonical_type": "list(card) -> bool",
      "mapped": false,
      "unmapped_reason": "fp_not_in_pool"
    },
    {
      "prog_str": "(\u03bb gt (sum_ranks $0) 2)",
      "visit_count": 127,
      "visit_mass": 0.0003174968250317497,
      "parse_ok": true,
      "type_ok": true,
      "pruner_ok": true,
      "depth": 5,
      "size": 8,
      "in_d6_pool_hypothetical": true,
      "in_d7_pool_hypothetical": true,
      "in_d7_pool_actual": false,
      "fingerprint": "4ec297ba99da804fe1068f1a398d0de8c7ed84461f2efbfd59557f1f5c94ab96",
      "canonical_type": "list(card) -> bool",
      "mapped": false,
      "unmapped_reason": "fp_not_in_pool"
    },
    {
      "prog_str": "(\u03bb gt (sum_ranks $0) 1)",
      "visit_count": 70,
      "visit_mass": 0.00017499825001749983,
      "parse_ok": true,
      "type_ok": true,
      "pruner_ok": true,
      "depth": 5,
      "size": 8,
      "in_d6_pool_hypothetical": true,
      "in_d7_pool_hypothetical": true,
      "in_d7_pool_actual": false,
      "fingerprint": "4ec297ba99da804fe1068f1a398d0de8c7ed84461f2efbfd59557f1f5c94ab96",
      "canonical_type": "list(card) -> bool",
      "mapped": false,
      "unmapped_reason": "fp_not_in_pool"
    },
    {
      "prog_str": "(\u03bb gt (sum_ranks $0) 5)",
      "visit_count": 23,
      "visit_mass": 5.749942500574994e-05,
      "parse_ok": true,
      "type_ok": true,
      "pruner_ok": true,
      "depth": 5,
      "size": 8,
      "in_d6_pool_hypothetical": true,
      "in_d7_pool_hypothetical": true,
      "in_d7_pool_actual": false,
      "fingerprint": "4ec297ba99da804fe1068f1a398d0de8c7ed84461f2efbfd59557f1f5c94ab96",
      "canonical_type": "list(card) -> bool",
      "mapped": false,
      "unmapped_reason": "fp_not_in_pool"
    },
    {
      "prog_str": "(\u03bb gt (n_unique_colors $0) 0)",
      "visit_count": 71,
      "visit_mass": 0.00017749822501774982,
      "parse_ok": true,
      "type_ok": true,
      "pruner_ok": true,
      "depth": 5,
      "size": 8,
      "in_d6_pool_hypothetical": true,
      "in_d7_pool_hypothetical": true,
      "in_d7_pool_actual": false,
      "fingerprint": "4ec297ba99da804fe1068f1a398d0de8c7ed84461f2efbfd59557f1f5c94ab96",
      "canonical_type": "list(card) -> bool",
      "mapped": false,
      "unmapped_reason": "fp_not_in_pool"
    },
    {
      "prog_str": "(\u03bb gt (n_unique_colors (sort_by_rank (first_half $0))) 0)",
      "visit_count": 19,
      "visit_mass": 4.7499525004749954e-05,
      "parse_ok": true,
      "type_ok": true,
      "pruner_ok": true,
      "depth": 7,
      "size": 12,
      "in_d6_pool_hypothetical": false,
      "in_d7_pool_hypothetical": true,
      "in_d7_pool_actual": false,
      "fingerprint": "4ec297ba99da804fe1068f1a398d0de8c7ed84461f2efbfd59557f1f5c94ab96",
      "canonical_type": "list(card) -> bool",
      "mapped": false,
      "unmapped_reason": "fp_not_in_pool"
    },
    {
      "prog_str": "(\u03bb gt (n_unique_ranks (head (adjacent_pairs $0))) 0)",
      "visit_count": 59,
      "visit_mass": 0.00014749852501474986,
      "parse_ok": true,
      "type_ok": true,
      "pruner_ok": true,
      "depth": 7,
      "size": 12,
      "in_d6_pool_hypothetical": false,
      "in_d7_pool_hypothetical": true,
      "in_d7_pool_actual": false,
      "fingerprint": "4ec297ba99da804fe1068f1a398d0de8c7ed84461f2efbfd59557f1f5c94ab96",
      "canonical_type": "list(card) -> bool",
      "mapped": false,
      "unmapped_reason": "fp_not_in_pool"
    },
    {
      "prog_str": "(\u03bb gt (n_unique_ranks $0) 0)",
      "visit_count": 3,
      "visit_mass": 7.499925000749993e-06,
      "parse_ok": true,
      "type_ok": true,
      "pruner_ok": true,
      "depth": 5,
      "size": 8,
      "in_d6_pool_hypothetical": true,
      "in_d7_pool_hypothetical": true,
      "in_d7_pool_actual": false,
      "fingerprint": "4ec297ba99da804fe1068f1a398d0de8c7ed84461f2efbfd59557f1f5c94ab96",
      "canonical_type": "list(card) -> bool",
      "mapped": false,
      "unmapped_reason": "fp_not_in_pool"
    },
    {
      "prog_str": "(\u03bb gt (n_unique_ranks $0) 1)",
      "visit_count": 80,
      "visit_mass": 0.0001999980000199998,
      "parse_ok": true,
      "type_ok": true,
      "pruner_ok": true,
      "depth": 5,
      "size": 8,
      "in_d6_pool_hypothetical": true,
      "in_d7_pool_hypothetical": true,
      "in_d7_pool_actual": false,
      "fingerprint": "4ec297ba99da804fe1068f1a398d0de8c7ed84461f2efbfd59557f1f5c94ab96",
      "canonical_type": "list(card) -> bool",
      "mapped": false,
      "unmapped_reason": "fp_not_in_pool"
    },
    {
      "prog_str": "(\u03bb gt 5 (n_unique_colors (first_half $0)))",
      "visit_count": 5,
      "visit_mass": 1.2499875001249987e-05,
      "parse_ok": true,
      "type_ok": true,
      "pruner_ok": true,
      "depth": 5,
      "size": 10,
      "in_d6_pool_hypothetical": true,
      "in_d7_pool_hypothetical": true,
      "in_d7_pool_actual": false,
      "fingerprint": "4ec297ba99da804fe1068f1a398d0de8c7ed84461f2efbfd59557f1f5c94ab96",
      "canonical_type": "list(card) -> bool",
      "mapped": false,
      "unmapped_reason": "fp_not_in_pool"
    },
    {
      "prog_str": "(\u03bb gt 3 (n_unique_colors (first_half $0)))",
      "visit_count": 4,
      "visit_mass": 9.99990000099999e-06,
      "parse_ok": true,
      "type_ok": true,
      "pruner_ok": true,
      "depth": 5,
      "size": 10,
      "in_d6_pool_hypothetical": true,
      "in_d7_pool_hypothetical": true,
      "in_d7_pool_actual": false,
      "fingerprint": "4ec297ba99da804fe1068f1a398d0de8c7ed84461f2efbfd59557f1f5c94ab96",
      "canonical_type": "list(card) -> bool",
      "mapped": false,
      "unmapped_reason": "fp_not_in_pool"
    },
    {
      "prog_str": "(\u03bb gt 5 (n_unique_colors $0))",
      "visit_count": 170,
      "visit_mass": 0.0004249957500424996,
      "parse_ok": true,
      "type_ok": true,
      "pruner_ok": true,
      "depth": 4,
      "size": 8,
      "in_d6_pool_hypothetical": true,
      "in_d7_pool_hypothetical": true,
      "in_d7_pool_actual": false,
      "fingerprint": "4ec297ba99da804fe1068f1a398d0de8c7ed84461f2efbfd59557f1f5c94ab96",
      "canonical_type": "list(card) -> bool",
      "mapped": false,
      "unmapped_reason": "fp_not_in_pool"
    },
    {
      "prog_str": "(\u03bb gt 4 (n_unique_colors $0))",
      "visit_count": 99,
      "visit_mass": 0.00024749752502474976,
      "parse_ok": true,
      "type_ok": true,
      "pruner_ok": true,
      "depth": 4,
      "size": 8,
      "in_d6_pool_hypothetical": true,
      "in_d7_pool_hypothetical": true,
      "in_d7_pool_actual": false,
      "fingerprint": "4ec297ba99da804fe1068f1a398d0de8c7ed84461f2efbfd59557f1f5c94ab96",
      "canonical_type": "list(card) -> bool",
      "mapped": false,
      "unmapped_reason": "fp_not_in_pool"
    },
    {
      "prog_str": "(\u03bb gt 4 (n_unique_colors (first_half $0)))",
      "visit_count": 10,
      "visit_mass": 2.4999750002499974e-05,
      "parse_ok": true,
      "type_ok": true,
      "pruner_ok": true,
      "depth": 5,
      "size": 10,
      "in_d6_pool_hypothetical": true,
      "in_d7_pool_hypothetical": true,
      "in_d7_pool_actual": false,
      "fingerprint": "4ec297ba99da804fe1068f1a398d0de8c7ed84461f2efbfd59557f1f5c94ab96",
      "canonical_type": "list(card) -> bool",
      "mapped": false,
      "unmapped_reason": "fp_not_in_pool"
    },
    {
      "prog_str": "(\u03bb gt (suit_to_int SPADES) (n_unique_colors $0))",
      "visit_count": 5,
      "visit_mass": 1.2499875001249987e-05,
      "parse_ok": true,
      "type_ok": true,
      "pruner_ok": true,
      "depth": 5,
      "size": 10,
      "in_d6_pool_hypothetical": true,
      "in_d7_pool_hypothetical": true,
      "in_d7_pool_actual": false,
      "fingerprint": "4ec297ba99da804fe1068f1a398d0de8c7ed84461f2efbfd59557f1f5c94ab96",
      "canonical_type": "list(card) -> bool",
      "mapped": false,
      "unmapped_reason": "fp_not_in_pool"
    },
    {
      "prog_str": "(\u03bb gt 5 (n_repeated_ranks (reverse $0)))",
      "visit_count": 27,
      "visit_mass": 6.749932500674993e-05,
      "parse_ok": true,
      "type_ok": true,
      "pruner_ok": true,
      "depth": 5,
      "size": 10,
      "in_d6_pool_hypothetical": true,
      "in_d7_pool_hypothetical": true,
      "in_d7_pool_actual": false,
      "fingerprint": "4ec297ba99da804fe1068f1a398d0de8c7ed84461f2efbfd59557f1f5c94ab96",
      "canonical_type": "list(card) -> bool",
      "mapped": false,
      "unmapped_reason": "fp_not_in_pool"
    },
    {
      "prog_str": "(\u03bb gt 5 (n_repeated_ranks (first_half (first_half $0))))",
      "visit_count": 5,
      "visit_mass": 1.2499875001249987e-05,
      "parse_ok": true,
      "type_ok": true,
      "pruner_ok": true,
      "depth": 6,
      "size": 12,
      "in_d6_pool_hypothetical": true,
      "in_d7_pool_hypothetical": true,
      "in_d7_pool_actual": false,
      "fingerprint": "4ec297ba99da804fe1068f1a398d0de8c7ed84461f2efbfd59557f1f5c94ab96",
      "canonical_type": "list(card) -> bool",
      "mapped": false,
      "unmapped_reason": "fp_not_in_pool"
    },
    {
      "prog_str": "(\u03bb gt 5 (n_unique_suits (second_half $0)))",
      "visit_count": 81,
      "visit_mass": 0.0002024979750202498,
      "parse_ok": true,
      "type_ok": true,
      "pruner_ok": true,
      "depth": 5,
      "size": 10,
      "in_d6_pool_hypothetical": true,
      "in_d7_pool_hypothetical": true,
      "in_d7_pool_actual": false,
      "fingerprint": "4ec297ba99da804fe1068f1a398d0de8c7ed84461f2efbfd59557f1f5c94ab96",
      "canonical_type": "list(card) -> bool",
      "mapped": false,
      "unmapped_reason": "fp_not_in_pool"
    },
    {
      "prog_str": "(\u03bb gt 5 (n_unique_suits (sort_by_rank $0)))",
      "visit_count": 14,
      "visit_mass": 3.499965000349997e-05,
      "parse_ok": true,
      "type_ok": true,
      "pruner_ok": true,
      "depth": 5,
      "size": 10,
      "in_d6_pool_hypothetical": true,
      "in_d7_pool_hypothetical": true,
      "in_d7_pool_actual": false,
      "fingerprint": "4ec297ba99da804fe1068f1a398d0de8c7ed84461f2efbfd59557f1f5c94ab96",
      "canonical_type": "list(card) -> bool",
      "mapped": false,
      "unmapped_reason": "fp_not_in_pool"
    },
    {
      "prog_str": "(\u03bb gt 5 (n_unique_suits $0))",
      "visit_count": 239,
      "visit_mass": 0.0005974940250597494,
      "parse_ok": true,
      "type_ok": true,
      "pruner_ok": true,
      "depth": 4,
      "size": 8,
      "in_d6_pool_hypothetical": true,
      "in_d7_pool_hypothetical": true,
      "in_d7_pool_actual": false,
      "fingerprint": "4ec297ba99da804fe1068f1a398d0de8c7ed84461f2efbfd59557f1f5c94ab96",
      "canonical_type": "list(card) -> bool",
      "mapped": false,
      "unmapped_reason": "fp_not_in_pool"
    },
    {
      "prog_str": "(\u03bb gt (n_unique_suits (reverse (drop 2 (unique $0)))) (n_unique_ranks $0))",
      "visit_count": 176,
      "visit_mass": 0.00043999560004399956,
      "parse_ok": true,
      "type_ok": true,
      "pruner_ok": false,
      "depth": 8,
      "size": 18,
      "in_d6_pool_hypothetical": false,
      "in_d7_pool_hypothetical": false,
      "in_d7_pool_actual": false,
      "fingerprint": "0841ea62d9232a98182d4125fc05cc900721f0b303549d552a96bd99a451c447",
      "canonical_type": "list(card) -> bool",
      "mapped": false,
      "unmapped_reason": "fp_not_in_pool"
    },
    {
      "prog_str": "(\u03bb gt (n_unique_suits (reverse (drop 2 $0))) (n_unique_ranks (reverse (sort_by_rank $0))))",
      "visit_count": 20,
      "visit_mass": 4.999950000499995e-05,
      "parse_ok": true,
      "type_ok": true,
      "pruner_ok": true,
      "depth": 8,
      "size": 20,
      "in_d6_pool_hypothetical": false,
      "in_d7_pool_hypothetical": false,
      "in_d7_pool_actual": false,
      "fingerprint": "0841ea62d9232a98182d4125fc05cc900721f0b303549d552a96bd99a451c447",
      "canonical_type": "list(card) -> bool",
      "mapped": false,
      "unmapped_reason": "fp_not_in_pool"
    },
    {
      "prog_str": "(\u03bb gt (n_unique_suits (reverse (drop (suit_to_int CLUBS) $0))) (n_unique_ranks (reverse $0)))",
      "visit_count": 101,
      "visit_mass": 0.00025249747502524973,
      "parse_ok": true,
      "type_ok": true,
      "pruner_ok": true,
      "depth": 9,
      "size": 20,
      "in_d6_pool_hypothetical": false,
      "in_d7_pool_hypothetical": false,
      "in_d7_pool_actual": false,
      "fingerprint": "0841ea62d9232a98182d4125fc05cc900721f0b303549d552a96bd99a451c447",
      "canonical_type": "list(card) -> bool",
      "mapped": false,
      "unmapped_reason": "fp_not_in_pool"
    },
    {
      "prog_str": "(\u03bb gt (n_unique_suits (sort_by_rank (drop (- 3 1) $0))) (n_unique_ranks $0))",
      "visit_count": 39,
      "visit_mass": 9.74990250097499e-05,
      "parse_ok": true,
      "type_ok": true,
      "pruner_ok": true,
      "depth": 10,
      "size": 20,
      "in_d6_pool_hypothetical": false,
      "in_d7_pool_hypothetical": false,
      "in_d7_pool_actual": false,
      "fingerprint": "0841ea62d9232a98182d4125fc05cc900721f0b303549d552a96bd99a451c447",
      "canonical_type": "list(card) -> bool",
      "mapped": false,
      "unmapped_reason": "fp_not_in_pool"
    },
    {
      "prog_str": "(\u03bb gt (n_unique_suits (drop (suit_to_int CLUBS) (unique $0))) (n_unique_ranks $0))",
      "visit_count": 5,
      "visit_mass": 1.2499875001249987e-05,
      "parse_ok": true,
      "type_ok": true,
      "pruner_ok": true,
      "depth": 8,
      "size": 18,
      "in_d6_pool_hypothetical": false,
      "in_d7_pool_hypothetical": false,
      "in_d7_pool_actual": false,
      "fingerprint": "0841ea62d9232a98182d4125fc05cc900721f0b303549d552a96bd99a451c447",
      "canonical_type": "list(card) -> bool",
      "mapped": false,
      "unmapped_reason": "fp_not_in_pool"
    },
    {
      "prog_str": "(\u03bb gt (n_unique_suits (drop (- 4 2) $0)) (n_unique_ranks $0))",
      "visit_count": 116,
      "visit_mass": 0.0002899971000289997,
      "parse_ok": true,
      "type_ok": true,
      "pruner_ok": true,
      "depth": 9,
      "size": 18,
      "in_d6_pool_hypothetical": false,
      "in_d7_pool_hypothetical": false,
      "in_d7_pool_actual": false,
      "fingerprint": "0841ea62d9232a98182d4125fc05cc900721f0b303549d552a96bd99a451c447",
      "canonical_type": "list(card) -> bool",
      "mapped": false,
      "unmapped_reason": "fp_not_in_pool"
    },
    {
      "prog_str": "(\u03bb gt (n_unique_suits (drop (suit_to_int CLUBS) $0)) (n_unique_ranks (sort_by_rank $0)))",
      "visit_count": 210,
      "visit_mass": 0.0005249947500524995,
      "parse_ok": true,
      "type_ok": true,
      "pruner_ok": true,
      "depth": 8,
      "size": 18,
      "in_d6_pool_hypothetical": false,
      "in_d7_pool_hypothetical": false,
      "in_d7_pool_actual": false,
      "fingerprint": "0841ea62d9232a98182d4125fc05cc900721f0b303549d552a96bd99a451c447",
      "canonical_type": "list(card) -> bool",
      "mapped": false,
      "unmapped_reason": "fp_not_in_pool"
    }
  ]
}