[
  {
    "variant": "baseline",
    "removed": [],
    "n_primitives": 59,
    "tasks_solved_final": 0,
    "tasks_ever_solved": 0,
    "total_tasks": 44,
    "solve_rate": 0.0,
    "avg_depth": 0,
    "max_depth": 0,
    "total_programs": 8800000,
    "total_time": 250.1789300441742
  },
  {
    "variant": "no_gestalt",
    "removed": [
      "all_same_suit",
      "all_same_color"
    ],
    "n_primitives": 57,
    "tasks_solved_final": 0,
    "tasks_ever_solved": 0,
    "total_tasks": 44,
    "solve_rate": 0.0,
    "avg_depth": 0,
    "max_depth": 0,
    "total_programs": 8800000,
    "total_time": 338.86452078819275
  },
  {
    "variant": "minimal",
    "removed": [
      "first_half",
      "second_half",
      "has_suit",
      "has_color",
      "count_suit",
      "count_color",
      "all_same_suit",
      "all_same_color",
      "n_unique_suits",
      "n_unique_ranks",
      "n_unique_colors"
    ],
    "n_primitives": 48,
    "tasks_solved_final": 0,
    "tasks_ever_solved": 0,
    "total_tasks": 44,
    "solve_rate": 0.0,
    "avg_depth": 0,
    "max_depth": 0,
    "total_programs": 8800000,
    "total_time": 256.14526867866516
  }
]