{"rule_id": "all_clubs_or_hearts", "n_chains": 4, "n_unique_merged": 244, "n_unique_per_chain": [50, 78, 92, 66], "acceptance_rate_per_chain": [0.03495, 0.0342, 0.06245, 0.07235], "total_accepted": 4079, "total_steps": 80000, "best_program": "(\u03bb lt (n_unique_suits $0) 3)", "best_log_posterior": -140.40766971803356, "visit_counts": {"(\u03bb ge (count_suit (at (adjacent_pairs $0) 2) SPADES) 5)": 4, "(\u03bb ge (count_suit (at (adjacent_pairs $0) 5) SPADES) 5)": 26, "(\u03bb ge (count_suit (at (adjacent_pairs $0) 5) HEARTS) 5)": 22, "(\u03bb ge (count_suit (at (adjacent_pairs $0) 5) HEARTS) 0)": 7, "(\u03bb ge (count_suit (at (adjacent_pairs $0) 5) DIAMONDS) 0)": 1, "(\u03bb ge (sum_ranks (first_half $0)) 0)": 29, "(\u03bb ge (sum_ranks (first_half $0)) (signum 2))": 36, "(\u03bb ge (sum_ranks (unique $0)) (signum 2))": 7, "(\u03bb ge (sum_ranks (unique $0)) (signum 1))": 6, "(\u03bb ge (sum_ranks (unique (unique $0))) (signum 1))": 8, "(\u03bb ge (sum_ranks (unique (unique $0))) 5)": 7, "(\u03bb ge (sum_ranks (sort_by_rank (reverse $0))) 5)": 10, "(\u03bb ge (sum_ranks (sort_by_rank (reverse $0))) 2)": 3, "(\u03bb ge (rank_val (at $0 (- 3 1))) 2)": 1, "(\u03bb ge (rank_val (head $0)) 2)": 233, "(\u03bb ge (n_unique_ranks $0) 2)": 125, "(\u03bb ge (max_rank $0) 2)": 15, "(\u03bb ge (max_rank $0) 5)": 20, "(\u03bb ge (sum_ranks $0) 5)": 167, "(\u03bb ge (sum_ranks $0) 0)": 1, "(\u03bb ge (sum_ranks $0) 4)": 16, "(\u03bb ge (sum_ranks $0) 2)": 7, "(\u03bb ge (sum_ranks $0) 1)": 26, "(\u03bb ge (sum_ranks $0) (+ 4 1))": 6, "(\u03bb ge (sum_ranks $0) (+ 3 1))": 1, "(\u03bb ge (sum_ranks $0) 3)": 42, "(\u03bb has_color $0 RED)": 4564, "(\u03bb has_color $0 BLACK)": 4191, "(\u03bb has_color (unique $0) RED)": 105, "(\u03bb has_color (unique $0) BLACK)": 91, "(\u03bb lt (n_unique_suits $0) 3)": 16431, "(\u03bb lt (n_unique_suits (reverse $0)) 3)": 659, "(\u03bb lt (n_unique_suits $0) 5)": 65, "(\u03bb lt (n_unique_suits $0) 4)": 57, "(\u03bb lt (n_unique_suits $0) (+ 1 2))": 246, "(\u03bb lt (n_unique_suits (unique $0)) 3)": 200, "(\u03bb lt (n_unique_suits (unique (sort_by_rank $0))) 3)": 22, "(\u03bb lt (n_unique_suits (sort_by_rank $0)) 3)": 300, "(\u03bb lt (n_unique_suits $0) (suit_to_int SPADES))": 44, "(\u03bb lt (n_unique_suits (reverse (sort_by_rank $0))) 3)": 12, "(\u03bb lt (n_unique_suits (sort_by_rank $0)) (half_len $0))": 17, "(\u03bb lt (n_unique_suits $0) (half_len $0))": 387, "(\u03bb lt (n_unique_suits $0) (half_len (running_sum ((\u03bb 0)) $0)))": 57, "(\u03bb lt (n_unique_suits $0) (half_len (running_sum ((\u03bb 3)) $0)))": 13, "(\u03bb lt (n_unique_suits $0) (half_len (running_sum ((\u03bb signum 2)) $0)))": 11, "(\u03bb lt (n_unique_suits $0) (half_len (running_sum ((\u03bb signum 0)) $0)))": 17, "(\u03bb lt (n_unique_suits $0) (half_len (running_sum ((\u03bb 1)) $0)))": 161, "(\u03bb lt (n_unique_suits $0) (half_len (running_sum ((\u03bb suit_to_int HEARTS)) $0)))": 27, "(\u03bb lt (n_unique_suits $0) (half_len (running_sum ((\u03bb 2)) $0)))": 27, "(\u03bb lt (n_unique_suits $0) (half_len (running_sum ((\u03bb 4)) $0)))": 8, "(\u03bb le (n_unique_suits (at (adjacent_pairs $0) 3)) (n_repeated_ranks (first_half $0)))": 8, "(\u03bb le (half_len (take (suit_to_int HEARTS) $0)) (n_repeated_ranks (first_half $0)))": 16, "(\u03bb le (- (n_repeated_suits $0) 2) (n_repeated_ranks (first_half $0)))": 28, "(\u03bb le (- (n_repeated_suits $0) 2) 0)": 20, "(\u03bb le (- (n_repeated_suits (reverse $0)) 2) 0)": 28, "(\u03bb le (- (n_repeated_suits (reverse $0)) 2) (n_repeated_suits $0))": 20, "(\u03bb le (- (n_repeated_suits $0) 2) (n_repeated_suits $0))": 8, "(\u03bb le (- (n_repeated_suits $0) 2) 1)": 10, "(\u03bb le (- (n_repeated_suits $0) 3) 1)": 32, "(\u03bb le (- (n_repeated_suits $0) 3) 3)": 40, "(\u03bb le (- (n_repeated_suits $0) 4) 3)": 12, "(\u03bb le (- (n_repeated_suits $0) 3) 4)": 10, "(\u03bb le (- (n_repeated_suits $0) 3) (- 5 4))": 4, "(\u03bb le (- (n_repeated_suits $0) 4) 4)": 22, "(\u03bb le (- (n_repeated_suits $0) 2) 4)": 9, "(\u03bb le (- (n_repeated_suits (head (adjacent_pairs (first_half $0)))) 2) 4)": 13, "(\u03bb le (- (n_repeated_suits (head (adjacent_pairs (first_half $0)))) 3) 4)": 10, "(\u03bb le (- (n_repeated_suits (second_half $0)) 3) 4)": 4, "(\u03bb le (- (n_repeated_suits (second_half $0)) 5) 4)": 17, "(\u03bb le (- (n_repeated_suits (second_half $0)) 5) 3)": 1, "(\u03bb le (- (n_repeated_suits (second_half $0)) 3) 3)": 63, "(\u03bb le (- (n_unique_colors $0) 3) 3)": 17, "(\u03bb le (- (n_unique_colors $0) 4) 3)": 24, "(\u03bb le (- (n_unique_colors $0) 4) 1)": 16, "(\u03bb le (- (n_unique_colors $0) 2) 1)": 26, "(\u03bb le (- (n_unique_colors $0) 3) 1)": 5, "(\u03bb le (- (n_unique_colors $0) 2) 3)": 5, "(\u03bb le (- (n_unique_colors $0) 2) 5)": 9, "(\u03bb le (- (n_unique_colors $0) 1) 5)": 3, "(\u03bb le (- (n_unique_colors $0) 1) 4)": 55, "(\u03bb le (- (n_unique_colors $0) 2) 4)": 28, "(\u03bb le (- (n_unique_colors $0) 1) 2)": 67, "(\u03bb le (- (n_unique_colors $0) 1) 3)": 4, "(\u03bb le (- (n_unique_colors $0) 4) 2)": 12, "(\u03bb le (- (n_unique_colors $0) 0) 3)": 26, "(\u03bb le (- (half_len $0) 0) 3)": 22, "(\u03bb le (- (half_len $0) 2) 3)": 78, "(\u03bb le (- (half_len $0) 4) 3)": 2, "(\u03bb le (- (half_len $0) 3) 3)": 16, "(\u03bb le (length (last (adjacent_pairs $0))) 3)": 5, "(\u03bb le (n_repeated_suits $0) 3)": 109, "(\u03bb le (n_repeated_suits $0) 5)": 55, "(\u03bb le (max_suit_count $0) 5)": 115, "(\u03bb le (max_suit_count (reverse $0)) 5)": 2, "(\u03bb le (min_rank $0) 5)": 415, "(\u03bb le (min_rank $0) 2)": 27, "(\u03bb le (min_rank $0) 4)": 206, "(\u03bb le (min_rank $0) 3)": 51, "(\u03bb le (n_repeated_suits $0) 2)": 32, "(\u03bb le (n_repeated_suits $0) 4)": 14, "(\u03bb le (n_repeated_suits $0) (suit_to_int CLUBS))": 15, "(\u03bb le (min_rank (unique $0)) 5)": 2, "(\u03bb ge (n_unique_ranks $0) 1)": 49, "(\u03bb ge (n_unique_ranks $0) 5)": 63, "(\u03bb ge (n_unique_ranks $0) 3)": 6, "(\u03bb ge (n_unique_ranks $0) 0)": 35, "(\u03bb ge (n_unique_ranks (head (adjacent_pairs $0))) 0)": 31, "(\u03bb ge (count_color $0 BLACK) 0)": 33, "(\u03bb ge (count_color $0 RED) 0)": 71, "(\u03bb ge (count_color $0 RED) 1)": 120, "(\u03bb ge (count_color $0 BLACK) 1)": 21, "(\u03bb ge (count_color $0 BLACK) (signum 4))": 7, "(\u03bb ge (n_unique_colors $0) 0)": 33, "(\u03bb ge (n_unique_colors $0) 2)": 20, "(\u03bb ge (n_unique_colors $0) (n_unique_suits $0))": 972, "(\u03bb ge 2 (n_unique_suits $0))": 30853, "(\u03bb ge 2 (n_unique_suits (reverse $0)))": 944, "(\u03bb ge 2 (n_unique_suits (second_half $0)))": 9, "(\u03bb ge 2 (n_unique_suits (sort_by_rank $0)))": 459, "(\u03bb ge 2 (n_unique_suits (sort_by_rank (sort_by_rank $0))))": 8, "(\u03bb ge 2 (n_unique_suits (unique $0)))": 927, "(\u03bb ge (mod 2 3) (n_unique_suits $0))": 120, "(\u03bb ge (mod 2 5) (n_unique_suits $0))": 111, "(\u03bb ge (mod 2 4) (n_unique_suits $0))": 316, "(\u03bb ge (suit_to_int CLUBS) (n_unique_suits $0))": 1937, "(\u03bb ge 2 (n_unique_suits (sort_by_rank (reverse $0))))": 11, "(\u03bb ge 2 (n_unique_suits (sort_by_rank (reverse (sort_by_rank $0)))))": 51, "(\u03bb has_color (second_half (sort_by_rank $0)) (head (unique (map ((\u03bb BLACK)) $0))))": 4, "(\u03bb has_color (second_half (sort_by_rank $0)) BLACK)": 7, "(\u03bb has_color (second_half $0) BLACK)": 77, "(\u03bb has_color (second_half $0) RED)": 28, "(\u03bb has_suit $0 HEARTS)": 2778, "(\u03bb has_suit $0 CLUBS)": 3205, "(\u03bb has_suit (sort_by_rank (take 5 $0)) CLUBS)": 7, "(\u03bb has_suit (sort_by_rank (take 5 $0)) HEARTS)": 21, "(\u03bb has_suit (sort_by_rank (first_half $0)) CLUBS)": 42, "(\u03bb has_suit (drop 4 $0) CLUBS)": 14, "(\u03bb has_suit (drop 4 $0) HEARTS)": 9, "(\u03bb has_suit (drop (signum 0) $0) CLUBS)": 2, "(\u03bb has_suit (first_half $0) CLUBS)": 337, "(\u03bb has_suit (second_half $0) CLUBS)": 54, "(\u03bb has_suit (second_half $0) HEARTS)": 40, "(\u03bb has_suit (sort_by_rank $0) CLUBS)": 45, "(\u03bb lt (n_unique_colors $0) 3)": 82, "(\u03bb lt (n_unique_colors $0) 4)": 62, "(\u03bb lt (n_unique_colors $0) 5)": 167, "(\u03bb lt (n_unique_colors (sort_by_rank $0)) 5)": 10, "(\u03bb lt (n_unique_colors (reverse $0)) 5)": 28, "(\u03bb lt (n_repeated_ranks $0) 4)": 49, "(\u03bb lt (n_repeated_ranks $0) 5)": 41, "(\u03bb le 0 (n_repeated_ranks $0))": 14, "(\u03bb le 0 (n_unique_ranks $0))": 76, "(\u03bb le (suit_to_int DIAMONDS) (n_unique_ranks $0))": 17, "(\u03bb le (suit_to_int SPADES) (n_unique_ranks $0))": 5, "(\u03bb le (suit_to_int HEARTS) (n_unique_ranks $0))": 28, "(\u03bb le 5 (n_unique_ranks $0))": 27, "(\u03bb le (signum 1) (n_unique_ranks $0))": 10, "(\u03bb le (signum 4) (n_unique_ranks $0))": 20, "(\u03bb le 0 (n_unique_ranks (second_half $0)))": 71, "(\u03bb le 0 (sum_ranks $0))": 26, "(\u03bb le 2 (sum_ranks $0))": 2, "(\u03bb le 3 (sum_ranks $0))": 7, "(\u03bb le 1 (sum_ranks $0))": 25, "(\u03bb le 1 (sum_ranks (head (adjacent_pairs $0))))": 16, "(\u03bb le (max_rank (sort_by_rank $0)) (sum_ranks (head (adjacent_pairs $0))))": 2, "(\u03bb le (max_rank (sort_by_rank $0)) (sum_ranks $0))": 3, "(\u03bb le (max_rank $0) (sum_ranks $0))": 3, "(\u03bb has_color (sort_by_rank $0) BLACK)": 108, "(\u03bb has_color (sort_by_rank $0) RED)": 43, "(\u03bb has_color (drop 0 $0) RED)": 35, "(\u03bb has_color (drop 2 $0) RED)": 16, "(\u03bb has_color (drop 2 $0) BLACK)": 22, "(\u03bb has_color (first_half $0) BLACK)": 34, "(\u03bb has_color (sort_by_rank (sort_by_rank $0)) RED)": 8, "(\u03bb ge (max_suit_count $0) 3)": 90, "(\u03bb ge (max_suit_count $0) (n_repeated_suits $0))": 7, "(\u03bb ge (max_suit_count $0) 0)": 17, "(\u03bb ge (n_unique_ranks (second_half $0)) 0)": 2, "(\u03bb ge (n_unique_ranks (sort_by_rank $0)) 0)": 1, "(\u03bb ge (n_unique_ranks $0) 4)": 33, "(\u03bb ge (n_unique_suits $0) 1)": 22, "(\u03bb ge (n_unique_suits $0) 2)": 207, "(\u03bb ge (n_unique_suits $0) (suit_to_int CLUBS))": 1, "(\u03bb ge (n_unique_suits $0) 0)": 61, "(\u03bb ge (rank_val (head $0)) 0)": 28, "(\u03bb ge (count_suit $0 SPADES) 0)": 60, "(\u03bb ge (count_suit $0 DIAMONDS) 0)": 39, "(\u03bb ge (count_suit $0 HEARTS) 0)": 60, "(\u03bb ge (count_suit $0 CLUBS) 0)": 41, "(\u03bb ge (half_len $0) 0)": 31, "(\u03bb has_suit (first_half $0) HEARTS)": 26, "(\u03bb has_suit (head (adjacent_pairs $0)) HEARTS)": 11, "(\u03bb has_suit (head (adjacent_pairs $0)) CLUBS)": 77, "(\u03bb ge (count_suit $0 CLUBS) 2)": 719, "(\u03bb ge (length $0) 2)": 23, "(\u03bb ge (length $0) 0)": 37, "(\u03bb ge (length $0) (suit_to_int DIAMONDS))": 11, "(\u03bb ge (mod (n_unique_suits (reverse $0)) 3) 2)": 142, "(\u03bb ge (mod (n_unique_suits (unique $0)) 3) 2)": 7, "(\u03bb ge (mod (n_unique_suits $0) 3) 2)": 57, "(\u03bb ge (mod (n_unique_suits $0) 3) (suit_to_int CLUBS))": 536, "(\u03bb ge (mod (n_unique_suits $0) 3) (n_unique_suits $0))": 191, "(\u03bb ge (suit_to_int CLUBS) (n_unique_suits (reverse $0)))": 32, "(\u03bb ge 2 (n_unique_suits (sort_by_rank (sort_by_rank (sort_by_rank $0)))))": 12, "(\u03bb ge (n_unique_colors $0) (n_unique_suits (reverse $0)))": 35, "(\u03bb ge 2 (n_unique_suits (reverse (unique $0))))": 36, "(\u03bb has_color (take (count_color $0 RED) (second_half $0)) (get_color (last $0)))": 8, "(\u03bb has_color (take (n_unique_ranks $0) (second_half $0)) (get_color (last $0)))": 1, "(\u03bb has_color (take (n_unique_ranks $0) (second_half $0)) RED)": 12, "(\u03bb has_color (unique (head (adjacent_pairs $0))) RED)": 5, "(\u03bb has_color (first_half $0) RED)": 5, "(\u03bb lt 2 (max_rank $0))": 94, "(\u03bb lt 0 (max_rank $0))": 24, "(\u03bb lt 5 (max_rank $0))": 21, "(\u03bb lt 3 (max_rank $0))": 13, "(\u03bb has_color (second_half (unique $0)) BLACK)": 25, "(\u03bb has_suit (sort_by_rank $0) HEARTS)": 45, "(\u03bb has_color $0 (get_color (head $0)))": 23, "(\u03bb has_color (reverse $0) RED)": 13, "(\u03bb has_color (reverse $0) BLACK)": 22, "(\u03bb eq $0 $0)": 517, "(\u03bb has_suit (unique $0) HEARTS)": 38, "(\u03bb has_suit (unique $0) CLUBS)": 24, "(\u03bb has_suit (drop 3 $0) HEARTS)": 12, "(\u03bb has_suit (reverse $0) CLUBS)": 32, "(\u03bb ge (rank_val (head $0)) 3)": 21, "(\u03bb ge (rank_val (last $0)) 2)": 13, "(\u03bb ge (rank_val (head $0)) (min_rank $0))": 4, "(\u03bb ge 5 (min_rank $0))": 98, "(\u03bb ge 4 (min_rank $0))": 228, "(\u03bb ge 5 (n_repeated_suits (sort_by_rank $0)))": 15, "(\u03bb ge 5 (n_repeated_suits $0))": 57, "(\u03bb ge 3 (n_repeated_suits $0))": 22, "(\u03bb ge 2 (n_repeated_suits $0))": 55, "(\u03bb ge 4 (n_repeated_suits $0))": 17, "(\u03bb ge 5 (n_repeated_ranks $0))": 183, "(\u03bb ge 2 (n_repeated_ranks $0))": 34, "(\u03bb ge 4 (n_repeated_ranks $0))": 31, "(\u03bb ge 3 (n_repeated_ranks $0))": 140, "(\u03bb ge (half_len $0) (n_repeated_ranks $0))": 1, "(\u03bb ge 1 (n_repeated_ranks $0))": 60, "(\u03bb ge (mod 5 3) (n_unique_suits $0))": 46, "(\u03bb ge (n_unique_colors $0) (n_unique_suits (unique $0)))": 75, "(\u03bb ge (suit_to_int CLUBS) (n_unique_suits (sort_by_rank $0)))": 8}, "first_passage": {"(\u03bb ge (count_suit (at (adjacent_pairs $0) 2) SPADES) 5)": 0, "(\u03bb ge (count_suit (at (adjacent_pairs $0) 5) SPADES) 5)": 4, "(\u03bb ge (count_suit (at (adjacent_pairs $0) 5) HEARTS) 5)": 30, "(\u03bb ge (count_suit (at (adjacent_pairs $0) 5) HEARTS) 0)": 52, "(\u03bb ge (count_suit (at (adjacent_pairs $0) 5) DIAMONDS) 0)": 59, "(\u03bb ge (sum_ranks (first_half $0)) 0)": 60, "(\u03bb ge (sum_ranks (first_half $0)) (signum 2))": 89, "(\u03bb ge (sum_ranks (unique $0)) (signum 2))": 125, "(\u03bb ge (sum_ranks (unique $0)) (signum 1))": 132, "(\u03bb ge (sum_ranks (unique (unique $0))) (signum 1))": 138, "(\u03bb ge (sum_ranks (unique (unique $0))) 5)": 146, "(\u03bb ge (sum_ranks (sort_by_rank (reverse $0))) 5)": 153, "(\u03bb ge (sum_ranks (sort_by_rank (reverse $0))) 2)": 163, "(\u03bb ge (rank_val (at $0 (- 3 1))) 2)": 166, "(\u03bb ge (rank_val (head $0)) 2)": 167, "(\u03bb ge (n_unique_ranks $0) 2)": 196, "(\u03bb ge (max_rank $0) 2)": 199, "(\u03bb ge (max_rank $0) 5)": 214, "(\u03bb ge (sum_ranks $0) 5)": 234, "(\u03bb ge (sum_ranks $0) 0)": 277, "(\u03bb ge (sum_ranks $0) 4)": 313, "(\u03bb ge (sum_ranks $0) 2)": 399, "(\u03bb ge (sum_ranks $0) 1)": 406, "(\u03bb ge (sum_ranks $0) (+ 4 1))": 417, "(\u03bb ge (sum_ranks $0) (+ 3 1))": 423, "(\u03bb ge (sum_ranks $0) 3)": 429, "(\u03bb has_color $0 RED)": 22, "(\u03bb has_color $0 BLACK)": 11, "(\u03bb has_color (unique $0) RED)": 310, "(\u03bb has_color (unique $0) BLACK)": 309, "(\u03bb lt (n_unique_suits $0) 3)": 1240, "(\u03bb lt (n_unique_suits (reverse $0)) 3)": 1953, "(\u03bb lt (n_unique_suits $0) 5)": 2422, "(\u03bb lt (n_unique_suits $0) 4)": 2487, "(\u03bb lt (n_unique_suits $0) (+ 1 2))": 3777, "(\u03bb lt (n_unique_suits (unique $0)) 3)": 6194, "(\u03bb lt (n_unique_suits (unique (sort_by_rank $0))) 3)": 6199, "(\u03bb lt (n_unique_suits (sort_by_rank $0)) 3)": 11208, "(\u03bb lt (n_unique_suits $0) (suit_to_int SPADES))": 11955, "(\u03bb lt (n_unique_suits (reverse (sort_by_rank $0))) 3)": 13602, "(\u03bb lt (n_unique_suits (sort_by_rank $0)) (half_len $0))": 14962, "(\u03bb lt (n_unique_suits $0) (half_len $0))": 14979, "(\u03bb lt (n_unique_suits $0) (half_len (running_sum ((\u03bb 0)) $0)))": 17405, "(\u03bb lt (n_unique_suits $0) (half_len (running_sum ((\u03bb 3)) $0)))": 17416, "(\u03bb lt (n_unique_suits $0) (half_len (running_sum ((\u03bb signum 2)) $0)))": 17429, "(\u03bb lt (n_unique_suits $0) (half_len (running_sum ((\u03bb signum 0)) $0)))": 17440, "(\u03bb lt (n_unique_suits $0) (half_len (running_sum ((\u03bb 1)) $0)))": 17457, "(\u03bb lt (n_unique_suits $0) (half_len (running_sum ((\u03bb suit_to_int HEARTS)) $0)))": 17522, "(\u03bb lt (n_unique_suits $0) (half_len (running_sum ((\u03bb 2)) $0)))": 17638, "(\u03bb lt (n_unique_suits $0) (half_len (running_sum ((\u03bb 4)) $0)))": 17665, "(\u03bb le (n_unique_suits (at (adjacent_pairs $0) 3)) (n_repeated_ranks (first_half $0)))": 0, "(\u03bb le (half_len (take (suit_to_int HEARTS) $0)) (n_repeated_ranks (first_half $0)))": 8, "(\u03bb le (- (n_repeated_suits $0) 2) (n_repeated_ranks (first_half $0)))": 24, "(\u03bb le (- (n_repeated_suits $0) 2) 0)": 52, "(\u03bb le (- (n_repeated_suits (reverse $0)) 2) 0)": 72, "(\u03bb le (- (n_repeated_suits (reverse $0)) 2) (n_repeated_suits $0))": 100, "(\u03bb le (- (n_repeated_suits $0) 2) (n_repeated_suits $0))": 120, "(\u03bb le (- (n_repeated_suits $0) 2) 1)": 128, "(\u03bb le (- (n_repeated_suits $0) 3) 1)": 138, "(\u03bb le (- (n_repeated_suits $0) 3) 3)": 170, "(\u03bb le (- (n_repeated_suits $0) 4) 3)": 185, "(\u03bb le (- (n_repeated_suits $0) 3) 4)": 222, "(\u03bb le (- (n_repeated_suits $0) 3) (- 5 4))": 223, "(\u03bb le (- (n_repeated_suits $0) 4) 4)": 236, "(\u03bb le (- (n_repeated_suits $0) 2) 4)": 258, "(\u03bb le (- (n_repeated_suits (head (adjacent_pairs (first_half $0)))) 2) 4)": 267, "(\u03bb le (- (n_repeated_suits (head (adjacent_pairs (first_half $0)))) 3) 4)": 280, "(\u03bb le (- (n_repeated_suits (second_half $0)) 3) 4)": 290, "(\u03bb le (- (n_repeated_suits (second_half $0)) 5) 4)": 294, "(\u03bb le (- (n_repeated_suits (second_half $0)) 5) 3)": 311, "(\u03bb le (- (n_repeated_suits (second_half $0)) 3) 3)": 312, "(\u03bb le (- (n_unique_colors $0) 3) 3)": 375, "(\u03bb le (- (n_unique_colors $0) 4) 3)": 379, "(\u03bb le (- (n_unique_colors $0) 4) 1)": 390, "(\u03bb le (- (n_unique_colors $0) 2) 1)": 406, "(\u03bb le (- (n_unique_colors $0) 3) 1)": 432, "(\u03bb le (- (n_unique_colors $0) 2) 3)": 450, "(\u03bb le (- (n_unique_colors $0) 2) 5)": 455, "(\u03bb le (- (n_unique_colors $0) 1) 5)": 464, "(\u03bb le (- (n_unique_colors $0) 1) 4)": 467, "(\u03bb le (- (n_unique_colors $0) 2) 4)": 484, "(\u03bb le (- (n_unique_colors $0) 1) 2)": 550, "(\u03bb le (- (n_unique_colors $0) 1) 3)": 617, "(\u03bb le (- (n_unique_colors $0) 4) 2)": 631, "(\u03bb le (- (n_unique_colors $0) 0) 3)": 646, "(\u03bb le (- (half_len $0) 0) 3)": 672, "(\u03bb le (- (half_len $0) 2) 3)": 678, "(\u03bb le (- (half_len $0) 4) 3)": 689, "(\u03bb le (- (half_len $0) 3) 3)": 691, "(\u03bb le (length (last (adjacent_pairs $0))) 3)": 790, "(\u03bb le (n_repeated_suits $0) 3)": 795, "(\u03bb le (n_repeated_suits $0) 5)": 885, "(\u03bb le (max_suit_count $0) 5)": 904, "(\u03bb le (max_suit_count (reverse $0)) 5)": 1019, "(\u03bb le (min_rank $0) 5)": 1021, "(\u03bb le (min_rank $0) 2)": 1054, "(\u03bb le (min_rank $0) 4)": 1081, "(\u03bb le (min_rank $0) 3)": 1335, "(\u03bb le (n_repeated_suits $0) 2)": 1405, "(\u03bb le (n_repeated_suits $0) 4)": 1453, "(\u03bb le (n_repeated_suits $0) (suit_to_int CLUBS))": 1458, "(\u03bb le (min_rank (unique $0)) 5)": 1650, "(\u03bb ge (n_unique_ranks $0) 1)": 1838, "(\u03bb ge (n_unique_ranks $0) 5)": 1877, "(\u03bb ge (n_unique_ranks $0) 3)": 1955, "(\u03bb ge (n_unique_ranks $0) 0)": 1961, "(\u03bb ge (n_unique_ranks (head (adjacent_pairs $0))) 0)": 1977, "(\u03bb ge (count_color $0 BLACK) 0)": 2008, "(\u03bb ge (count_color $0 RED) 0)": 2031, "(\u03bb ge (count_color $0 RED) 1)": 2079, "(\u03bb ge (count_color $0 BLACK) 1)": 2092, "(\u03bb ge (count_color $0 BLACK) (signum 4))": 2220, "(\u03bb ge (n_unique_colors $0) 0)": 2260, "(\u03bb ge (n_unique_colors $0) 2)": 2293, "(\u03bb ge (n_unique_colors $0) (n_unique_suits $0))": 2313, "(\u03bb ge 2 (n_unique_suits $0))": 2390, "(\u03bb ge 2 (n_unique_suits (reverse $0)))": 4348, "(\u03bb ge 2 (n_unique_suits (second_half $0)))": 5536, "(\u03bb ge 2 (n_unique_suits (sort_by_rank $0)))": 6062, "(\u03bb ge 2 (n_unique_suits (sort_by_rank (sort_by_rank $0))))": 6110, "(\u03bb ge 2 (n_unique_suits (unique $0)))": 7463, "(\u03bb ge (mod 2 3) (n_unique_suits $0))": 10098, "(\u03bb ge (mod 2 5) (n_unique_suits $0))": 10116, "(\u03bb ge (mod 2 4) (n_unique_suits $0))": 10180, "(\u03bb ge (suit_to_int CLUBS) (n_unique_suits $0))": 10121, "(\u03bb ge 2 (n_unique_suits (sort_by_rank (reverse $0))))": 15117, "(\u03bb ge 2 (n_unique_suits (sort_by_rank (reverse (sort_by_rank $0)))))": 15128, "(\u03bb has_color (second_half (sort_by_rank $0)) (head (unique (map ((\u03bb BLACK)) $0))))": 0, "(\u03bb has_color (second_half (sort_by_rank $0)) BLACK)": 4, "(\u03bb has_color (second_half $0) BLACK)": 42, "(\u03bb has_color (second_half $0) RED)": 78, "(\u03bb has_suit $0 HEARTS)": 474, "(\u03bb has_suit $0 CLUBS)": 525, "(\u03bb has_suit (sort_by_rank (take 5 $0)) CLUBS)": 613, "(\u03bb has_suit (sort_by_rank (take 5 $0)) HEARTS)": 617, "(\u03bb has_suit (sort_by_rank (first_half $0)) CLUBS)": 641, "(\u03bb has_suit (drop 4 $0) CLUBS)": 683, "(\u03bb has_suit (drop 4 $0) HEARTS)": 693, "(\u03bb has_suit (drop (signum 0) $0) CLUBS)": 706, "(\u03bb has_suit (first_half $0) CLUBS)": 879, "(\u03bb has_suit (second_half $0) CLUBS)": 1236, "(\u03bb has_suit (second_half $0) HEARTS)": 1248, "(\u03bb has_suit (sort_by_rank $0) CLUBS)": 1310, "(\u03bb lt (n_unique_colors $0) 3)": 1473, "(\u03bb lt (n_unique_colors $0) 4)": 1475, "(\u03bb lt (n_unique_colors $0) 5)": 1498, "(\u03bb lt (n_unique_colors (sort_by_rank $0)) 5)": 1611, "(\u03bb lt (n_unique_colors (reverse $0)) 5)": 1621, "(\u03bb lt (n_repeated_ranks $0) 4)": 1822, "(\u03bb lt (n_repeated_ranks $0) 5)": 1871, "(\u03bb le 0 (n_repeated_ranks $0))": 2679, "(\u03bb le 0 (n_unique_ranks $0))": 2693, "(\u03bb le (suit_to_int DIAMONDS) (n_unique_ranks $0))": 2717, "(\u03bb le (suit_to_int SPADES) (n_unique_ranks $0))": 2730, "(\u03bb le (suit_to_int HEARTS) (n_unique_ranks $0))": 2739, "(\u03bb le 5 (n_unique_ranks $0))": 2767, "(\u03bb le (signum 1) (n_unique_ranks $0))": 2794, "(\u03bb le (signum 4) (n_unique_ranks $0))": 2804, "(\u03bb le 0 (n_unique_ranks (second_half $0)))": 2872, "(\u03bb le 0 (sum_ranks $0))": 2947, "(\u03bb le 2 (sum_ranks $0))": 2973, "(\u03bb le 3 (sum_ranks $0))": 2975, "(\u03bb le 1 (sum_ranks $0))": 2982, "(\u03bb le 1 (sum_ranks (head (adjacent_pairs $0))))": 2986, "(\u03bb le (max_rank (sort_by_rank $0)) (sum_ranks (head (adjacent_pairs $0))))": 3002, "(\u03bb le (max_rank (sort_by_rank $0)) (sum_ranks $0))": 3004, "(\u03bb le (max_rank $0) (sum_ranks $0))": 3007, "(\u03bb has_color (sort_by_rank $0) BLACK)": 1472, "(\u03bb has_color (sort_by_rank $0) RED)": 1475, "(\u03bb has_color (drop 0 $0) RED)": 3580, "(\u03bb has_color (drop 2 $0) RED)": 3615, "(\u03bb has_color (drop 2 $0) BLACK)": 3620, "(\u03bb has_color (first_half $0) BLACK)": 327, "(\u03bb has_color (sort_by_rank (sort_by_rank $0)) RED)": 3880, "(\u03bb ge (max_suit_count $0) 3)": 5280, "(\u03bb ge (max_suit_count $0) (n_repeated_suits $0))": 5370, "(\u03bb ge (max_suit_count $0) 0)": 5377, "(\u03bb ge (n_unique_ranks (second_half $0)) 0)": 5395, "(\u03bb ge (n_unique_ranks (sort_by_rank $0)) 0)": 5397, "(\u03bb ge (n_unique_ranks $0) 4)": 5419, "(\u03bb ge (n_unique_suits $0) 1)": 5476, "(\u03bb ge (n_unique_suits $0) 2)": 5484, "(\u03bb ge (n_unique_suits $0) (suit_to_int CLUBS))": 5703, "(\u03bb ge (n_unique_suits $0) 0)": 5706, "(\u03bb ge (rank_val (head $0)) 0)": 5767, "(\u03bb ge (count_suit $0 SPADES) 0)": 5820, "(\u03bb ge (count_suit $0 DIAMONDS) 0)": 5844, "(\u03bb ge (count_suit $0 HEARTS) 0)": 5857, "(\u03bb ge (count_suit $0 CLUBS) 0)": 5901, "(\u03bb ge (half_len $0) 0)": 6020, "(\u03bb has_suit (first_half $0) HEARTS)": 6346, "(\u03bb has_suit (head (adjacent_pairs $0)) HEARTS)": 7497, "(\u03bb has_suit (head (adjacent_pairs $0)) CLUBS)": 7508, "(\u03bb ge (count_suit $0 CLUBS) 2)": 8398, "(\u03bb ge (length $0) 2)": 9117, "(\u03bb ge (length $0) 0)": 9136, "(\u03bb ge (length $0) (suit_to_int DIAMONDS))": 9165, "(\u03bb ge (mod (n_unique_suits (reverse $0)) 3) 2)": 9188, "(\u03bb ge (mod (n_unique_suits (unique $0)) 3) 2)": 9330, "(\u03bb ge (mod (n_unique_suits $0) 3) 2)": 9337, "(\u03bb ge (mod (n_unique_suits $0) 3) (suit_to_int CLUBS))": 9394, "(\u03bb ge (mod (n_unique_suits $0) 3) (n_unique_suits $0))": 9930, "(\u03bb ge (suit_to_int CLUBS) (n_unique_suits (reverse $0)))": 11942, "(\u03bb ge 2 (n_unique_suits (sort_by_rank (sort_by_rank (sort_by_rank $0)))))": 13298, "(\u03bb ge (n_unique_colors $0) (n_unique_suits (reverse $0)))": 18273, "(\u03bb ge 2 (n_unique_suits (reverse (unique $0))))": 19437, "(\u03bb has_color (take (count_color $0 RED) (second_half $0)) (get_color (last $0)))": 0, "(\u03bb has_color (take (n_unique_ranks $0) (second_half $0)) (get_color (last $0)))": 8, "(\u03bb has_color (take (n_unique_ranks $0) (second_half $0)) RED)": 9, "(\u03bb has_color (unique (head (adjacent_pairs $0))) RED)": 21, "(\u03bb has_color (first_half $0) RED)": 322, "(\u03bb lt 2 (max_rank $0))": 480, "(\u03bb lt 0 (max_rank $0))": 526, "(\u03bb lt 5 (max_rank $0))": 544, "(\u03bb lt 3 (max_rank $0))": 586, "(\u03bb has_color (second_half (unique $0)) BLACK)": 3371, "(\u03bb has_suit (sort_by_rank $0) HEARTS)": 4623, "(\u03bb has_color $0 (get_color (head $0)))": 5077, "(\u03bb has_color (reverse $0) RED)": 5475, "(\u03bb has_color (reverse $0) BLACK)": 5488, "(\u03bb eq $0 $0)": 5692, "(\u03bb has_suit (unique $0) HEARTS)": 6505, "(\u03bb has_suit (unique $0) CLUBS)": 7046, "(\u03bb has_suit (drop 3 $0) HEARTS)": 7791, "(\u03bb has_suit (reverse $0) CLUBS)": 8020, "(\u03bb ge (rank_val (head $0)) 3)": 9456, "(\u03bb ge (rank_val (last $0)) 2)": 9522, "(\u03bb ge (rank_val (head $0)) (min_rank $0))": 9662, "(\u03bb ge 5 (min_rank $0))": 9666, "(\u03bb ge 4 (min_rank $0))": 9703, "(\u03bb ge 5 (n_repeated_suits (sort_by_rank $0)))": 9992, "(\u03bb ge 5 (n_repeated_suits $0))": 10007, "(\u03bb ge 3 (n_repeated_suits $0))": 10023, "(\u03bb ge 2 (n_repeated_suits $0))": 10045, "(\u03bb ge 4 (n_repeated_suits $0))": 10100, "(\u03bb ge 5 (n_repeated_ranks $0))": 10158, "(\u03bb ge 2 (n_repeated_ranks $0))": 10222, "(\u03bb ge 4 (n_repeated_ranks $0))": 10224, "(\u03bb ge 3 (n_repeated_ranks $0))": 10284, "(\u03bb ge (half_len $0) (n_repeated_ranks $0))": 10389, "(\u03bb ge 1 (n_repeated_ranks $0))": 10457, "(\u03bb ge (mod 5 3) (n_unique_suits $0))": 15394, "(\u03bb ge (n_unique_colors $0) (n_unique_suits (unique $0)))": 16898, "(\u03bb ge (suit_to_int CLUBS) (n_unique_suits (sort_by_rank $0)))": 17167}, "ext_fractions": {"(\u03bb ge (count_suit (at (adjacent_pairs $0) 2) SPADES) 5)": 0.0, "(\u03bb ge (count_suit (at (adjacent_pairs $0) 5) SPADES) 5)": 0.0, "(\u03bb ge (count_suit (at (adjacent_pairs $0) 5) HEARTS) 5)": 0.0, "(\u03bb ge (count_suit (at (adjacent_pairs $0) 5) HEARTS) 0)": 0.0, "(\u03bb ge (count_suit (at (adjacent_pairs $0) 5) DIAMONDS) 0)": 0.0, "(\u03bb ge (sum_ranks (first_half $0)) 0)": 1.0, "(\u03bb ge (sum_ranks (first_half $0)) (signum 2))": 1.0, "(\u03bb ge (sum_ranks (unique $0)) (signum 2))": 1.0, "(\u03bb ge (sum_ranks (unique $0)) (signum 1))": 1.0, "(\u03bb ge (sum_ranks (unique (unique $0))) (signum 1))": 1.0, "(\u03bb ge (sum_ranks (unique (unique $0))) 5)": 1.0, "(\u03bb ge (sum_ranks (sort_by_rank (reverse $0))) 5)": 1.0, "(\u03bb ge (sum_ranks (sort_by_rank (reverse $0))) 2)": 1.0, "(\u03bb ge (rank_val (at $0 (- 3 1))) 2)": 1.0, "(\u03bb ge (rank_val (head $0)) 2)": 1.0, "(\u03bb ge (n_unique_ranks $0) 2)": 1.0, "(\u03bb ge (max_rank $0) 2)": 1.0, "(\u03bb ge (max_rank $0) 5)": 1.0, "(\u03bb ge (sum_ranks $0) 5)": 1.0, "(\u03bb ge (sum_ranks $0) 0)": 1.0, "(\u03bb ge (sum_ranks $0) 4)": 1.0, "(\u03bb ge (sum_ranks $0) 2)": 1.0, "(\u03bb ge (sum_ranks $0) 1)": 1.0, "(\u03bb ge (sum_ranks $0) (+ 4 1))": 1.0, "(\u03bb ge (sum_ranks $0) (+ 3 1))": 1.0, "(\u03bb ge (sum_ranks $0) 3)": 1.0, "(\u03bb has_color $0 RED)": 0.989, "(\u03bb has_color $0 BLACK)": 0.989, "(\u03bb has_color (unique $0) RED)": 0.989, "(\u03bb has_color (unique $0) BLACK)": 0.989, "(\u03bb lt (n_unique_suits $0) 3)": 0.0705, "(\u03bb lt (n_unique_suits (reverse $0)) 3)": 0.0705, "(\u03bb lt (n_unique_suits $0) 5)": 1.0, "(\u03bb lt (n_unique_suits $0) 4)": 0.573, "(\u03bb lt (n_unique_suits $0) (+ 1 2))": 0.0705, "(\u03bb lt (n_unique_suits (unique $0)) 3)": 0.0705, "(\u03bb lt (n_unique_suits (unique (sort_by_rank $0))) 3)": 0.0705, "(\u03bb lt (n_unique_suits (sort_by_rank $0)) 3)": 0.0705, "(\u03bb lt (n_unique_suits $0) (suit_to_int SPADES))": 0.0705, "(\u03bb lt (n_unique_suits (reverse (sort_by_rank $0))) 3)": 0.0705, "(\u03bb lt (n_unique_suits (sort_by_rank $0)) (half_len $0))": 0.0705, "(\u03bb lt (n_unique_suits $0) (half_len $0))": 0.0705, "(\u03bb lt (n_unique_suits $0) (half_len (running_sum ((\u03bb 0)) $0)))": 0.0705, "(\u03bb lt (n_unique_suits $0) (half_len (running_sum ((\u03bb 3)) $0)))": 0.0705, "(\u03bb lt (n_unique_suits $0) (half_len (running_sum ((\u03bb signum 2)) $0)))": 0.0705, "(\u03bb lt (n_unique_suits $0) (half_len (running_sum ((\u03bb signum 0)) $0)))": 0.0705, "(\u03bb lt (n_unique_suits $0) (half_len (running_sum ((\u03bb 1)) $0)))": 0.0705, "(\u03bb lt (n_unique_suits $0) (half_len (running_sum ((\u03bb suit_to_int HEARTS)) $0)))": 0.0705, "(\u03bb lt (n_unique_suits $0) (half_len (running_sum ((\u03bb 2)) $0)))": 0.0705, "(\u03bb lt (n_unique_suits $0) (half_len (running_sum ((\u03bb 4)) $0)))": 0.0705, "(\u03bb le (n_unique_suits (at (adjacent_pairs $0) 3)) (n_repeated_ranks (first_half $0)))": 0.0385, "(\u03bb le (half_len (take (suit_to_int HEARTS) $0)) (n_repeated_ranks (first_half $0)))": 1.0, "(\u03bb le (- (n_repeated_suits $0) 2) (n_repeated_ranks (first_half $0)))": 0.9185, "(\u03bb le (- (n_repeated_suits $0) 2) 0)": 0.9055, "(\u03bb le (- (n_repeated_suits (reverse $0)) 2) 0)": 0.9055, "(\u03bb le (- (n_repeated_suits (reverse $0)) 2) (n_repeated_suits $0))": 1.0, "(\u03bb le (- (n_repeated_suits $0) 2) (n_repeated_suits $0))": 1.0, "(\u03bb le (- (n_repeated_suits $0) 2) 1)": 1.0, "(\u03bb le (- (n_repeated_suits $0) 3) 1)": 1.0, "(\u03bb le (- (n_repeated_suits $0) 3) 3)": 1.0, "(\u03bb le (- (n_repeated_suits $0) 4) 3)": 1.0, "(\u03bb le (- (n_repeated_suits $0) 3) 4)": 1.0, "(\u03bb le (- (n_repeated_suits $0) 3) (- 5 4))": 1.0, "(\u03bb le (- (n_repeated_suits $0) 4) 4)": 1.0, "(\u03bb le (- (n_repeated_suits $0) 2) 4)": 1.0, "(\u03bb le (- (n_repeated_suits (head (adjacent_pairs (first_half $0)))) 2) 4)": 1.0, "(\u03bb le (- (n_repeated_suits (head (adjacent_pairs (first_half $0)))) 3) 4)": 1.0, "(\u03bb le (- (n_repeated_suits (second_half $0)) 3) 4)": 1.0, "(\u03bb le (- (n_repeated_suits (second_half $0)) 5) 4)": 1.0, "(\u03bb le (- (n_repeated_suits (second_half $0)) 5) 3)": 1.0, "(\u03bb le (- (n_repeated_suits (second_half $0)) 3) 3)": 1.0, "(\u03bb le (- (n_unique_colors $0) 3) 3)": 1.0, "(\u03bb le (- (n_unique_colors $0) 4) 3)": 1.0, "(\u03bb le (- (n_unique_colors $0) 4) 1)": 1.0, "(\u03bb le (- (n_unique_colors $0) 2) 1)": 1.0, "(\u03bb le (- (n_unique_colors $0) 3) 1)": 1.0, "(\u03bb le (- (n_unique_colors $0) 2) 3)": 1.0, "(\u03bb le (- (n_unique_colors $0) 2) 5)": 1.0, "(\u03bb le (- (n_unique_colors $0) 1) 5)": 1.0, "(\u03bb le (- (n_unique_colors $0) 1) 4)": 1.0, "(\u03bb le (- (n_unique_colors $0) 2) 4)": 1.0, "(\u03bb le (- (n_unique_colors $0) 1) 2)": 1.0, "(\u03bb le (- (n_unique_colors $0) 1) 3)": 1.0, "(\u03bb le (- (n_unique_colors $0) 4) 2)": 1.0, "(\u03bb le (- (n_unique_colors $0) 0) 3)": 1.0, "(\u03bb le (- (half_len $0) 0) 3)": 1.0, "(\u03bb le (- (half_len $0) 2) 3)": 1.0, "(\u03bb le (- (half_len $0) 4) 3)": 1.0, "(\u03bb le (- (half_len $0) 3) 3)": 1.0, "(\u03bb le (length (last (adjacent_pairs $0))) 3)": 1.0, "(\u03bb le (n_repeated_suits $0) 3)": 1.0, "(\u03bb le (n_repeated_suits $0) 5)": 1.0, "(\u03bb le (max_suit_count $0) 5)": 1.0, "(\u03bb le (max_suit_count (reverse $0)) 5)": 1.0, "(\u03bb le (min_rank $0) 5)": 0.9015, "(\u03bb le (min_rank $0) 2)": 0.378, "(\u03bb le (min_rank $0) 4)": 0.802, "(\u03bb le (min_rank $0) 3)": 0.627, "(\u03bb le (n_repeated_suits $0) 2)": 0.9055, "(\u03bb le (n_repeated_suits $0) 4)": 1.0, "(\u03bb le (n_repeated_suits $0) (suit_to_int CLUBS))": 0.9055, "(\u03bb le (min_rank (unique $0)) 5)": 0.9015, "(\u03bb ge (n_unique_ranks $0) 1)": 1.0, "(\u03bb ge (n_unique_ranks $0) 5)": 0.8305, "(\u03bb ge (n_unique_ranks $0) 3)": 1.0, "(\u03bb ge (n_unique_ranks $0) 0)": 1.0, "(\u03bb ge (n_unique_ranks (head (adjacent_pairs $0))) 0)": 1.0, "(\u03bb ge (count_color $0 BLACK) 0)": 1.0, "(\u03bb ge (count_color $0 RED) 0)": 1.0, "(\u03bb ge (count_color $0 RED) 1)": 0.989, "(\u03bb ge (count_color $0 BLACK) 1)": 0.989, "(\u03bb ge (count_color $0 BLACK) (signum 4))": 0.989, "(\u03bb ge (n_unique_colors $0) 0)": 1.0, "(\u03bb ge (n_unique_colors $0) 2)": 0.978, "(\u03bb ge (n_unique_colors $0) (n_unique_suits $0))": 0.04850000000000001, "(\u03bb ge 2 (n_unique_suits $0))": 0.0705, "(\u03bb ge 2 (n_unique_suits (reverse $0)))": 0.0705, "(\u03bb ge 2 (n_unique_suits (second_half $0)))": 0.611, "(\u03bb ge 2 (n_unique_suits (sort_by_rank $0)))": 0.0705, "(\u03bb ge 2 (n_unique_suits (sort_by_rank (sort_by_rank $0))))": 0.0705, "(\u03bb ge 2 (n_unique_suits (unique $0)))": 0.0705, "(\u03bb ge (mod 2 3) (n_unique_suits $0))": 0.0705, "(\u03bb ge (mod 2 5) (n_unique_suits $0))": 0.0705, "(\u03bb ge (mod 2 4) (n_unique_suits $0))": 0.0705, "(\u03bb ge (suit_to_int CLUBS) (n_unique_suits $0))": 0.0705, "(\u03bb ge 2 (n_unique_suits (sort_by_rank (reverse $0))))": 0.0705, "(\u03bb ge 2 (n_unique_suits (sort_by_rank (reverse (sort_by_rank $0)))))": 0.0705, "(\u03bb has_color (second_half (sort_by_rank $0)) (head (unique (map ((\u03bb BLACK)) $0))))": 0.8985, "(\u03bb has_color (second_half (sort_by_rank $0)) BLACK)": 0.8985, "(\u03bb has_color (second_half $0) BLACK)": 0.883, "(\u03bb has_color (second_half $0) RED)": 0.88, "(\u03bb has_suit $0 HEARTS)": 0.8525, "(\u03bb has_suit $0 CLUBS)": 0.8315, "(\u03bb has_suit (sort_by_rank (take 5 $0)) CLUBS)": 0.7645, "(\u03bb has_suit (sort_by_rank (take 5 $0)) HEARTS)": 0.792, "(\u03bb has_suit (sort_by_rank (first_half $0)) CLUBS)": 0.5735, "(\u03bb has_suit (drop 4 $0) CLUBS)": 0.426, "(\u03bb has_suit (drop 4 $0) HEARTS)": 0.445, "(\u03bb has_suit (drop (signum 0) $0) CLUBS)": 0.8315, "(\u03bb has_suit (first_half $0) CLUBS)": 0.5735, "(\u03bb has_suit (second_half $0) CLUBS)": 0.574, "(\u03bb has_suit (second_half $0) HEARTS)": 0.586, "(\u03bb has_suit (sort_by_rank $0) CLUBS)": 0.8315, "(\u03bb lt (n_unique_colors $0) 3)": 1.0, "(\u03bb lt (n_unique_colors $0) 4)": 1.0, "(\u03bb lt (n_unique_colors $0) 5)": 1.0, "(\u03bb lt (n_unique_colors (sort_by_rank $0)) 5)": 1.0, "(\u03bb lt (n_unique_colors (reverse $0)) 5)": 1.0, "(\u03bb lt (n_repeated_ranks $0) 4)": 1.0, "(\u03bb lt (n_repeated_ranks $0) 5)": 1.0, "(\u03bb le 0 (n_repeated_ranks $0))": 1.0, "(\u03bb le 0 (n_unique_ranks $0))": 1.0, "(\u03bb le (suit_to_int DIAMONDS) (n_unique_ranks $0))": 0.991, "(\u03bb le (suit_to_int SPADES) (n_unique_ranks $0))": 1.0, "(\u03bb le (suit_to_int HEARTS) (n_unique_ranks $0))": 1.0, "(\u03bb le 5 (n_unique_ranks $0))": 0.8305, "(\u03bb le (signum 1) (n_unique_ranks $0))": 1.0, "(\u03bb le (signum 4) (n_unique_ranks $0))": 1.0, "(\u03bb le 0 (n_unique_ranks (second_half $0)))": 1.0, "(\u03bb le 0 (sum_ranks $0))": 1.0, "(\u03bb le 2 (sum_ranks $0))": 1.0, "(\u03bb le 3 (sum_ranks $0))": 1.0, "(\u03bb le 1 (sum_ranks $0))": 1.0, "(\u03bb le 1 (sum_ranks (head (adjacent_pairs $0))))": 1.0, "(\u03bb le (max_rank (sort_by_rank $0)) (sum_ranks (head (adjacent_pairs $0))))": 0.7605, "(\u03bb le (max_rank (sort_by_rank $0)) (sum_ranks $0))": 1.0, "(\u03bb le (max_rank $0) (sum_ranks $0))": 1.0, "(\u03bb has_color (sort_by_rank $0) BLACK)": 0.989, "(\u03bb has_color (sort_by_rank $0) RED)": 0.989, "(\u03bb has_color (drop 0 $0) RED)": 0.989, "(\u03bb has_color (drop 2 $0) RED)": 0.944, "(\u03bb has_color (drop 2 $0) BLACK)": 0.951, "(\u03bb has_color (first_half $0) BLACK)": 0.889, "(\u03bb has_color (sort_by_rank (sort_by_rank $0)) RED)": 0.989, "(\u03bb ge (max_suit_count $0) 3)": 0.617, "(\u03bb ge (max_suit_count $0) (n_repeated_suits $0))": 0.9055, "(\u03bb ge (max_suit_count $0) 0)": 1.0, "(\u03bb ge (n_unique_ranks (second_half $0)) 0)": 1.0, "(\u03bb ge (n_unique_ranks (sort_by_rank $0)) 0)": 1.0, "(\u03bb ge (n_unique_ranks $0) 4)": 0.991, "(\u03bb ge (n_unique_suits $0) 1)": 1.0, "(\u03bb ge (n_unique_suits $0) 2)": 1.0, "(\u03bb ge (n_unique_suits $0) (suit_to_int CLUBS))": 1.0, "(\u03bb ge (n_unique_suits $0) 0)": 1.0, "(\u03bb ge (rank_val (head $0)) 0)": 1.0, "(\u03bb ge (count_suit $0 SPADES) 0)": 1.0, "(\u03bb ge (count_suit $0 DIAMONDS) 0)": 1.0, "(\u03bb ge (count_suit $0 HEARTS) 0)": 1.0, "(\u03bb ge (count_suit $0 CLUBS) 0)": 1.0, "(\u03bb ge (half_len $0) 0)": 1.0, "(\u03bb has_suit (first_half $0) HEARTS)": 0.589, "(\u03bb has_suit (head (adjacent_pairs $0)) HEARTS)": 0.4405, "(\u03bb has_suit (head (adjacent_pairs $0)) CLUBS)": 0.426, "(\u03bb ge (count_suit $0 CLUBS) 2)": 0.446, "(\u03bb ge (length $0) 2)": 1.0, "(\u03bb ge (length $0) 0)": 1.0, "(\u03bb ge (length $0) (suit_to_int DIAMONDS))": 1.0, "(\u03bb ge (mod (n_unique_suits (reverse $0)) 3) 2)": 0.0705, "(\u03bb ge (mod (n_unique_suits (unique $0)) 3) 2)": 0.0705, "(\u03bb ge (mod (n_unique_suits $0) 3) 2)": 0.0705, "(\u03bb ge (mod (n_unique_suits $0) 3) (suit_to_int CLUBS))": 0.0705, "(\u03bb ge (mod (n_unique_suits $0) 3) (n_unique_suits $0))": 0.0705, "(\u03bb ge (suit_to_int CLUBS) (n_unique_suits (reverse $0)))": 0.0705, "(\u03bb ge 2 (n_unique_suits (sort_by_rank (sort_by_rank (sort_by_rank $0)))))": 0.0705, "(\u03bb ge (n_unique_colors $0) (n_unique_suits (reverse $0)))": 0.0485, "(\u03bb ge 2 (n_unique_suits (reverse (unique $0))))": 0.0705, "(\u03bb has_color (take (count_color $0 RED) (second_half $0)) (get_color (last $0)))": 0.897, "(\u03bb has_color (take (n_unique_ranks $0) (second_half $0)) (get_color (last $0)))": 1.0, "(\u03bb has_color (take (n_unique_ranks $0) (second_half $0)) RED)": 0.88, "(\u03bb has_color (unique (head (adjacent_pairs $0))) RED)": 0.7465, "(\u03bb has_color (first_half $0) RED)": 0.8805, "(\u03bb lt 2 (max_rank $0))": 1.0, "(\u03bb lt 0 (max_rank $0))": 1.0, "(\u03bb lt 5 (max_rank $0))": 1.0, "(\u03bb lt 3 (max_rank $0))": 1.0, "(\u03bb has_color (second_half (unique $0)) BLACK)": 0.883, "(\u03bb has_suit (sort_by_rank $0) HEARTS)": 0.8525, "(\u03bb has_color $0 (get_color (head $0)))": 1.0, "(\u03bb has_color (reverse $0) RED)": 0.989, "(\u03bb has_color (reverse $0) BLACK)": 0.989, "(\u03bb eq $0 $0)": 1.0, "(\u03bb has_suit (unique $0) HEARTS)": 0.8525, "(\u03bb has_suit (unique $0) CLUBS)": 0.8315, "(\u03bb has_suit (drop 3 $0) HEARTS)": 0.586, "(\u03bb has_suit (reverse $0) CLUBS)": 0.8315, "(\u03bb ge (rank_val (head $0)) 3)": 0.9225, "(\u03bb ge (rank_val (last $0)) 2)": 1.0, "(\u03bb ge (rank_val (head $0)) (min_rank $0))": 1.0, "(\u03bb ge 5 (min_rank $0))": 0.9015, "(\u03bb ge 4 (min_rank $0))": 0.802, "(\u03bb ge 5 (n_repeated_suits (sort_by_rank $0)))": 1.0, "(\u03bb ge 5 (n_repeated_suits $0))": 1.0, "(\u03bb ge 3 (n_repeated_suits $0))": 1.0, "(\u03bb ge 2 (n_repeated_suits $0))": 0.9055, "(\u03bb ge 4 (n_repeated_suits $0))": 1.0, "(\u03bb ge 5 (n_repeated_ranks $0))": 1.0, "(\u03bb ge 2 (n_repeated_ranks $0))": 0.9955, "(\u03bb ge 4 (n_repeated_ranks $0))": 1.0, "(\u03bb ge 3 (n_repeated_ranks $0))": 1.0, "(\u03bb ge (half_len $0) (n_repeated_ranks $0))": 1.0, "(\u03bb ge 1 (n_repeated_ranks $0))": 0.871, "(\u03bb ge (mod 5 3) (n_unique_suits $0))": 0.0705, "(\u03bb ge (n_unique_colors $0) (n_unique_suits (unique $0)))": 0.0485, "(\u03bb ge (suit_to_int CLUBS) (n_unique_suits (sort_by_rank $0)))": 0.0705}}